Workbook
Name RawQQC_: #REF!
Name RawQQC_: #REF!
Name RawQR_: #REF!
Name RawQR_: #REF!
Name RawQRC_: #REF!
Name RawQRC_: #REF!
Name U_RR: #REF!
Name U_RR: #REF!
Name Unit_RR: Report!$C$3
Name Unit_RR: #REF!

Sheet ForecastA(ctrlv)
Y17: Sales &COGS | AA17: Foreign Exchange I&E | AC17: Non-op. I&E | AE17: Events | BE17: (*) 첫 추정연도 분기배분
C18: ForecastA | D18: ForecastA | Y18: SG&A | AA18: Non-current assets | AC18: NI &Compre. Income | AE18: Dividend | BE18: ForecastQ
Y19: Other op. I&E | AA19: Current assets | AC19: Shareholders' Equity
X20: History | Y20: Interest I&E | AA20: Debt & Liabilities | AC20: Shares &Prices | AE20: Cash flow statement | BF20: Quarter | BJ20: Annual
B21: Period_CY_ | J21: 2000.12 | K21: 2001.12 | L21: 2002.12 | M21: 2003.12 | N21: 2004.12 | O21: 2005.12 | P21: 2006.12 | Q21: 2007.12 | R21: 2008.12 | S21: 2009.12 | T21: 2010.12 | U21: 2011.12 | V21: 2012.12 | W21: 2013.12 | X21: 2014.12 | Y21: 2015.12 | Z21: 2016.12 | AA21: 2017.12 | AB21: 2018.12 | AC21: 2019.12 | AD21: 2020.12 | AE21: 2021.12 | AF21: 2022.12 | AG21: 2023.12 | AH21: 2024.12 | AI21: 2025.12 | AJ21: 2026.12 | AK21: 2027.12 | AL21: 2028.12 | AM21: 2029.12 | AN21: 2030.12 | AO21: 2031.12 | AP21: 2032.12 | AQ21: 2033.12 | AR21: 2034.12 | AS21: 2035.12 | BD21: Period_CY_ | BF21: 2025.03 | BG21: 2025.06 | BH21: 2025.09 | BI21: 2025.12 | BJ21: 2025.12
B22: Period_FY_ | J22: 2000A | K22: 2001A | L22: 2002A | M22: 2003A | N22: 2004A | O22: 2005A | P22: 2006A | Q22: 2007A | R22: 2008A | S22: 2009A | T22: 2010A | U22: 2011A | V22: 2012A | W22: 2013A | X22: 2014A | Y22: 2015A | Z22: 2016A | AA22: 2017A | AB22: 2018A | AC22: 2019A | AD22: 2020A | AE22: 2021A | AF22: 2022A | AG22: 2023A | AH22: 2024A | AI22: 2025F | AJ22: 2026F | AK22: 2027F | AL22: 2028F | AM22: 2029F | AN22: 2030F | AO22: 2031F | AP22: 2032F | AQ22: 2033F | AR22: 2034F | AS22: 2035F | BD22: Period_FY_ | BF22: 2025_1F | BG22: 2025_2F | BH22: 2025_3F | BI22: 2025_4F | BJ22: 2025F
C24: Balance_BS : Asset - (Liability + Equity) | D24: BS: A-(L+E) | Z24: 0 | AA24: 0 | AB24: 0 | AC24: 0 | AD24: 0 | AE24: 0 | AF24: 0 | AG24: 0 | AH24: 0 | AI24: -6519.7335 | AJ24: -9417.1389 | AK24: -14913.418 | AL24: -24710.818 | AM24: -41483.768 | AN24: -69443.508 | AO24: -115223.96 | AP24: -189273.01 | AQ24: -308038.45 | AR24: -497402.88 | AS24: -798081.52 | AT24: FALSE | AX24: 필수입력
C25: Balance_CF : Cash(BS) - Cash(CF) | D25: CF: Cash(BS) - Cash(CF) | Z25: 0 | AA25: 0 | AB25: 0 | AC25: 0 | AD25: 0 | AE25: 0 | AF25: 0 | AG25: 0 | AH25: 0 | AI25: -6753.8315 | AJ25: -9885.3349 | AK25: -15615.712 | AL25: -25647.21 | AM25: -42654.258 | AN25: -70848.096 | AO25: -116862.65 | AP25: -191145.79 | AQ25: -310145.33 | AR25: -499743.86 | AS25: -800656.6 | AT25: FALSE | AX25: 선택입력
A28: Sales & COGS | BC28: Sales & COGS
B30: 200000 | C30: 매출액 | D30: Sales | E30: 1 | J30: 6392.2461 | K30: 6353.3612 | L30: 5478.9981 | M30: 5348.3267 | N30: 4854.0952 | O30: 4547.182 | P30: 5449.8714 | Q30: 6076.052 | R30: 8036.4935 | S30: 10390.595 | T30: 11217.013 | U30: 11920.167 | V30: 13324.821 | W30: 13852.042 | X30: 17276.48 | Y30: 19233.18 | Z30: 18825.015 | AA30: 16887.09 | AB30: 16730.894 | AC30: 17278.792 | AD30: 16970.859 | AE30: 18065.534 | AF30: 21239.082 | AG30: 29651.357 | AH30: 32670.268 | AI30: 35996.545 | AJ30: 39661.483 | AK30: 43699.56 | AL30: 48148.769 | AM30: 53050.968 | AN30: 58452.277 | AO30: 64403.513 | AP30: 70960.666 | AQ30: 78185.426 | AR30: 86145.765 | AS30: 94916.574 | BD30: 200000 | BE30: 매출액 | BF30: 8999.1363 | BG30: 8999.1363 | BH30: 8999.1363 | BI30: 8999.1363 | BJ30: 35996.545
C31: *컨센서스 | AI31: 30389.475 | AJ31: 30437.262 | AK31: 31298.569 | AL31: N/A | AM31: N/A | AN31: N/A | AO31: N/A | AP31: N/A | AQ31: N/A | AR31: N/A | AS31: N/A | BE31: (분기비중) | BF31: 0.25 | BG31: 0.25 | BH31: 0.25 | BI31: 0.25 | BJ31: 1
C32: (manual) | D32: (manual) | AI32: 32670.268 | AJ32: 35996.545 | AK32: 39661.483 | AL32: 43699.56 | AM32: 48148.769 | AN32: 53050.968 | AO32: 58452.277 | AP32: 64403.513 | AQ32: 70960.666 | AR32: 78185.426 | AS32: 86145.765
C33: (% growth) | D33: (% growth) | J33: 0 | K33: -0.0060831286 | L33: -0.13762214 | M33: -0.023849508 | N33: -0.092408614 | O33: -0.063227687 | P33: 0.19851623 | Q33: 0.11489823 | R33: 0.32265055 | S33: 0.29292642 | T33: 0.079535263 | U33: 0.062686339 | V33: 0.11783845 | W33: 0.039566835 | X33: 0.24721539 | Y33: 0.11325802 | Z33: -0.02122192 | AA33: -0.10294414 | AB33: -0.0092494326 | AC33: 0.032747682 | AD33: -0.017821443 | AE33: 0.064503217 | AF33: 0.17566865 | AG33: 0.39607526 | AH33: 0.10181359 | AI33: 0.10181359 | AJ33: 0.10181359 | AK33: 0.10181359 | AL33: 0.10181359 | AM33: 0.10181359 | AN33: 0.10181359 | AO33: 0.10181359 | AP33: 0.10181359 | AQ33: 0.10181359 | AR33: 0.10181359 | AS33: 0.10181359
B35: 200360 | C35: 매출원가 | D35: Cost of Sales | E35: 1 | J35: 5961.3531 | K35: 6282.5313 | L35: 5105.3947 | M35: 4847.7051 | N35: 4368.8944 | O35: 3933.0239 | P35: 4793.506 | Q35: 5420.8049 | R35: 7148.7166 | S35: 9441.7516 | T35: 9908.9062 | U35: 10751.856 | V35: 12075.949 | W35: 12732.365 | X35: 15864.906 | Y35: 17508.138 | Z35: 16895.275 | AA35: 15108.126 | AB35: 15069.747 | AC35: 15552.887 | AD35: 15573.996 | AE35: 16268.298 | AF35: 19726.334 | AG35: 27948.549 | AH35: 32887.201 | AI35: 36235.565 | AJ35: 39924.838 | AK35: 43989.729 | AL35: 48468.481 | AM35: 53403.231 | AN35: 58840.405 | AO35: 64831.158 | AP35: 71431.85 | AQ35: 78704.583 | AR35: 86717.779 | AS35: 95546.827 | BD35: 200360 | BE35: 매출원가 | BF35: 10788.268 | BG35: 10788.268 | BH35: 10788.268 | BI35: 3870.7595 | BJ35: 36235.565
C36: (manual) | D36: (manual) | AI36: 32887.201 | AJ36: 36235.565 | AK36: 39924.838 | AL36: 43989.729 | AM36: 48468.481 | AN36: 53403.231 | AO36: 58840.405 | AP36: 64831.158 | AQ36: 71431.85 | AR36: 78704.583 | AS36: 86717.779 | BE36: (분기비중) | BF36: 0.29772596 | BG36: 0.29772596 | BH36: 0.29772596 | BI36: 0.10682211 | BJ36: 1
C37: (% of sales) | D37: (% of sales) | J37: 0.93259131 | K37: 0.98885159 | L37: 0.93181173 | M37: 0.90639659 | N37: 0.90004299 | O37: 0.86493655 | P37: 0.87956314 | Q37: 0.89215907 | R37: 0.8895318 | S37: 0.90868249 | T37: 0.88338185 | U37: 0.90198871 | V37: 0.90627476 | W37: 0.91916881 | X37: 0.91829505 | Y37: 0.91030906 | Z37: 0.89749065 | AA37: 0.89465538 | AB37: 0.90071379 | AC37: 0.90011426 | AD37: 0.9176905 | AE37: 0.90051576 | AF37: 0.92877526 | AG37: 0.94257234 | AH37: 1.0066401 | AI37: 1.0066401 | AJ37: 1.0066401 | AK37: 1.0066401 | AL37: 1.0066401 | AM37: 1.0066401 | AN37: 1.0066401 | AO37: 1.0066401 | AP37: 1.0066401 | AQ37: 1.0066401 | AR37: 1.0066401 | AS37: 1.0066401 | BE37: (분기비중) | BF37: 0.29772596 | BG37: 0.29772596 | BH37: 0.29772596 | BI37: 0.10682211 | BJ37: 1
B39: 200810 | C39: 매출총이익 | D39: Gross Profit | J39: 430.89291 | K39: 70.82988 | L39: 373.60339 | M39: 500.62159 | N39: 485.20085 | O39: 614.15808 | P39: 656.3654 | Q39: 655.24712 | R39: 887.77696 | S39: 948.84324 | T39: 1308.1073 | U39: 1168.311 | V39: 1248.872 | W39: 1119.677 | X39: 1411.574 | Y39: 1725.042 | Z39: 1929.74 | AA39: 1778.964 | AB39: 1661.147 | AC39: 1725.905 | AD39: 1396.863 | AE39: 1797.236 | AF39: 1512.748 | AG39: 1702.808 | AH39: -216.933 | AI39: -239.01973 | AJ39: -263.35518 | AK39: -290.16832 | AL39: -319.7114 | AM39: -352.26236 | AN39: -388.12745 | AO39: -427.6441 | AP39: -471.18408 | AQ39: -519.15702 | AR39: -572.01426 | AS39: -630.25308 | BD39: 200810 | BE39: 매출총이익 | BF39: -1789.1322 | BG39: -1789.1322 | BH39: -1789.1322 | BI39: 5128.3768 | BJ39: -239.01973
C40: (% of sales) | D40: (% of sales) | J40: 0.067408686 | K40: 0.011148411 | L40: 0.068188268 | M40: 0.093603406 | N40: 0.099957011 | O40: 0.13506345 | P40: 0.12043686 | Q40: 0.10784093 | R40: 0.1104682 | S40: 0.09131751 | T40: 0.11661815 | U40: 0.098011295 | V40: 0.093725237 | W40: 0.080831187 | X40: 0.081704954 | Y40: 0.08969094 | Z40: 0.10250935 | AA40: 0.10534462 | AB40: 0.099286207 | AC40: 0.099885744 | AD40: 0.082309505 | AE40: 0.099484244 | AF40: 0.071224736 | AG40: 0.057427658 | AH40: -0.0066400741 | AI40: -0.0066400741 | AJ40: -0.0066400741 | AK40: -0.0066400741 | AL40: -0.0066400741 | AM40: -0.0066400741 | AN40: -0.0066400741 | AO40: -0.0066400741 | AP40: -0.0066400741 | AQ40: -0.0066400741 | AR40: -0.0066400741 | AS40: -0.0066400741 | BE40: (분기비중) | BF40: 7.4852908 | BG40: 7.4852908 | BH40: 7.4852908 | BI40: -21.455872 | BJ40: 1
A54: SG&A | BC54: SG&A
B56: 200820 | C56: 판매비와 관리비 등 | D56: SG&A | J56: 407.99263 | K56: 456.84213 | L56: 198.2763 | M56: 182.51919 | N56: 155.87193 | O56: 162.66844 | P56: 237.24228 | Q56: 256.95763 | R56: 320.87371 | S56: 367.80215 | T56: 552.8057 | U56: 432.715 | V56: 488.464 | W56: 415.58 | X56: 582.379 | Y56: 635.714 | Z56: 770.781 | AA56: 792.859 | AB56: 821.158 | AC56: 866.238 | AD56: 847.891 | AE56: 1043.732 | AF56: 937.846 | AG56: 917.378 | AH56: 1046.487 | AI56: 1152.4978 | AJ56: 1243.3807 | AK56: 1351.7707 | AL56: 1476.7942 | AM56: 1618.3513 | AN56: 1776.9137 | AO56: 1953.3935 | AP56: 2149.0603 | AQ56: 2365.4917 | AR56: 2604.5463 | AS56: 2868.3534 | BD56: 200820 | BE56: 판매비와 관리비 등 | BF56: 288.12446 | BG56: 288.12446 | BH56: 288.12446 | BI56: 288.12446 | BJ56: 1152.4978
C57: (% of sales) | J57: 0.063826177 | K57: 0.071905581 | L57: 0.036188423 | M57: 0.03412641 | N57: 0.032111429 | O57: 0.035773462 | P57: 0.043531721 | Q57: 0.042290229 | R57: 0.039927078 | S57: 0.035397603 | T57: 0.049282788 | U57: 0.036301085 | V57: 0.036658204 | W57: 0.030001353 | X57: 0.033709355 | Y57: 0.033052984 | Z57: 0.040944509 | AA57: 0.0469506 | AB57: 0.049080342 | AC57: 0.050133019 | AD57: 0.049961584 | AE57: 0.057774766 | AF57: 0.044156617 | AG57: 0.03093882 | AH57: 0.032031785 | AI57: 0.032016901 | AJ57: 0.031349829 | AK57: 0.030933279 | AL57: 0.030671484 | AM57: 0.030505594 | AN57: 0.030399392 | AO57: 0.030330542 | AP57: 0.030285233 | AQ57: 0.030254893 | AR57: 0.030234177 | AS57: 0.030219732 | BD57: 113091 | BE57: (분기비중) | BF57: 0.25 | BG57: 0.25 | BH57: 0.25 | BI57: 0.25 | BJ57: 1
B59: 200821 | C59: 인건비및복리후생비 | D59: Salaries and Wages | E59: 1 | J59: 94.429825 | K59: 89.858617 | L59: 83.296341 | M59: 84.624425 | N59: 81.517198 | O59: 85.682788 | P59: 111.95286 | Q59: 128.18888 | R59: 157.94683 | S59: 173.58203 | T59: 214.30022 | U59: 248.371 | V59: 265.646 | W59: 256.381 | X59: 310.644 | Y59: 330.179 | Z59: 419.216 | AA59: 431.846 | AB59: 475.484 | AC59: 466.614 | AD59: 498.26 | AE59: 513.969 | AF59: 538.377 | AG59: 583.153 | AH59: 633.54 | AI59: 698.04298 | AJ59: 769.11324 | AK59: 847.41942 | AL59: 933.69823 | AM59: 1028.7614 | AN59: 1133.5033 | AO59: 1248.9093 | AP59: 1376.0652 | AQ59: 1516.1674 | AR59: 1670.5338 | AS59: 1840.6169 | BD59: 200821 | BE59: 인건비및복리후생비 | BF59: 174.51074 | BG59: 174.51074 | BH59: 174.51074 | BI59: 174.51074 | BJ59: 698.04298
C60: (manual) | D60: (manual) | AI60: 633.54 | AJ60: 698.04298 | AK60: 769.11324 | AL60: 847.41942 | AM60: 933.69823 | AN60: 1028.7614 | AO60: 1133.5033 | AP60: 1248.9093 | AQ60: 1376.0652 | AR60: 1516.1674 | AS60: 1670.5338 | BE60: (분기비중) | BF60: 0.25 | BG60: 0.25 | BH60: 0.25 | BI60: 0.25 | BJ60: 1
C61: (% of sales) | D61: (% of sales) | J61: 0.014772558 | K61: 0.014143477 | L61: 0.015202842 | M61: 0.015822598 | N61: 0.01679349 | O61: 0.018843052 | P61: 0.020542294 | Q61: 0.021097397 | R61: 0.0196537 | S61: 0.016705688 | T61: 0.019104927 | U61: 0.020836201 | V61: 0.019936178 | W61: 0.018508535 | X61: 0.017980746 | Y61: 0.017167156 | Z61: 0.022269092 | AA61: 0.025572553 | AB61: 0.028419521 | AC61: 0.027005013 | AD61: 0.02935974 | AE61: 0.028450252 | AF61: 0.025348412 | AG61: 0.019666992 | AH61: 0.019391944 | AI61: 0.019391944 | AJ61: 0.019391944 | AK61: 0.019391944 | AL61: 0.019391944 | AM61: 0.019391944 | AN61: 0.019391944 | AO61: 0.019391944 | AP61: 0.019391944 | AQ61: 0.019391944 | AR61: 0.019391944 | AS61: 0.019391944 | BE61: (분기비중) | BF61: 0.25 | BG61: 0.25 | BH61: 0.25 | BI61: 0.25 | BJ61: 1
B63: 200822 | C63: 일반관리비 | D63: General & Administrative Expenses | E63: 1 | J63: 20.688801 | K63: 27.67948 | L63: 14.808061 | M63: 22.754691 | N63: 15.348698 | O63: 15.521722 | P63: 18.088112 | Q63: 21.839695 | R63: 26.715606 | S63: 31.753244 | T63: 41.608142 | U63: 35.147 | V63: 32.314 | W63: 41.462 | X63: 65.62 | Y63: 57.974 | Z63: 64.359 | AA63: 76.622 | AB63: 91.086 | AC63: 85.774 | AD63: 77.47 | AE63: 71.581 | AF63: 91.261 | AG63: 86.619 | AH63: 97.144 | AI63: 107.03458 | AJ63: 117.93215 | AK63: 129.93925 | AL63: 143.16883 | AM63: 157.74536 | AN63: 173.80598 | AO63: 191.50179 | AP63: 210.99928 | AQ63: 232.48187 | AR63: 256.15168 | AS63: 282.23141 | BD63: 200822 | BE63: 일반관리비 | BF63: 26.758645 | BG63: 26.758645 | BH63: 26.758645 | BI63: 26.758645 | BJ63: 107.03458
C64: (manual) | D64: (manual) | AI64: 97.144 | AJ64: 107.03458 | AK64: 117.93215 | AL64: 129.93925 | AM64: 143.16883 | AN64: 157.74536 | AO64: 173.80598 | AP64: 191.50179 | AQ64: 210.99928 | AR64: 232.48187 | AS64: 256.15168 | BE64: (분기비중) | BF64: 0.25 | BG64: 0.25 | BH64: 0.25 | BI64: 0.25 | BJ64: 1
C65: (% of sales) | D65: (% of sales) | J65: 0.0032365464 | K65: 0.0043566671 | L65: 0.0027026951 | M65: 0.004254544 | N65: 0.0031620101 | O65: 0.0034134816 | P65: 0.0033189979 | Q65: 0.0035943891 | R65: 0.0033242864 | S65: 0.0030559602 | T65: 0.0037093779 | U65: 0.0029485325 | V65: 0.0024250982 | W65: 0.0029932049 | X65: 0.0037982274 | Y65: 0.0030142701 | Z65: 0.0034188021 | AA65: 0.0045373122 | AB65: 0.0054441801 | AC65: 0.0049641202 | AD65: 0.0045648838 | AE65: 0.0039622964 | AF65: 0.004296843 | AG65: 0.0029212491 | AH65: 0.0029734681 | AI65: 0.0029734681 | AJ65: 0.0029734681 | AK65: 0.0029734681 | AL65: 0.0029734681 | AM65: 0.0029734681 | AN65: 0.0029734681 | AO65: 0.0029734681 | AP65: 0.0029734681 | AQ65: 0.0029734681 | AR65: 0.0029734681 | AS65: 0.0029734681 | BE65: (분기비중) | BF65: 0.25 | BG65: 0.25 | BH65: 0.25 | BI65: 0.25 | BJ65: 1
B67: 200823 | C67: 판매비 | D67: Sales Expenses | E67: 1 | J67: 191.86575 | K67: 267.7065 | L67: 31.221592 | M67: 31.909233 | N67: 18.81937 | O67: 17.567628 | P67: 23.197482 | Q67: 37.260634 | R67: 57.794431 | S67: 75.636948 | T67: 78.384366 | U67: 36.788 | V67: 95.866 | W67: 35.423 | X67: 84.189 | Y67: 89.96 | Z67: 121.97 | AA67: 119.899 | AB67: 132.945 | AC67: 128.449 | AD67: 61.645 | AE67: 227.182 | AF67: 90.93 | AG67: 66.057 | AH67: 100.249 | AI67: 110.45571 | AJ67: 121.7016 | AK67: 134.09248 | AL67: 147.74492 | AM67: 162.78735 | AN67: 179.36132 | AO67: 197.62274 | AP67: 217.74342 | AQ67: 239.91266 | AR67: 264.33902 | AS67: 291.25233 | BD67: 200823 | BE67: 판매비 | BF67: 27.613928 | BG67: 27.613928 | BH67: 27.613928 | BI67: 27.613928 | BJ67: 110.45571
C68: (manual) | D68: (manual) | AI68: 100.249 | AJ68: 110.45571 | AK68: 121.7016 | AL68: 134.09248 | AM68: 147.74492 | AN68: 162.78735 | AO68: 179.36132 | AP68: 197.62274 | AQ68: 217.74342 | AR68: 239.91266 | AS68: 264.33902 | BE68: (분기비중) | BF68: 0.25 | BG68: 0.25 | BH68: 0.25 | BI68: 0.25 | BJ68: 1
C69: (% of sales) | D69: (% of sales) | J69: 0.030015389 | K69: 0.0421362 | L69: 0.0056984127 | M69: 0.0059662087 | N69: 0.0038770088 | O69: 0.0038634099 | P69: 0.0042565191 | Q69: 0.0061323758 | R69: 0.0071914985 | S69: 0.0072793665 | T69: 0.0069879889 | U69: 0.0030861984 | V69: 0.0071945432 | W69: 0.0025572403 | X69: 0.0048730413 | Y69: 0.0046773336 | Z69: 0.0064791449 | AA69: 0.0071000391 | AB69: 0.0079460787 | AC69: 0.0074339109 | AD69: 0.0036324031 | AE69: 0.012575438 | AF69: 0.0042812585 | AG69: 0.0022277901 | AH69: 0.0030685087 | AI69: 0.0030685087 | AJ69: 0.0030685087 | AK69: 0.0030685087 | AL69: 0.0030685087 | AM69: 0.0030685087 | AN69: 0.0030685087 | AO69: 0.0030685087 | AP69: 0.0030685087 | AQ69: 0.0030685087 | AR69: 0.0030685087 | AS69: 0.0030685087 | BE69: (분기비중) | BF69: 0.25 | BG69: 0.25 | BH69: 0.25 | BI69: 0.25 | BJ69: 1
B71: 201130 | C71: 연구개발비 | D71: Research & Development | E71: 1 | J71: 47.914759 | K71: 41.874442 | L71: 49.963009 | M71: 29.863303 | N71: 30.367165 | O71: 34.660921 | P71: 54.787273 | Q71: 38.816925 | R71: 50.786809 | S71: 68.254526 | T71: 190.47143 | U71: 93.468 | V71: 73.874 | W71: 62.059 | X71: 60.383 | Y71: 63.472 | Z71: 87.62 | AA71: 85.934 | AB71: 109.949 | AC71: 151.432 | AD71: 177.527 | AE71: 190.025 | AF71: 178.612 | AG71: 138.787 | AH71: 154.923 | AI71: 170.69627 | AJ71: 188.07547 | AK71: 207.2241 | AL71: 228.32233 | AM71: 251.56865 | AN71: 277.18175 | AO71: 305.40262 | AP71: 336.49676 | AQ71: 370.7567 | AR71: 408.50477 | AS71: 450.09611 | BD71: 201130 | BE71: 연구개발비 | BF71: 42.674067 | BG71: 42.674067 | BH71: 42.674067 | BI71: 42.674067 | BJ71: 170.69627
C72: (manual) | D72: (manual) | AI72: 154.923 | AJ72: 170.69627 | AK72: 188.07547 | AL72: 207.2241 | AM72: 228.32233 | AN72: 251.56865 | AO72: 277.18175 | AP72: 305.40262 | AQ72: 336.49676 | AR72: 370.7567 | AS72: 408.50477 | BE72: (분기비중) | BF72: 0.25 | BG72: 0.25 | BH72: 0.25 | BI72: 0.25 | BJ72: 1
C73: (% of sales) | D73: (% of sales) | J73: 0.0074957626 | K73: 0.0065909116 | L73: 0.0091190047 | M73: 0.0055836722 | N73: 0.0062559887 | O73: 0.0076225058 | P73: 0.010052948 | Q73: 0.006388511 | R73: 0.0063195234 | S73: 0.0065688757 | T73: 0.016980583 | U73: 0.0078411653 | V73: 0.0055440895 | W73: 0.0044801337 | X73: 0.0034950985 | Y73: 0.0033001303 | Z73: 0.0046544452 | AA73: 0.0050887394 | AB73: 0.0065716154 | AC73: 0.0087640386 | AD73: 0.010460696 | AE73: 0.010518648 | AF73: 0.0084095913 | AG73: 0.004680629 | AH73: 0.004742018 | AI73: 0.004742018 | AJ73: 0.004742018 | AK73: 0.004742018 | AL73: 0.004742018 | AM73: 0.004742018 | AN73: 0.004742018 | AO73: 0.004742018 | AP73: 0.004742018 | AQ73: 0.004742018 | AR73: 0.004742018 | AS73: 0.004742018 | BE73: (분기비중) | BF73: 0.25 | BG73: 0.25 | BH73: 0.25 | BI73: 0.25 | BJ73: 1
B75: 201160 | C75: 광고선전비 | D75: Advertising Expenses | E75: 1 | J75: 15.734294 | K75: 3.83863 | L75: 2.369024 | M75: 2.963381 | N75: 3.713335 | O75: 4.749634 | P75: 24.90458 | Q75: 25.972288 | R75: 22.429208 | S75: 13.709182 | T75: 14.352038 | U75: 11.4 | V75: 11.506 | W75: 10.024 | X75: 13.801 | Y75: 14.455 | Z75: 14.813 | AA75: 10.592 | AB75: 0 | AC75: 0 | AD75: 0 | AE75: 0 | AF75: 0 | AG75: 0 | AH75: 0 | AI75: 0 | AJ75: 0 | AK75: 0 | AL75: 0 | AM75: 0 | AN75: 0 | AO75: 0 | AP75: 0 | AQ75: 0 | AR75: 0 | AS75: 0 | BD75: 201160 | BE75: 광고선전비 | BF75: 0 | BG75: 0 | BH75: 0 | BI75: 0 | BJ75: 0
C76: (manual) | D76: (manual) | AI76: 0 | AJ76: 0 | AK76: 0 | AL76: 0 | AM76: 0 | AN76: 0 | AO76: 0 | AP76: 0 | AQ76: 0 | AR76: 0 | AS76: 0 | BE76: (분기비중)
C77: (% of sales) | D77: (% of sales) | J77: 0.0024614656 | K77: 0.00060418885 | L77: 0.0004323827 | M77: 0.00055407629 | N77: 0.00076499015 | O77: 0.0010445225 | P77: 0.0045697555 | Q77: 0.0042745335 | R77: 0.0027909197 | S77: 0.0013193838 | T77: 0.0012794883 | U77: 0.00095636244 | V77: 0.00086350128 | W77: 0.00072364782 | X77: 0.00079883171 | Y77: 0.00075156578 | Z77: 0.00078687852 | AA77: 0.0006272247 | AB77: 0 | AC77: 0 | AD77: 0 | AE77: 0 | AF77: 0 | AG77: 0 | AH77: 0 | AI77: 0 | AJ77: 0 | AK77: 0 | AL77: 0 | AM77: 0 | AN77: 0 | AO77: 0 | AP77: 0 | AQ77: 0 | AR77: 0 | AS77: 0 | BE77: (분기비중)
B79: 201080 | C79: 유형자산 감가상각비 | D79: Depreciation (SG&A) | J79: 37.3483 | K79: 25.873568 | L79: 16.607373 | M79: 10.400645 | N79: 6.054871 | O79: 4.316226 | P79: 3.816779 | Q79: 4.544511 | R79: 4.847228 | S79: 4.468217 | T79: 6.656417 | U79: 7.093 | V79: 8.302 | W79: 8.818 | X79: 9.091 | Y79: 10.094 | Z79: 11.269 | AA79: 11.852 | AB79: 11.694 | AC79: 17.807 | AD79: 27.58 | AE79: 34.378 | AF79: 34.859 | AG79: 37.749 | AH79: 53.999 | AI79: 58.062225 | AJ79: 39.129134 | AK79: 26.369798 | AL79: 17.771061 | AM79: 11.976225 | AN79: 8.0709842 | AO79: 5.4391753 | AP79: 3.665554 | AQ79: 2.47028 | AR79: 1.6647643 | AS79: 1.1219133 | BD79: 201080 | BE79: 유형자산 감가상각비 | BF79: 14.515556 | BG79: 14.515556 | BH79: 14.515556 | BI79: 14.515556 | BJ79: 58.062225
B80: 201090+201100 | C80: 무형자산상각비 | D80: Amortization (SG&A) | J80: 0.010894 | K80: 0.010894 | L80: 0.010894 | M80: 0.003511 | N80: 0.051299 | O80: 0.169521 | P80: 0.495198 | Q80: 0.334702 | R80: 0.353596 | S80: 0.398002 | T80: 7.033087 | U80: 0.448 | V80: 0.956 | W80: 1.413 | X80: 38.651 | Y80: 69.58 | Z80: 51.534 | AA80: 56.114 | AB80: 0 | AC80: 16.162 | AD80: 5.409 | AE80: 6.597 | AF80: 3.807 | AG80: 5.013 | AH80: 6.632 | AI80: 8.2060772 | AJ80: 7.4290818 | AK80: 6.7256564 | AL80: 6.0888352 | AM80: 5.5123116 | AN80: 4.9903764 | AO80: 4.5178608 | AP80: 4.0900855 | AQ80: 3.7028142 | AR80: 3.3522119 | AS80: 3.0348065 | BD80: 201090+201100 | BE80: 무형자산상각비 | BF80: 2.0515193 | BG80: 2.0515193 | BH80: 2.0515193 | BI80: 2.0515193 | BJ80: 8.2060772
A91: Operating Income | BC91: Other Operating Income & Expenses
B93: 203590 | C93: 기타영업수익 | D93: Other Operating Income | J93: 0 | K93: 0 | L93: 0 | M93: 0 | N93: 0 | O93: 0 | P93: 0 | Q93: 0 | R93: 0 | S93: 0 | T93: 0 | U93: 202.47927 | V93: 0 | W93: 0 | X93: 0 | Y93: 0 | Z93: 0 | AA93: 0 | AB93: 0 | AC93: 0 | AD93: 0 | AE93: 0 | AF93: 0 | AG93: 0 | AH93: 0 | AI93: 0 | AJ93: 0 | AK93: 0 | AL93: 0 | AM93: 0 | AN93: 0 | AO93: 0 | AP93: 0 | AQ93: 0 | AR93: 0 | AS93: 0 | BD93: 203590 | BE93: 기타영업수익 | BF93: 0 | BG93: 0 | BH93: 0 | BI93: 0 | BJ93: 0
BE94: (분기비중)
B95: 203600 | C95: 이자수익 | D95: Interest Income | J95: 0 | K95: 0 | L95: 0 | M95: 0 | N95: 0 | O95: 0 | P95: 0 | Q95: 0 | R95: 0 | S95: 0 | T95: 0 | U95: 0 | V95: 0 | W95: 0 | X95: 0 | Y95: 0 | Z95: 0 | AA95: 0 | AB95: 0 | AC95: 0 | AD95: 0 | AE95: 0 | AF95: 0 | AG95: 0 | AH95: 0 | AI95: 0 | AJ95: 0 | AK95: 0 | AL95: 0 | AM95: 0 | AN95: 0 | AO95: 0 | AP95: 0 | AQ95: 0 | AR95: 0 | AS95: 0 | BD95: 203600 | BE95: 이자수익 | BF95: 0 | BG95: 0 | BH95: 0 | BI95: 0 | BJ95: 0
B96: 203620 | C96: 외환거래이익 | D96: Gains on Foreign Exchange | J96: 0 | K96: 0 | L96: 0 | M96: 0 | N96: 0 | O96: 0 | P96: 0 | Q96: 0 | R96: 0 | S96: 0 | T96: 0 | U96: 90.597 | V96: 0 | W96: 0 | X96: 0 | Y96: 0 | Z96: 0 | AA96: 0 | AB96: 0 | AC96: 0 | AD96: 0 | AE96: 0 | AF96: 0 | AG96: 0 | AH96: 0 | AI96: 0 | AJ96: 0 | AK96: 0 | AL96: 0 | AM96: 0 | AN96: 0 | AO96: 0 | AP96: 0 | AQ96: 0 | AR96: 0 | AS96: 0 | BD96: 203620 | BE96: 외환거래이익 | BF96: 0 | BG96: 0 | BH96: 0 | BI96: 0 | BJ96: 0
B97: 203610 | C97: 배당금수익 | D97: Dividend Income | J97: 0 | K97: 0 | L97: 0 | M97: 0 | N97: 0 | O97: 0 | P97: 0 | Q97: 0 | R97: 0 | S97: 0 | T97: 0 | U97: 0 | V97: 0 | W97: 0 | X97: 0 | Y97: 0 | Z97: 0 | AA97: 0 | AB97: 0 | AC97: 0 | AD97: 0 | AE97: 0 | AF97: 0 | AG97: 0 | AH97: 0 | AI97: 0 | AJ97: 0 | AK97: 0 | AL97: 0 | AM97: 0 | AN97: 0 | AO97: 0 | AP97: 0 | AQ97: 0 | AR97: 0 | AS97: 0 | BD97: 203610 | BE97: 배당금수익 | BF97: 0 | BG97: 0 | BH97: 0 | BI97: 0 | BJ97: 0
B98: 203800 | C98: 투자자산평가이익 | D98: Gains on Investment Assets | J98: 0 | K98: 0 | L98: 0 | M98: 0 | N98: 0 | O98: 0 | P98: 0 | Q98: 0 | R98: 0 | S98: 0 | T98: 0 | U98: 0 | V98: 0 | W98: 0 | X98: 0 | Y98: 0 | Z98: 0 | AA98: 0 | AB98: 0 | AC98: 0 | AD98: 0 | AE98: 0 | AF98: 0 | AG98: 0 | AH98: 0 | AI98: 0 | AJ98: 0 | AK98: 0 | AL98: 0 | AM98: 0 | AN98: 0 | AO98: 0 | AP98: 0 | AQ98: 0 | AR98: 0 | AS98: 0 | BD98: 203800 | BE98: 투자자산평가이익 | BF98: 0 | BG98: 0 | BH98: 0 | BI98: 0 | BJ98: 0
B99: 203591 | C99: 기타 기타수익 | D99: Others | J99: 0 | K99: 0 | L99: 0 | M99: 0 | N99: 0 | O99: 0 | P99: 0 | Q99: 0 | R99: 0 | S99: 0 | T99: 0 | U99: 111.88227 | V99: 0 | W99: 0 | X99: 0 | Y99: 0 | Z99: 0 | AA99: 0 | AB99: 0 | AC99: 0 | AD99: 0 | AE99: 0 | AF99: 0 | AG99: 0 | AH99: 0 | AI99: 0 | AJ99: 0 | AK99: 0 | AL99: 0 | AM99: 0 | AN99: 0 | AO99: 0 | AP99: 0 | AQ99: 0 | AR99: 0 | AS99: 0 | BD99: 203591 | BE99: 기타 기타수익 | BF99: 0 | BG99: 0 | BH99: 0 | BI99: 0 | BJ99: 0
B101: 204030 | C101: 기타영업비용 | D101: Other Operating Expenses | J101: 0 | K101: 0 | L101: 0 | M101: 0 | N101: 0 | O101: 0 | P101: 0 | Q101: 0 | R101: 0 | S101: 0 | T101: 0 | U101: 184.06849 | V101: 0 | W101: 0 | X101: 0 | Y101: 0 | Z101: 0 | AA101: 0 | AB101: 0 | AC101: 0 | AD101: 0 | AE101: 0 | AF101: 0 | AG101: 0 | AH101: 0 | AI101: 0 | AJ101: 0 | AK101: 0 | AL101: 0 | AM101: 0 | AN101: 0 | AO101: 0 | AP101: 0 | AQ101: 0 | AR101: 0 | AS101: 0 | BD101: 204030 | BE101: 기타영업비용 | BF101: 0 | BG101: 0 | BH101: 0 | BI101: 0 | BJ101: 0
BE102: (분기비중)
B103: 204040 | C103: 이자비용 | D103: Interest Expenses | J103: 0 | K103: 0 | L103: 0 | M103: 0 | N103: 0 | O103: 0 | P103: 0 | Q103: 0 | R103: 0 | S103: 0 | T103: 0 | U103: 0 | V103: 0 | W103: 0 | X103: 0 | Y103: 0 | Z103: 0 | AA103: 0 | AB103: 0 | AC103: 0 | AD103: 0 | AE103: 0 | AF103: 0 | AG103: 0 | AH103: 0 | AI103: 0 | AJ103: 0 | AK103: 0 | AL103: 0 | AM103: 0 | AN103: 0 | AO103: 0 | AP103: 0 | AQ103: 0 | AR103: 0 | AS103: 0 | BD103: 204040 | BE103: 이자비용 | BF103: 0 | BG103: 0 | BH103: 0 | BI103: 0 | BJ103: 0
B104: 204050 | C104: 외환거래손실 | D104: Losses on Foreign Exchange | J104: 0 | K104: 0 | L104: 0 | M104: 0 | N104: 0 | O104: 0 | P104: 0 | Q104: 0 | R104: 0 | S104: 0 | T104: 0 | U104: 89.398 | V104: 0 | W104: 0 | X104: 0 | Y104: 0 | Z104: 0 | AA104: 0 | AB104: 0 | AC104: 0 | AD104: 0 | AE104: 0 | AF104: 0 | AG104: 0 | AH104: 0 | AI104: 0 | AJ104: 0 | AK104: 0 | AL104: 0 | AM104: 0 | AN104: 0 | AO104: 0 | AP104: 0 | AQ104: 0 | AR104: 0 | AS104: 0 | BD104: 204050 | BE104: 외환거래손실 | BF104: 0 | BG104: 0 | BH104: 0 | BI104: 0 | BJ104: 0
B105: 204240 | C105: 투자자산평가손실 | D105: Losses on Investment Assets | J105: 0 | K105: 0 | L105: 0 | M105: 0 | N105: 0 | O105: 0 | P105: 0 | Q105: 0 | R105: 0 | S105: 0 | T105: 0 | U105: 0 | V105: 0 | W105: 0 | X105: 0 | Y105: 0 | Z105: 0 | AA105: 0 | AB105: 0 | AC105: 0 | AD105: 0 | AE105: 0 | AF105: 0 | AG105: 0 | AH105: 0 | AI105: 0 | AJ105: 0 | AK105: 0 | AL105: 0 | AM105: 0 | AN105: 0 | AO105: 0 | AP105: 0 | AQ105: 0 | AR105: 0 | AS105: 0 | BD105: 204240 | BE105: 투자자산평가손실 | BF105: 0 | BG105: 0 | BH105: 0 | BI105: 0 | BJ105: 0
B106: 204031 | C106: 기타 기타비용 | D106: Others | J106: 0 | K106: 0 | L106: 0 | M106: 0 | N106: 0 | O106: 0 | P106: 0 | Q106: 0 | R106: 0 | S106: 0 | T106: 0 | U106: 94.670495 | V106: 0 | W106: 0 | X106: 0 | Y106: 0 | Z106: 0 | AA106: 0 | AB106: 0 | AC106: 0 | AD106: 0 | AE106: 0 | AF106: 0 | AG106: 0 | AH106: 0 | AI106: 0 | AJ106: 0 | AK106: 0 | AL106: 0 | AM106: 0 | AN106: 0 | AO106: 0 | AP106: 0 | AQ106: 0 | AR106: 0 | AS106: 0 | BD106: 204031 | BE106: 기타 기타비용 | BF106: 0 | BG106: 0 | BH106: 0 | BI106: 0 | BJ106: 0
B108: 201370 | C108: 영업이익 | D108: Operating Income | J108: 22.900283 | K108: -386.01225 | L108: 175.32709 | M108: 318.1024 | N108: 329.32891 | O108: 451.48964 | P108: 419.12311 | Q108: 398.28949 | R108: 566.90325 | S108: 581.04109 | T108: 755.30163 | U108: 754.00678 | V108: 760.408 | W108: 704.097 | X108: 829.195 | Y108: 1089.328 | Z108: 1158.959 | AA108: 986.105 | AB108: 839.989 | AC108: 859.667 | AD108: 548.972 | AE108: 753.504 | AF108: 574.902 | AG108: 785.43 | AH108: -1263.42 | AI108: -1391.5176 | AJ108: -1506.7359 | AK108: -1641.939 | AL108: -1796.5056 | AM108: -1970.6137 | AN108: -2165.0411 | AO108: -2381.0376 | AP108: -2620.2444 | AQ108: -2884.6487 | AR108: -3176.5605 | AS108: -3498.6065 | BD108: 201370 | BE108: 영업이익 | BF108: -2077.2566 | BG108: -2077.2566 | BH108: -2077.2566 | BI108: 4840.2523 | BJ108: -1391.5176
C109: *컨센서스 | AI109: 994.34375 | AJ109: 1257.4688 | AK109: 1308.4 | AL109: N/A | AM109: N/A | AN109: N/A | AO109: N/A | AP109: N/A | AQ109: N/A | AR109: N/A | AS109: N/A | BE109: (% of sales) | BF109: -0.23082844 | BG109: -0.23082844 | BH109: -0.23082844 | BI109: 0.53785743 | BJ109: -0.038656976
C110: (% of sales) | D110: (% of sales) | J110: 0.0035825096 | K110: -0.06075717 | L110: 0.031999845 | M110: 0.059476996 | N110: 0.067845581 | O110: 0.099289987 | P110: 0.076905138 | Q110: 0.065550704 | R110: 0.070541119 | S110: 0.055919907 | T110: 0.067335359 | U110: 0.063254716 | V110: 0.057067033 | W110: 0.050829834 | X110: 0.047995599 | Y110: 0.056637956 | Z110: 0.061564838 | AA110: 0.058394016 | AB110: 0.050205865 | AC110: 0.049752726 | AD110: 0.032347921 | AE110: 0.041709478 | AF110: 0.027068119 | AG110: 0.026488838 | AH110: -0.038671859 | AI110: -0.038656976 | AJ110: -0.037989903 | AK110: -0.037573353 | AL110: -0.037311558 | AM110: -0.037145668 | AN110: -0.037039466 | AO110: -0.036970617 | AP110: -0.036925308 | AQ110: -0.036894967 | AR110: -0.036874251 | AS110: -0.036859806 | BE110: (분기비중) | BF110: 1.4927994 | BG110: 1.4927994 | BH110: 1.4927994 | BI110: -3.4783983 | BJ110: 1
C111: (% growth) | D111: (% growth) | K111: -17.856222 | L111: 1.4542009 | M111: 0.81433685 | N111: 0.035292123 | O111: 0.37093838 | P111: -0.071688309 | Q111: -0.049707657 | R111: 0.42334475 | S111: 0.024938719 | T111: 0.29991088 | U111: -0.0017143582 | V111: 0.0084896101 | W111: -0.074053666 | X111: 0.17767154 | Y111: 0.31371752 | Z111: 0.06392106 | AA111: -0.14914591 | AB111: -0.14817489 | AC111: 0.023426497 | AD111: -0.3614132 | AE111: 0.37257274 | AF111: -0.2370286 | AG111: 0.36619807 | AH111: -2.6085711 | AI111: -0.10138953 | AJ111: -0.08280046 | AK111: -0.08973249 | AL111: -0.094136611 | AM111: -0.096914842 | AN111: -0.098663428 | AO111: -0.09976552 | AP111: -0.10046327 | AQ111: -0.10090826 | AR111: -0.10119492 | AS111: -0.10138197 | BF111: 1.4927994 | BG111: 1.4927994 | BH111: 1.4927994 | BI111: -3.4783983 | BJ111: 1
B113: 201371 | C113: 조정영업이익 | D113: adj. Operating Income | J113: 22.900283 | K113: -386.01225 | L113: 175.32709 | M113: 318.1024 | N113: 329.32891 | O113: 451.48964 | P113: 419.12311 | Q113: 398.28949 | R113: 566.90325 | S113: 581.04109 | T113: 755.30163 | U113: 735.596 | V113: 760.408 | W113: 704.097 | X113: 829.195 | Y113: 1089.328 | Z113: 1158.959 | AA113: 986.105 | AB113: 839.989 | AC113: 859.667 | AD113: 548.972 | AE113: 753.504 | AF113: 574.902 | AG113: 785.43 | AH113: -1263.42 | AI113: -1391.5176 | AJ113: -1506.7359 | AK113: -1641.939 | AL113: -1796.5056 | AM113: -1970.6137 | AN113: -2165.0411 | AO113: -2381.0376 | AP113: -2620.2444 | AQ113: -2884.6487 | AR113: -3176.5605 | AS113: -3498.6065 | BD113: 201371 | BE113: 조정영업이익 | BF113: -2077.2566 | BG113: -2077.2566 | BH113: -2077.2566 | BI113: 4840.2523 | BJ113: -1391.5176
C114: (% of sales) | D114: (% of sales) | J114: 0.0035825096 | K114: -0.06075717 | L114: 0.031999845 | M114: 0.059476996 | N114: 0.067845581 | O114: 0.099289987 | P114: 0.076905138 | Q114: 0.065550704 | R114: 0.070541119 | S114: 0.055919907 | T114: 0.067335359 | U114: 0.061710209 | V114: 0.057067033 | W114: 0.050829834 | X114: 0.047995599 | Y114: 0.056637956 | Z114: 0.061564838 | AA114: 0.058394016 | AB114: 0.050205865 | AC114: 0.049752726 | AD114: 0.032347921 | AE114: 0.041709478 | AF114: 0.027068119 | AG114: 0.026488838 | AH114: -0.038671859 | AI114: -0.038656976 | AJ114: -0.037989903 | AK114: -0.037573353 | AL114: -0.037311558 | AM114: -0.037145668 | AN114: -0.037039466 | AO114: -0.036970617 | AP114: -0.036925308 | AQ114: -0.036894967 | AR114: -0.036874251 | AS114: -0.036859806 | BE114: (% of sales) | BF114: -0.23082844 | BG114: -0.23082844 | BH114: -0.23082844 | BI114: 0.53785743 | BJ114: -0.038656976
C115: (% growth) | D115: (% growth) | K115: -17.856222 | L115: 1.4542009 | M115: 0.81433685 | N115: 0.035292123 | O115: 0.37093838 | P115: -0.071688309 | Q115: -0.049707657 | R115: 0.42334475 | S115: 0.024938719 | T115: 0.29991088 | U115: -0.026089754 | V115: 0.033730472 | W115: -0.074053666 | X115: 0.17767154 | Y115: 0.31371752 | Z115: 0.06392106 | AA115: -0.14914591 | AB115: -0.14817489 | AC115: 0.023426497 | AD115: -0.3614132 | AE115: 0.37257274 | AF115: -0.2370286 | AG115: 0.36619807 | AH115: -2.6085711 | AI115: -0.10138953 | AJ115: -0.08280046 | AK115: -0.08973249 | AL115: -0.094136611 | AM115: -0.096914842 | AN115: -0.098663428 | AO115: -0.09976552 | AP115: -0.10046327 | AQ115: -0.10090826 | AR115: -0.10119492 | AS115: -0.10138197 | BE115: (분기비중) | BF115: 1.4927994 | BG115: 1.4927994 | BH115: 1.4927994 | BI115: -3.4783983 | BJ115: 1
B117: 201372 | C117: EBITDA (*)조정영업이익 기준 | D117: adj. EBITDA (= adj. Operating Income + DA) | J117: 104.79604 | K117: -318.77913 | L117: 220.59976 | M117: 358.94501 | N117: 361.91431 | O117: 470.22315 | P117: 444.06645 | Q117: 429.18777 | R117: 611.31641 | S117: 666.32031 | T117: 840.22744 | U117: 812.03 | V117: 846.187 | W117: 797.36 | X117: 983.249 | Y117: 1285.147 | Z117: 1349.42 | AA117: 1179.466 | AB117: 1012.107 | AC117: 1043.921 | AD117: 720.629 | AE117: 925.005 | AF117: 756.61 | AG117: 981.544 | AH117: -1041.923 | AI117: -1151.7154 | AJ117: -1342.2352 | AK117: -1528.4594 | AL117: -1717.658 | AM117: -1915.3297 | AN117: -2125.8404 | AO117: -2352.8597 | AP117: -2599.6617 | AQ117: -2869.3353 | AR117: -3164.9348 | AS117: -3489.5896 | BD117: 201372 | BE117: EBITDA (*)조정영업이익 기준 | BF117: -2017.3061 | BG117: -2017.3061 | BH117: -2017.3061 | BI117: 4900.2028 | BJ117: -1151.7154
C118: (% of sales) | D118: (% of sales) | J118: 0.016394244 | K118: -0.050174879 | L118: 0.040262792 | M118: 0.067113516 | N118: 0.074558552 | O118: 0.10340979 | P118: 0.081482005 | Q118: 0.070635961 | R118: 0.076067555 | S118: 0.064127254 | T118: 0.07490652 | U118: 0.068122368 | V118: 0.063504568 | W118: 0.057562632 | X118: 0.056912577 | Y118: 0.066819268 | Z118: 0.07168228 | AA118: 0.069844242 | AB118: 0.060493301 | AC118: 0.060416318 | AD118: 0.04246273 | AE118: 0.051202749 | AF118: 0.035623479 | AG118: 0.033102836 | AH118: -0.031892086 | AI118: -0.031995165 | AJ118: -0.033842286 | AK118: -0.034976539 | AL118: -0.035673974 | AM118: -0.036103576 | AN118: -0.036368821 | AO118: -0.036533096 | AP118: -0.036635249 | AQ118: -0.036699107 | AR118: -0.036739297 | AS118: -0.036764808 | BE118: (% of sales) | BF118: -0.22416663 | BG118: -0.22416663 | BH118: -0.22416663 | BI118: 0.54451924 | BJ118: -0.031995165
C119: (% growth) | D119: (% growth) | K119: -4.0419005 | L119: 1.6920144 | M119: 0.62713238 | N119: 0.0082723006 | O119: 0.29926654 | P119: -0.05562614 | Q119: -0.033505526 | R119: 0.42435655 | S119: 0.089976151 | T119: 0.2609963 | U119: -0.0335593 | V119: 0.042063717 | W119: -0.057702375 | X119: 0.23313058 | Y119: 0.30704125 | Z119: 0.050012178 | AA119: -0.12594596 | AB119: -0.14189387 | AC119: 0.031433435 | AD119: -0.3096901 | AE119: 0.28360779 | AF119: -0.18204766 | AG119: 0.29729187 | AH119: -2.0615143 | AI119: -0.10537477 | AJ119: -0.16542266 | AK119: -0.13874183 | AL119: -0.12378384 | AM119: -0.11508212 | AN119: -0.10990837 | AO119: -0.10679038 | AP119: -0.10489445 | AQ119: -0.10373413 | AR119: -0.10302019 | AS119: -0.10257866 | BE119: (분기비중) | BF119: 1.7515665 | BG119: 1.7515665 | BH119: 1.7515665 | BI119: -4.2546994 | BJ119: 1
A134: Interest I&E
B136: 203600+202220 | C136: 이자수익 (Total) | D136: Interest income (Total) | J136: 53.145008 | K136: 52.093861 | L136: 51.216052 | M136: 36.548506 | N136: 31.57821 | O136: 36.577279 | P136: 54.765098 | Q136: 60.109962 | R136: 62.596867 | S136: 66.492417 | T136: 61.850527 | U136: 62.748 | V136: 75.642 | W136: 67.481 | X136: 67.86 | Y136: 70.868 | Z136: 78.772 | AA136: 92.9 | AB136: 110.298 | AC136: 108.61 | AD136: 97.095 | AE136: 100.219 | AF136: 162.194 | AG136: 179.519 | AH136: 216.805 | AI136: 19.514374 | AJ136: 14.363708 | AK136: 10.57252 | AL136: 7.7819864 | AM136: 5.7279922 | AN136: 4.2161336 | AO136: 3.1033182 | AP136: 2.2842217 | AQ136: 1.6813193 | AR136: 1.2375483 | AS136: 0.91090714 | BD136: 203600+202220
C137: 평균 이자율(%) | D137: Interest rate(%, avg) | J137: 0.27912823 | K137: 0.070844902 | L137: 0.073496594 | M137: 0.053630097 | N137: 0.076109958 | O137: 0.075754649 | P137: 0.0989762 | Q137: 0.099558603 | R137: 0.040918361 | S137: 0.042431915 | T137: 0.031514569 | U137: 0.03110246 | V137: 0.033929582 | W137: 0.028388226 | X137: 0.021952547 | Y137: 0.021883119 | Z137: 0.019672801 | AA137: 0.025353288 | AB137: 0.025644925 | AC137: 0.023847347 | AD137: 0.015999922 | AE137: 0.016167948 | AF137: 0.029477256 | AG137: 0.034677942 | AH137: 0.03709146 | AI137: 0.03709146 | AJ137: 0.03709146 | AK137: 0.03709146 | AL137: 0.03709146 | AM137: 0.03709146 | AN137: 0.03709146 | AO137: 0.03709146 | AP137: 0.03709146 | AQ137: 0.03709146 | AR137: 0.03709146 | AS137: 0.03709146
B139: 800050 | C139: (*) 이자발생자산 | D139: (*) Interest bearing assets | J139: 190.39639 | K139: 735.32265 | L139: 696.84933 | M139: 681.49244 | N139: 414.90248 | O139: 482.83873 | P139: 553.31583 | Q139: 603.76462 | R139: 1529.799 | S139: 1567.0379 | T139: 1962.6011 | U139: 2017.461 | V139: 2229.382 | W139: 2377.077 | X139: 3091.213 | Y139: 3238.478 | Z139: 4004.107 | AA139: 3664.219 | AB139: 4300.968 | AC139: 4554.385 | AD139: 6068.467 | AE139: 6198.622 | AF139: 5502.344 | AG139: 5176.749 | AH139: 5845.146 | AI139: 526.11501 | AJ139: 387.25108 | AK139: 285.0392 | AL139: 209.80534 | AM139: 154.42887 | AN139: 113.66858 | AO139: 83.666651 | AP139: 61.583495 | AQ139: 45.329015 | AR139: 33.364777 | AS139: 24.558406 | BD139: 800050
C141: <이자수익 배분> | D141: <Allocation>
B142: 203600 | C142: 이자수익(기타영업수익내) | D142: Interest income (Other op. income) | J142: 0 | K142: 0 | L142: 0 | M142: 0 | N142: 0 | O142: 0 | P142: 0 | Q142: 0 | R142: 0 | S142: 0 | T142: 0 | U142: 0 | V142: 0 | W142: 0 | X142: 0 | Y142: 0 | Z142: 0 | AA142: 0 | AB142: 0 | AC142: 0 | AD142: 0 | AE142: 0 | AF142: 0 | AG142: 0 | AH142: 0 | AI142: 0 | AJ142: 0 | AK142: 0 | AL142: 0 | AM142: 0 | AN142: 0 | AO142: 0 | AP142: 0 | AQ142: 0 | AR142: 0 | AS142: 0 | BD142: 203600
C143: Portion(%) | D143: Portion(%) | J143: 0 | K143: 0 | L143: 0 | M143: 0 | N143: 0 | O143: 0 | P143: 0 | Q143: 0 | R143: 0 | S143: 0 | T143: 0 | U143: 0 | V143: 0 | W143: 0 | X143: 0 | Y143: 0 | Z143: 0 | AA143: 0 | AB143: 0 | AC143: 0 | AD143: 0 | AE143: 0 | AF143: 0 | AG143: 0 | AH143: 0 | AI143: 0 | AJ143: 0 | AK143: 0 | AL143: 0 | AM143: 0 | AN143: 0 | AO143: 0 | AP143: 0 | AQ143: 0 | AR143: 0 | AS143: 0
B144: 202220 | C144: 이자수익(금융수익내) | D144: Interest income (Financial Income) | J144: 53.145008 | K144: 52.093861 | L144: 51.216052 | M144: 36.548506 | N144: 31.57821 | O144: 36.577279 | P144: 54.765098 | Q144: 60.109962 | R144: 62.596867 | S144: 66.492417 | T144: 61.850527 | U144: 62.748 | V144: 75.642 | W144: 67.481 | X144: 67.86 | Y144: 70.868 | Z144: 78.772 | AA144: 92.9 | AB144: 110.298 | AC144: 108.61 | AD144: 97.095 | AE144: 100.219 | AF144: 162.194 | AG144: 179.519 | AH144: 216.805 | AI144: 19.514374 | AJ144: 14.363708 | AK144: 10.57252 | AL144: 7.7819864 | AM144: 5.7279922 | AN144: 4.2161336 | AO144: 3.1033182 | AP144: 2.2842217 | AQ144: 1.6813193 | AR144: 1.2375483 | AS144: 0.91090714 | BD144: 202220
C145: Portion(%) | D145: Portion(%) | J145: 1 | K145: 1 | L145: 1 | M145: 1 | N145: 1 | O145: 1 | P145: 1 | Q145: 1 | R145: 1 | S145: 1 | T145: 1 | U145: 1 | V145: 1 | W145: 1 | X145: 1 | Y145: 1 | Z145: 1 | AA145: 1 | AB145: 1 | AC145: 1 | AD145: 1 | AE145: 1 | AF145: 1 | AG145: 1 | AH145: 1 | AI145: 1 | AJ145: 1 | AK145: 1 | AL145: 1 | AM145: 1 | AN145: 1 | AO145: 1 | AP145: 1 | AQ145: 1 | AR145: 1 | AS145: 1
B147: 204040+202560 | C147: 이자비용 (Total) | D147: Interest expenses (Total) | J147: 563.40683 | K147: 357.26468 | L147: 160.83509 | M147: 134.68476 | N147: 123.4153 | O147: 113.43441 | P147: 105.84587 | Q147: 99.382807 | R147: 98.433517 | S147: 79.752025 | T147: 59.591422 | U147: 42.676 | V147: 61.046 | W147: 70.007 | X147: 105.527 | Y147: 103.081 | Z147: 87.061 | AA147: 76.816 | AB147: 91.114 | AC147: 84.754 | AD147: 78.126 | AE147: 58.036 | AF147: 43.727 | AG147: 64.062 | AH147: 100.546 | AI147: 100.546 | AJ147: 100.546 | AK147: 100.546 | AL147: 100.546 | AM147: 100.546 | AN147: 100.546 | AO147: 100.546 | AP147: 100.546 | AQ147: 100.546 | AR147: 100.546 | AS147: 100.546 | BD147: 204040+202560
C148: 평균 이자율(%) | D148: Interest rate(%, avg) | J148: 0.1256126 | K148: 0.1898703 | L148: 0.093018639 | M148: 0.082864623 | N148: 0.077930661 | O148: 0.06398471 | P148: 0.062601606 | Q148: 0.063017043 | R148: 0.067829258 | S148: 0.071225871 | T148: 0.05170688 | U148: 0.028764332 | V148: 0.03527651 | W148: 0.029705168 | X148: 0.039382197 | Y148: 0.037907586 | Z148: 0.032786583 | AA148: 0.032103043 | AB148: 0.035948759 | AC148: 0.030259689 | AD148: 0.028616 | AE148: 0.024116642 | AF148: 0.02201463 | AG148: 0.02519219 | AH148: 0.027720432 | AI148: 0.027720432 | AJ148: 0.027720432 | AK148: 0.027720432 | AL148: 0.027720432 | AM148: 0.027720432 | AN148: 0.027720432 | AO148: 0.027720432 | AP148: 0.027720432 | AQ148: 0.027720432 | AR148: 0.027720432 | AS148: 0.027720432
C150: (*) 이자발생부채 | D150: (*) Interest bearing debts | J150: 4485.2731 | K150: 1881.6249 | L150: 1729.0631 | M150: 1625.359 | N150: 1583.6553 | O150: 1772.8361 | P150: 1690.7852 | Q150: 1577.0782 | R150: 1451.1955 | S150: 1119.7059 | T150: 1152.4853 | U150: 1483.643 | V150: 1730.5 | W150: 2356.728 | X150: 2679.561 | Y150: 2719.271 | Z150: 2655.385 | AA150: 2392.795 | AB150: 2534.552 | AC150: 2800.888 | AD150: 2730.151 | AE150: 2406.471 | AF150: 1986.27 | AG150: 2542.931 | AH150: 3627.144 | AI150: 3627.144 | AJ150: 3627.144 | AK150: 3627.144 | AL150: 3627.144 | AM150: 3627.144 | AN150: 3627.144 | AO150: 3627.144 | AP150: 3627.144 | AQ150: 3627.144 | AR150: 3627.144 | AS150: 3627.144
C152: <이자비용 배분> | D152: <Allocation>
B153: 204040 | C153: 이자비용(기타영업비용내) | D153: Interest expenses (Other op. income) | J153: 0 | K153: 0 | L153: 0 | M153: 0 | N153: 0 | O153: 0 | P153: 0 | Q153: 0 | R153: 0 | S153: 0 | T153: 0 | U153: 0 | V153: 0 | W153: 0 | X153: 0 | Y153: 0 | Z153: 0 | AA153: 0 | AB153: 0 | AC153: 0 | AD153: 0 | AE153: 0 | AF153: 0 | AG153: 0 | AH153: 0 | AI153: 0 | AJ153: 0 | AK153: 0 | AL153: 0 | AM153: 0 | AN153: 0 | AO153: 0 | AP153: 0 | AQ153: 0 | AR153: 0 | AS153: 0 | BD153: 204040
C154: Portion(%) | D154: Portion(%) | J154: 0 | K154: 0 | L154: 0 | M154: 0 | N154: 0 | O154: 0 | P154: 0 | Q154: 0 | R154: 0 | S154: 0 | T154: 0 | U154: 0 | V154: 0 | W154: 0 | X154: 0 | Y154: 0 | Z154: 0 | AA154: 0 | AB154: 0 | AC154: 0 | AD154: 0 | AE154: 0 | AF154: 0 | AG154: 0 | AH154: 0 | AI154: 0 | AJ154: 0 | AK154: 0 | AL154: 0 | AM154: 0 | AN154: 0 | AO154: 0 | AP154: 0 | AQ154: 0 | AR154: 0 | AS154: 0
B155: 202560 | C155: 이자비용(금융비용내) | D155: Interest expenses (Financial Income) | J155: 563.40683 | K155: 357.26468 | L155: 160.83509 | M155: 134.68476 | N155: 123.4153 | O155: 113.43441 | P155: 105.84587 | Q155: 99.382807 | R155: 98.433517 | S155: 79.752025 | T155: 59.591422 | U155: 42.676 | V155: 61.046 | W155: 70.007 | X155: 105.527 | Y155: 103.081 | Z155: 87.061 | AA155: 76.816 | AB155: 91.114 | AC155: 84.754 | AD155: 78.126 | AE155: 58.036 | AF155: 43.727 | AG155: 64.062 | AH155: 100.546 | AI155: 100.546 | AJ155: 100.546 | AK155: 100.546 | AL155: 100.546 | AM155: 100.546 | AN155: 100.546 | AO155: 100.546 | AP155: 100.546 | AQ155: 100.546 | AR155: 100.546 | AS155: 100.546 | BD155: 202560
C156: Portion(%) | D156: Portion(%) | J156: 1 | K156: 1 | L156: 1 | M156: 1 | N156: 1 | O156: 1 | P156: 1 | Q156: 1 | R156: 1 | S156: 1 | T156: 1 | U156: 1 | V156: 1 | W156: 1 | X156: 1 | Y156: 1 | Z156: 1 | AA156: 1 | AB156: 1 | AC156: 1 | AD156: 1 | AE156: 1 | AF156: 1 | AG156: 1 | AH156: 1 | AI156: 1 | AJ156: 1 | AK156: 1 | AL156: 1 | AM156: 1 | AN156: 1 | AO156: 1 | AP156: 1 | AQ156: 1 | AR156: 1 | AS156: 1
A171: Foreign Exchange I&E
B173: 203620+202240+201420 | C173: 외환거래이익 (Total) | D173: Income from Foreign exchange (Total) | J173: 26.073388 | K173: 25.429503 | L173: 11.502606 | M173: 28.697276 | N173: 36.58403 | O173: 18.119845 | P173: 21.056154 | Q173: 18.696109 | R173: 209.21763 | S173: 218.74762 | T173: 196.56986 | U173: 258.509 | V173: 111.303 | W173: 138.948 | X173: 172.39 | Y173: 279.237 | Z173: 324.691 | AA173: 296.466 | AB173: 222.108 | AC173: 185.619 | AD173: 326.716 | AE173: 354.324 | AF173: 409.93 | AG173: 339.594 | AH173: 520.985 | AI173: 304.226 | AJ173: 304.226 | AK173: 304.226 | AL173: 304.226 | AM173: 304.226 | AN173: 304.226 | AO173: 304.226 | AP173: 304.226 | AQ173: 304.226 | AR173: 304.226 | AS173: 304.226 | BD173: 203620+202240+201420
B174: 203630+202250+201430 | C174: 외환차익 | D174: 외환차익 | J174: 25.769443 | K174: 23.551024 | L174: 10.316105 | M174: 28.229927 | N174: 34.556282 | O174: 15.36346 | P174: 17.816524 | Q174: 10.544148 | R174: 93.960462 | S174: 209.73387 | T174: 178.20837 | U174: 233.861 | V174: 97.694 | W174: 105.688 | X174: 116.141 | Y174: 175.913 | Z174: 189.314 | AA174: 208.945 | AB174: 112.425 | AC174: 104.721 | AD174: 207.11 | AE174: 115.785 | AF174: 250.129 | AG174: 266.814 | AH174: 304.226 | AI174: 304.226 | AJ174: 304.226 | AK174: 304.226 | AL174: 304.226 | AM174: 304.226 | AN174: 304.226 | AO174: 304.226 | AP174: 304.226 | AQ174: 304.226 | AR174: 304.226 | AS174: 304.226 | BD174: 203630+202250+201430
B175: 203640+202260+201440 | C175: 외화환산이익 | D175: 외화환산이익 | J175: 0.303945 | K175: 1.878479 | L175: 1.186501 | M175: 0.467349 | N175: 2.027748 | O175: 2.756385 | P175: 3.23963 | Q175: 8.151961 | R175: 115.25716 | S175: 9.013754 | T175: 18.361484 | U175: 24.648 | V175: 13.609 | W175: 33.26 | X175: 56.249 | Y175: 103.324 | Z175: 135.377 | AA175: 87.521 | AB175: 109.683 | AC175: 80.898 | AD175: 119.606 | AE175: 238.539 | AF175: 159.801 | AG175: 72.78 | AH175: 216.759 | AI175: 0 | AJ175: 0 | AK175: 0 | AL175: 0 | AM175: 0 | AN175: 0 | AO175: 0 | AP175: 0 | AQ175: 0 | AR175: 0 | AS175: 0 | BD175: 203640+202260+201440
B176: 203650+202270+201450 | C176: 기타외환거래이익 | D176: 기타외환거래이익 | J176: 0 | K176: 0 | L176: 0 | M176: 0 | N176: 0 | O176: 0 | P176: 0 | Q176: 0 | R176: 0 | S176: 0 | T176: 0 | U176: 0 | V176: 0 | W176: 0 | X176: 0 | Y176: 0 | Z176: 0 | AA176: 0 | AB176: 0 | AC176: 0 | AD176: 0 | AE176: 0 | AF176: 0 | AG176: 0 | AH176: 0 | AI176: 0 | AJ176: 0 | AK176: 0 | AL176: 0 | AM176: 0 | AN176: 0 | AO176: 0 | AP176: 0 | AQ176: 0 | AR176: 0 | AS176: 0 | BD176: 203650+202270+201450
B178: 204050+202570+201850 | C178: 외환거래손실 (Total) | D178: Expenses from Foreign exchange (Total) | J178: 25.24249 | K178: 38.479121 | L178: 12.643112 | M178: 18.103409 | N178: 18.967259 | O178: 21.006307 | P178: 47.571997 | Q178: 19.868921 | R178: 122.99958 | S178: 257.2655 | T178: 220.89728 | U178: 251.551 | V178: 125.478 | W178: 141.152 | X178: 203.652 | Y178: 258.751 | Z178: 247.313 | AA178: 497.155 | AB178: 137.332 | AC178: 137.98 | AD178: 321.906 | AE178: 162.675 | AF178: 348.196 | AG178: 321.06 | AH178: 381.932 | AI178: 289.735 | AJ178: 289.735 | AK178: 289.735 | AL178: 289.735 | AM178: 289.735 | AN178: 289.735 | AO178: 289.735 | AP178: 289.735 | AQ178: 289.735 | AR178: 289.735 | AS178: 289.735 | BD178: 204050+202570+201850
B179: 204060+202580+201860 | C179: 외환차손 | D179: 외환차손 | J179: 17.406126 | K179: 36.110731 | L179: 9.891897 | M179: 16.922297 | N179: 17.383995 | O179: 13.403332 | P179: 17.646017 | Q179: 15.012122 | R179: 88.939957 | S179: 218.01068 | T179: 195.80655 | U179: 234.624 | V179: 74.003 | W179: 105.052 | X179: 139.925 | Y179: 206.814 | Z179: 166.977 | AA179: 201.472 | AB179: 100.367 | AC179: 100.498 | AD179: 195.38 | AE179: 96.832 | AF179: 262.618 | AG179: 247.394 | AH179: 289.735 | AI179: 289.735 | AJ179: 289.735 | AK179: 289.735 | AL179: 289.735 | AM179: 289.735 | AN179: 289.735 | AO179: 289.735 | AP179: 289.735 | AQ179: 289.735 | AR179: 289.735 | AS179: 289.735 | BD179: 204060+202580+201860
B180: 204070+202590+201870 | C180: 외화환산손실 | D180: 외화환산손실 | J180: 7.836364 | K180: 2.36839 | L180: 2.751215 | M180: 1.181112 | N180: 1.583264 | O180: 7.602975 | P180: 29.92598 | Q180: 4.856799 | R180: 34.05962 | S180: 39.254817 | T180: 25.090731 | U180: 16.927 | V180: 51.475 | W180: 36.1 | X180: 63.727 | Y180: 51.937 | Z180: 80.336 | AA180: 295.683 | AB180: 36.965 | AC180: 37.482 | AD180: 126.526 | AE180: 65.843 | AF180: 85.578 | AG180: 73.666 | AH180: 92.197 | AI180: 0 | AJ180: 0 | AK180: 0 | AL180: 0 | AM180: 0 | AN180: 0 | AO180: 0 | AP180: 0 | AQ180: 0 | AR180: 0 | AS180: 0 | BD180: 204070+202590+201870
B181: 204080+202600+201880 | C181: 기타외환거래손실 | D181: 기타외환거래손실 | J181: 0 | K181: 0 | L181: 0 | M181: 0 | N181: 0 | O181: 0 | P181: 0 | Q181: 0 | R181: 0 | S181: 0 | T181: 0 | U181: 0 | V181: 0 | W181: 0 | X181: 0 | Y181: 0 | Z181: 0 | AA181: 0 | AB181: 0 | AC181: 0 | AD181: 0 | AE181: 0 | AF181: 0 | AG181: 0 | AH181: 0 | AI181: 0 | AJ181: 0 | AK181: 0 | AL181: 0 | AM181: 0 | AN181: 0 | AO181: 0 | AP181: 0 | AQ181: 0 | AR181: 0 | AS181: 0 | BD181: 204080+202600+201880
C183: 환율 (Econ) | D183: 환율 (Econ)
C184: KRW/US$ (Yr-end) | D184: KRW/US$ (Yr-end) | J184: 1264.5 | K184: 1313.5 | L184: 1186.2 | M184: 1192.6 | N184: 1035.1 | O184: 1011.6 | P184: 929.8 | Q184: 936.1 | R184: 1259.5 | S184: 1164.5 | T184: 1134.8 | U184: 1151.8 | V184: 1070.6 | W184: 1055.4 | X184: 1099.3 | Y184: 1172.5 | Z184: 1207.7 | AA184: 1070.5 | AB184: 1115.7 | AC184: 1156.4 | AD184: 1086.3 | AE184: 1188.8 | AF184: 1264.5 | AG184: 1288 | AH184: 1472.5 | AI184: 1400 | AJ184: #N/A | AK184: #N/A | AL184: #N/A | AM184: #N/A | AN184: #N/A | AO184: #N/A | AP184: #N/A | AQ184: #N/A | AR184: #N/A | AS184: #N/A
C185: 변동률(%) | D185: Change Rate(%) | J185: 0 | K185: 3.8750494 | L185: -9.6916635 | M185: 0.53953802 | N185: -13.20644 | O185: -2.270312 | P185: -8.0862001 | Q185: 0.67756507 | R185: 34.547591 | S185: -7.5426757 | T185: -2.5504508 | U185: 1.4980613 | V185: -7.049835 | W185: -1.4197646 | X185: 4.1595604 | Y185: 6.6587829 | Z185: 3.0021322 | AA185: -11.360437 | AB185: 4.222326 | AC185: 3.647934 | AD185: -6.0619163 | AE185: 9.4356992 | AF185: 6.3677658 | AG185: 1.8584421 | AH185: 14.324534 | AI185: -4.9235993 | AJ185: 0 | AK185: 0 | AL185: 0 | AM185: 0 | AN185: 0 | AO185: 0 | AP185: 0 | AQ185: 0 | AR185: 0 | AS185: 0
C186: KRW/US$ (Yr-average) | D186: KRW/US$ (Yr-average) | J186: 1130.36 | K186: 1290.78 | L186: 1251.65 | M186: 1191.74 | N186: 1146.04 | O186: 1024.29 | P186: 955.35 | Q186: 929.33 | R186: 1100.13 | S186: 1277.46 | T186: 1156.45 | U186: 1108.18 | V186: 1126.84 | W186: 1095.02 | X186: 1052.89 | Y186: 1130.97 | Z186: 1160.78 | AA186: 1130.85 | AB186: 1100.13 | AC186: 1165.29 | AD186: 1180.23 | AE186: 1143.98 | AF186: 1291.24 | AG186: 1305.61 | AH186: 1363.53 | AI186: 1450.65 | AJ186: #N/A | AK186: #N/A | AL186: #N/A | AM186: #N/A | AN186: #N/A | AO186: #N/A | AP186: #N/A | AQ186: #N/A | AR186: #N/A | AS186: #N/A
C187: 변동률(%) | D187: Change Rate(%) | J187: 0 | K187: 14.191939 | L187: -3.0315003 | M187: -4.7864818 | N187: -3.8347291 | O187: -10.623538 | P187: -6.7305158 | Q187: -2.7236091 | R187: 18.378832 | S187: 16.119004 | T187: -9.4727036 | U187: -4.1739807 | V187: 1.683842 | W187: -2.8238259 | X187: -3.8474183 | Y187: 7.4157794 | Z187: 2.6357905 | AA187: -2.5784386 | AB187: -2.7165407 | AC187: 5.9229364 | AD187: 1.2820843 | AE187: -3.0714352 | AF187: 12.872603 | AG187: 1.1128837 | AH187: 4.4362405 | AI187: 6.3892984 | AJ187: 0 | AK187: 0 | AL187: 0 | AM187: 0 | AN187: 0 | AO187: 0 | AP187: 0 | AQ187: 0 | AR187: 0 | AS187: 0
C188: KRW/100Yen (Yr-end) | D188: KRW/100Yen (Yr-end) | J188: 1101.52 | K188: 1009.4 | L188: 1012.87 | M188: 1119.6 | N188: 1012.07 | O188: 860.04 | P188: 781.83 | Q188: 833.33 | R188: 1393.89 | S188: 1262.82 | T188: 1397.08 | U188: 1485.16 | V188: 1247.5 | W188: 1004.66 | X188: 920.14 | Y188: 972.01 | Z188: 1036.81 | AA188: 949.11 | AB188: 1013.18 | AC188: 1063.47 | AD188: 1054.26 | AE188: 1030.24 | AF188: 953.18 | AG188: 912.66 | AH188: 936.48 | AI188: 956.69 | AJ188: #N/A | AK188: #N/A | AL188: #N/A | AM188: #N/A | AN188: #N/A | AO188: #N/A | AP188: #N/A | AQ188: #N/A | AR188: #N/A | AS188: #N/A
C189: 변동률(%) | D189: Change Rate(%) | J189: 0 | K189: -8.3629893 | L189: 0.34376858 | M189: 10.537384 | N189: -9.604323 | O189: -15.021688 | P189: -9.0937631 | Q189: 6.5871097 | R189: 67.267469 | S189: -9.403181 | T189: 10.631761 | U189: 6.3045781 | V189: -16.002316 | W189: -19.466132 | X189: -8.4127964 | Y189: 5.6371856 | Z189: 6.6665981 | AA189: -8.4586376 | AB189: 6.7505347 | AC189: 4.96358 | AD189: -0.86603289 | AE189: -2.2783754 | AF189: -7.4798105 | AG189: -4.2510334 | AH189: 2.6099533 | AI189: 2.1580813 | AJ189: 0 | AK189: 0 | AL189: 0 | AM189: 0 | AN189: 0 | AO189: 0 | AP189: 0 | AQ189: 0 | AR189: 0 | AS189: 0
C190: KRW/100Yen (Yr-average) | D190: KRW/100Yen (Yr-average) | J190: 1048.87 | K190: 1062.69 | L190: 999.42 | M190: 1029.19 | N190: 1059.68 | O190: 931.6 | P190: 821.33 | Q190: 789.91 | R190: 1073.38 | S190: 1364.66 | T190: 1319.65 | U190: 1390.6 | V190: 1412.82 | W190: 1123.55 | X190: 996.36 | Y190: 934.51 | Z190: 1068.13 | AA190: 1008.31 | AB190: 996.32 | AC190: 1069.34 | AD190: 1105.07 | AE190: 1041.86 | AF190: 984.23 | AG190: 931.33 | AH190: 900.41 | AI190: 964.57 | AJ190: #N/A | AK190: #N/A | AL190: #N/A | AM190: #N/A | AN190: #N/A | AO190: #N/A | AP190: #N/A | AQ190: #N/A | AR190: #N/A | AS190: #N/A
C191: 변동률(%) | D191: Change Rate(%) | K191: 1.3176085 | L191: -5.9537589 | M191: 2.9787277 | N191: 2.9625239 | O191: -12.086668 | P191: -11.836625 | Q191: -3.8255025 | R191: 35.886367 | S191: 27.136708 | T191: -3.2982574 | U191: 5.3764256 | V191: 1.5978714 | W191: -20.474654 | X191: -11.320368 | Y191: -6.2075956 | Z191: 14.298402 | AA191: -5.6004419 | AB191: -1.1891184 | AC191: 7.3289706 | AD191: 3.3413133 | AE191: -5.7199996 | AF191: -5.5314534 | AG191: -5.37476 | AH191: -3.3199832 | AI191: 7.1256428 | AJ191: 0 | AK191: 0 | AL191: 0 | AM191: 0 | AN191: 0 | AO191: 0 | AP191: 0 | AQ191: 0 | AR191: 0 | AS191: 0
C193: (unit : 십억원 KRW) | D193: (unit : 십억원 USD)
C194: US$ 자산 | D194: US$ Asset
C195: US$ 부채 | D195: US$ Debt
...

Sheet Annual(ctrlv)
C14: Annual | D14: BaseA
B17: Period_CY_ | J17: 2014.12 | K17: 2015.12 | L17: 2016.12 | M17: 2017.12 | N17: 2018.12 | O17: 2019.12 | P17: 2020.12 | Q17: 2021.12 | R17: 2022.12 | S17: 2023.12 | T17: 2024.12 | U17: 2025.12 | V17: 2026.12 | W17: 2027.12 | X17: 2028.12 | Y17: 2029.12
B18: Period_FY_ | J18: 2014A | K18: 2015A | L18: 2016A | M18: 2017A | N18: 2018A | O18: 2019A | P18: 2020A | Q18: 2021A | R18: 2022A | S18: 2023A | T18: 2024A | U18: 2025F | V18: 2026F | W18: 2027F | X18: 2028F | Y18: 2029F
A25: Income Statement
B27: 200000 | C27: 매출액 | D27: Sales | J27: 17276.48 | K27: 19233.18 | L27: 18825.015 | M27: 16887.09 | N27: 16730.894 | O27: 17278.792 | P27: 16970.859 | Q27: 18065.534 | R27: 21239.082 | S27: 29651.357 | T27: 32670.268 | U27: 35996.545 | V27: 39661.483 | W27: 43699.56 | X27: 48148.769 | Y27: 53050.968
B29: 200001 | C29: 순매출액 (직접 입력) | D29: Net sales (manual)
B31: 200360 | C31: 매출원가 | D31: Cost of Sales | J31: 15864.906 | K31: 17508.138 | L31: 16895.275 | M31: 15108.126 | N31: 15069.747 | O31: 15552.887 | P31: 15573.996 | Q31: 16268.298 | R31: 19726.334 | S31: 27948.549 | T31: 32887.201 | U31: 36235.565 | V31: 39924.838 | W31: 43989.729 | X31: 48468.481 | Y31: 53403.231
B33: 200810 | C33: 매출총이익 | D33: Gross Profit | J33: 1411.574 | K33: 1725.042 | L33: 1929.74 | M33: 1778.964 | N33: 1661.147 | O33: 1725.905 | P33: 1396.863 | Q33: 1797.236 | R33: 1512.748 | S33: 1702.808 | T33: -216.933 | U33: -239.01973 | V33: -263.35518 | W33: -290.16832 | X33: -319.7114 | Y33: -352.26236
B35: 200820 | C35: 판매비와 관리비 | D35: SG&A | J35: 582.379 | K35: 635.714 | L35: 770.781 | M35: 792.859 | N35: 821.158 | O35: 866.238 | P35: 847.891 | Q35: 1043.732 | R35: 937.846 | S35: 917.378 | T35: 1046.487 | U35: 1152.4978 | V35: 1243.3807 | W35: 1351.7707 | X35: 1476.7942 | Y35: 1618.3513
B36: 200821 | C36: 인건비및복리후생비 | D36: Salaries and Wages | J36: 310.644 | K36: 330.179 | L36: 419.216 | M36: 431.846 | N36: 475.484 | O36: 466.614 | P36: 498.26 | Q36: 513.969 | R36: 538.377 | S36: 583.153 | T36: 633.54 | U36: 698.04298 | V36: 769.11324 | W36: 847.41942 | X36: 933.69823 | Y36: 1028.7614
B37: 200822 | C37: 일반관리비 | D37: General & Administrative Expenses | J37: 65.62 | K37: 57.974 | L37: 64.359 | M37: 76.622 | N37: 91.086 | O37: 85.774 | P37: 77.47 | Q37: 71.581 | R37: 91.261 | S37: 86.619 | T37: 97.144 | U37: 107.03458 | V37: 117.93215 | W37: 129.93925 | X37: 143.16883 | Y37: 157.74536
B38: 200823 | C38: 판매비 | D38: Sales Expenses | J38: 84.189 | K38: 89.96 | L38: 121.97 | M38: 119.899 | N38: 132.945 | O38: 128.449 | P38: 61.645 | Q38: 227.182 | R38: 90.93 | S38: 66.057 | T38: 100.249 | U38: 110.45571 | V38: 121.7016 | W38: 134.09248 | X38: 147.74492 | Y38: 162.78735
B39: 201130 | C39: 연구개발비 | D39: Research & Development | J39: 60.383 | K39: 63.472 | L39: 87.62 | M39: 85.934 | N39: 109.949 | O39: 151.432 | P39: 177.527 | Q39: 190.025 | R39: 178.612 | S39: 138.787 | T39: 154.923 | U39: 170.69627 | V39: 188.07547 | W39: 207.2241 | X39: 228.32233 | Y39: 251.56865
B40: 201160 | C40: 광고선전비 | D40: Advertising Expenses | J40: 13.801 | K40: 14.455 | L40: 14.813 | M40: 10.592 | N40: 0 | O40: 0 | P40: 0 | Q40: 0 | R40: 0 | S40: 0 | T40: 0 | U40: 0 | V40: 0 | W40: 0 | X40: 0 | Y40: 0
B41: 201080 | C41: 유형자산 감가상각비 | D41: Depreciation (SG&A) | J41: 9.091 | K41: 10.094 | L41: 11.269 | M41: 11.852 | N41: 11.694 | O41: 17.807 | P41: 27.58 | Q41: 34.378 | R41: 34.859 | S41: 37.749 | T41: 53.999 | U41: 58.062225 | V41: 39.129134 | W41: 26.369798 | X41: 17.771061 | Y41: 11.976225
B42: 201090+201100 | C42: 무형자산상각비 | D42: Amortization (SG&A) | J42: 38.651 | K42: 69.58 | L42: 51.534 | M42: 56.114 | N42: 0 | O42: 16.162 | P42: 5.409 | Q42: 6.597 | R42: 3.807 | S42: 5.013 | T42: 6.632 | U42: 8.2060772 | V42: 7.4290818 | W42: 6.7256564 | X42: 6.0888352 | Y42: 5.5123116
B44: 203590 | C44: 기타영업수익 | D44: Other Operating Income | J44: 0 | K44: 0 | L44: 0 | M44: 0 | N44: 0 | O44: 0 | P44: 0 | Q44: 0 | R44: 0 | S44: 0 | T44: 0 | U44: 0 | V44: 0 | W44: 0 | X44: 0 | Y44: 0
B45: 203600 | C45: 이자수익 | D45: Interest Income | J45: 0 | K45: 0 | L45: 0 | M45: 0 | N45: 0 | O45: 0 | P45: 0 | Q45: 0 | R45: 0 | S45: 0 | T45: 0 | U45: 0 | V45: 0 | W45: 0 | X45: 0 | Y45: 0
B46: 203610 | C46: 배당금수익 | D46: Dividend Income | J46: 0 | K46: 0 | L46: 0 | M46: 0 | N46: 0 | O46: 0 | P46: 0 | Q46: 0 | R46: 0 | S46: 0 | T46: 0 | U46: 0 | V46: 0 | W46: 0 | X46: 0 | Y46: 0
B47: 203620 | C47: 외환거래이익 | D47: Gains on Foreign Exchange | J47: 0 | K47: 0 | L47: 0 | M47: 0 | N47: 0 | O47: 0 | P47: 0 | Q47: 0 | R47: 0 | S47: 0 | T47: 0 | U47: 0 | V47: 0 | W47: 0 | X47: 0 | Y47: 0
B48: 203800 | C48: 투자자산평가이익 | D48: Gains on Investment Assets | J48: 0 | K48: 0 | L48: 0 | M48: 0 | N48: 0 | O48: 0 | P48: 0 | Q48: 0 | R48: 0 | S48: 0 | T48: 0 | U48: 0 | V48: 0 | W48: 0 | X48: 0 | Y48: 0
B49: 203591 | C49: 기타 기타수익 | D49: Others | J49: 0 | K49: 0 | L49: 0 | M49: 0 | N49: 0 | O49: 0 | P49: 0 | Q49: 0 | R49: 0 | S49: 0 | T49: 0 | U49: 0 | V49: 0 | W49: 0 | X49: 0 | Y49: 0
B51: 204030 | C51: 기타영업비용 | D51: Other Operating Expenses | J51: 0 | K51: 0 | L51: 0 | M51: 0 | N51: 0 | O51: 0 | P51: 0 | Q51: 0 | R51: 0 | S51: 0 | T51: 0 | U51: 0 | V51: 0 | W51: 0 | X51: 0 | Y51: 0
B52: 204040 | C52: 이자비용 | D52: Interest Expenses | J52: 0 | K52: 0 | L52: 0 | M52: 0 | N52: 0 | O52: 0 | P52: 0 | Q52: 0 | R52: 0 | S52: 0 | T52: 0 | U52: 0 | V52: 0 | W52: 0 | X52: 0 | Y52: 0
B53: 204050 | C53: 외환거래손실 | D53: Losses on Foreign Exchange | J53: 0 | K53: 0 | L53: 0 | M53: 0 | N53: 0 | O53: 0 | P53: 0 | Q53: 0 | R53: 0 | S53: 0 | T53: 0 | U53: 0 | V53: 0 | W53: 0 | X53: 0 | Y53: 0
B54: 204240 | C54: 투자자산평가손실 | D54: Losses on Investment Assets | J54: 0 | K54: 0 | L54: 0 | M54: 0 | N54: 0 | O54: 0 | P54: 0 | Q54: 0 | R54: 0 | S54: 0 | T54: 0 | U54: 0 | V54: 0 | W54: 0 | X54: 0 | Y54: 0
B55: 204031 | C55: 기타 기타비용 | D55: Others | J55: 0 | K55: 0 | L55: 0 | M55: 0 | N55: 0 | O55: 0 | P55: 0 | Q55: 0 | R55: 0 | S55: 0 | T55: 0 | U55: 0 | V55: 0 | W55: 0 | X55: 0 | Y55: 0
B57: 201370 | C57: 영업이익 | D57: Operating Income | J57: 829.195 | K57: 1089.328 | L57: 1158.959 | M57: 986.105 | N57: 839.989 | O57: 859.667 | P57: 548.972 | Q57: 753.504 | R57: 574.902 | S57: 785.43 | T57: -1263.42 | U57: -1391.5176 | V57: -1506.7359 | W57: -1641.939 | X57: -1796.5056 | Y57: -1970.6137
... B108: 203300 | C108: 총포괄이익 | D108: Total Comprehensive Income | J108: 453.414 | K108: 701.215 | L108: 842.416 | M108: 444.145 | N108: 328.166 | O108: 540.166 | P108: 137.01 | Q108: 710.987 | R108: 615.028 | S108: 626.027 | T108: -689.8 | U108: -1041.3797 | V108: -1134.9453 | W108: -1242.9889 | X108: -1365.3063 | Y108: -1502.2412
A117: Balance Sheet
B119: 110000 | C119: 자산총계 | D119: Assets | J119: 18244.6 | K119: 19350.103 | L119: 19873.443 | M119: 18431.902 | N119: 18054.609 | O119: 18226.972 | P119: 17939.274 | Q119: 19637.264 | R119: 20911.708 | S119: 23714.495 | T119: 27005.385 | U119: 23159.065 | V119: 24809.063 | W119: 26823.987 | X119: 29220.405 | Y119: 32030.162
B121: 110010 | C121: 비유동자산 | D121: Non-Current Assets | J121: 4803.452 | K121: 5121.679 | L121: 4935.519 | M121: 5182.062 | N121: 4717.841 | O121: 5054.979 | P121: 4540.331 | Q121: 5110.86 | R121: 5394.964 | S121: 5101.065 | T121: 5904.722 | U121: 5561.0318 | V121: 5292.6432 | W121: 5075.2756 | X121: 4892.5399 | Y121: 4733.3679
B122: 110020 | C122: 유형자산 | D122: Tangible Assets | J122: 1710.644 | K122: 1754.185 | L122: 1498.089 | M122: 1398.791 | N122: 1436.574 | O122: 1419.749 | P122: 967.47 | Q122: 1012.128 | R122: 1048.81 | S122: 1204.52 | T122: 1289.154 | U122: 1061.8577 | V122: 908.67878 | W122: 805.44887 | X122: 735.88046 | Y122: 688.99711
B123: 190010 | C123: 토지 | D123: Land | J123: 587.831 | K123: 590.645 | L123: 320.006 | M123: 330.733 | N123: 333.706 | O123: 349.836 | P123: 365.665 | Q123: 397.099 | R123: 363 | S123: 363.045 | T123: 368.27 | U123: 368.27 | V123: 368.27 | W123: 368.27 | X123: 368.27 | Y123: 368.27
B124: 190020 | C124: 설비자산 | D124: Plant Assets | J124: 1035.144 | K124: 1049.46 | L124: 1118.283 | M124: 986.336 | N124: 899.627 | O124: 981.35 | P124: 521.927 | Q124: 505.132 | R124: 487.634 | S124: 628.474 | T124: 677.768 | U124: 456.75954 | V124: 307.81812 | W124: 207.44394 | X124: 139.80005 | Y124: 94.21366
B125: 190150 | C125: 건설중인자산 | D125: Construction in Progress | J125: 65.953 | K125: 94.092 | L125: 41.176 | M125: 65.922 | N125: 187.959 | O125: 73.872 | P125: 64.061 | Q125: 92.182 | R125: 178.217 | S125: 193.204 | T125: 223.833 | U125: 223.833 | V125: 223.833 | W125: 223.833 | X125: 223.833 | Y125: 223.833
B126: 190160 | C126: 기타유형자산 | D126: Other Property Plant Equipment | J126: 21.716 | K126: 19.988 | L126: 18.624 | M126: 15.8 | N126: 15.282 | O126: 14.691 | P126: 15.817 | Q126: 17.715 | R126: 19.959 | S126: 19.797 | T126: 19.283 | U126: 12.995146 | V126: 8.7576529 | W126: 5.9019332 | X126: 3.9774145 | Y126: 2.6804482
B127: 110610 | C127: 무형자산 | D127: Intangible Assets | J127: 874.253 | K127: 857.312 | L127: 810.336 | M127: 760.228 | N127: 711.198 | O127: 697.843 | P127: 703.436 | Q127: 718.28 | R127: 720.626 | S127: 724.427 | T127: 750.741 | U127: 738.23515 | V127: 726.91341 | W127: 716.66368 | X127: 707.38445 | Y127: 698.98383
B128: 190170 | C128: 영업권 | D128: Goodwill | J128: 593.621 | K128: 618.594 | L128: 618.594 | M128: 618.594 | N128: 618.594 | O128: 618.594 | P128: 617.684 | Q128: 617.684 | R128: 617.684 | S128: 617.684 | T128: 618.663 | U128: 618.663 | V128: 618.663 | W128: 618.663 | X128: 618.663 | Y128: 618.663
B129: 110611 | C129: 기타무형자산 | D129: Other Intangible Assets | J129: 280.632 | K129: 238.718 | L129: 191.742 | M129: 141.634 | N129: 92.604 | O129: 79.249 | P129: 85.752 | Q129: 100.596 | R129: 102.942 | S129: 106.743 | T129: 132.078 | U129: 119.57215 | V129: 108.25041 | W129: 98.000684 | X129: 88.721453 | Y129: 80.32083
B130: 190311 | C130: 투자자산 | D130: Investment Assets | J130: 739.779 | K130: 870.424 | L130: 810.279 | M130: 1123.441 | N130: 559.201 | O130: 671.178 | P130: 1018.405 | Q130: 1353.343 | R130: 1557.3 | S130: 1217.043 | T130: 1390.132 | U130: 1286.244 | V130: 1182.356 | W130: 1078.468 | X130: 974.58 | Y130: 870.692
B131: 111450 | C131: 관계기업등지분관련투자자산 | D131: Investments in Associates, Subs and JVs | J131: 124.004 | K131: 107.986 | L131: 128.145 | M131: 79.319 | N131: 45.891 | O131: 62.049 | P131: 68.497 | Q131: 87.164 | R131: 88.958 | S131: 86.608 | T131: 168.064 | U131: 64.176 | V131: -39.712 | W131: -143.6 | X131: -247.488 | Y131: -351.376
... B187: 120620 | C187: 비지배주주지분 | D187: Non-Controlling Interests Equity | J187: 1495.791 | K187: 1670.344 | L187: 1795.62 | M187: 2005.292 | N187: 2017.762 | O187: 2052.426 | P187: 2134.626 | Q187: 2212.554 | R187: 2237.6 | S187: 2318.864 | T187: 1644.003 | U187: 772.25615 | V187: -172.46036 | W187: -1201.4375 | X187: -2325.8072 | Y187: -3556.9693
A197: Cash Flow Statements
B199: 400000 | C199: 영업활동현금흐름 | D199: Cash Flows from Operating Activities | J199: 426.038 | K199: 596.001 | L199: 1086.52 | M199: 514.404 | N199: 249.524 | O199: 478.916 | P199: 1729.721 | Q199: 1009.401 | R199: -143.474 | S199: -714.716 | T199: -118.8 | U199: 1195.1265 | V199: 2752.9655 | W199: 5388.4907 | X199: 9716.5904 | Y199: 16711.998
B200: 400010 | C200: 당기순이익 | D200: Net Income | J200: 479.34 | K200: 663.778 | L200: 731.713 | M200: 371.564 | N200: 535.303 | O200: 573.331 | P200: 227.697 | Q200: 554.377 | R200: 470.876 | S200: 654.28 | T200: -766.221 | U200: -1117.8007 | V200: -1211.3663 | W200: -1319.4099 | X200: -1441.7273 | Y200: -1578.6622
B201: 400030 | C201: 현금유출이없는비용 | D201: Non-Cash Expenses | J201: 921.247 | K201: 1109.92 | L201: 1196.431 | M201: 1344.703 | N201: 1026.125 | O201: 982.401 | P201: 955.776 | Q201: 1192.079 | R201: 1065.328 | S201: 1104.007 | T201: 1353.699 | U201: 953.00467 | V201: 850.8998 | W201: 768.92802 | X201: 699.2563 | Y201: 636.46548
B202: 400140 | C202: 유형자산감가상각비 | D202: Depreciation | J202: 112.727 | K202: 124.08 | L202: 136.193 | M202: 134.488 | N202: 116.35 | O202: 164.711 | P202: 163.159 | Q202: 161.982 | R202: 172.274 | S202: 186.602 | T202: 211.39 | U202: 227.29632 | V202: 153.17891 | W202: 103.2299 | X202: 69.568412 | Y202: 46.883352
B203: 400150+400160 | C203: 무형자산상각비 | D203: Amortization | J203: 41.327 | K203: 71.739 | L203: 54.268 | M203: 58.873 | N203: 55.768 | O203: 19.543 | P203: 8.498 | Q203: 9.519 | R203: 9.434 | S203: 9.512 | T203: 10.107 | U203: 12.505854 | V203: 11.321732 | W203: 10.24973 | X203: 9.2792306 | Y203: 8.4006233
B204: 400180 | C204: 외환거래손실 | D204: Losses on Foreign Exchange | J204: 80.112 | K204: 96.95 | L204: 110.176 | M204: 346.766 | N204: 37.996 | O204: 40.43 | P204: 266.22 | Q204: 79.449 | R204: 85.578 | S204: 73.666 | T204: 92.674 | U204: 0 | V204: 0 | W204: 0 | X204: 0 | Y204: 0
B205: 400641 | C205: 지분법, 종속, 관계기업관련손실 | D205: Losses in Associates, Subsidiaries and JVs | J205: 18.576 | K205: 6.45 | L205: 11.903 | M205: 19.051 | N205: 30.031 | O205: 8.432 | P205: 3.908 | Q205: 11.014 | R205: 21.214 | S205: 7.916 | T205: 11.704 | U205: 5.59 | V205: 5.59 | W205: 5.59 | X205: 5.59 | Y205: 5.59
B206: 400750 | C206: 법인세비용 | D206: Taxes Expenses | J206: 193.677 | K206: 234.359 | L206: 249.765 | M206: 183.265 | N206: 362.559 | O206: 225.601 | P206: 167.877 | Q206: 299.724 | R206: 282.939 | S206: 285.264 | T206: 0 | U206: -320.2115 | V206: -347.01484 | W206: -377.96562 | X206: -413.00534 | Y206: -452.23249
B207: 400050 | C207: 이자비용 | D207: Interest Expenses | J207: 105.527 | K207: 103.081 | L207: 87.061 | M207: 76.816 | N207: 91.114 | O207: 84.754 | P207: 78.126 | Q207: 58.036 | R207: 43.727 | S207: 64.062 | T207: 100.546 | U207: 100.546 | V207: 100.546 | W207: 100.546 | X207: 100.546 | Y207: 100.546
B208: 400031 | C208: 기타 | D208: Others | J208: 369.301 | K208: 473.261 | L208: 547.065 | M208: 525.444 | N208: 332.307 | O208: 438.93 | P208: 267.988 | Q208: 572.355 | R208: 450.162 | S208: 476.985 | T208: 927.278 | U208: 927.278 | V208: 927.278 | W208: 927.278 | X208: 927.278 | Y208: 927.278
B209: 400790 | C209: 현금유입이없는수익 | D209: Non-Cash Revenues | J209: -265.899 | K209: -342.982 | L209: -335.008 | M209: -294.724 | N209: -392.643 | O209: -296.247 | P209: -319.691 | Q209: -465.394 | R209: -595.664 | S209: -547.42 | T209: -1095.805 | U209: -848.06237 | V209: -842.91171 | W209: -839.12052 | X209: -836.32999 | Y209: -834.27599
B210: 400860 | C210: 외환거래이익 | D210: Gains on Foreign Exchange | J210: -63.911 | K210: -107.076 | L210: -144.09 | M210: -90.726 | N210: -116.722 | O210: -80.897 | P210: -121.12 | Q210: -239.782 | R210: -162.761 | S210: -160.024 | T210: -241.149 | U210: 0 | V210: 0 | W210: 0 | X210: 0 | Y210: 0
B211: 401321 | C211: 지분법, 종속, 관계기업관련이익 | D211: Gains in Associates, Subsidiaries and JVs | J211: -17.723 | K211: -29.872 | L211: -5.669 | M211: -16.726 | N211: -2.535 | O211: -2.907 | P211: -7.193 | Q211: -0.456 | R211: -18.058 | S211: -2.636 | T211: -254.078 | U211: -11.165 | V211: -11.165 | W211: -11.165 | X211: -11.165 | Y211: -11.165
B212: 400810 | C212: 이자수익 | D212: Interest Income | J212: 67.86 | K212: 70.868 | L212: 78.772 | M212: 92.9 | N212: 110.298 | O212: 108.61 | P212: 97.095 | Q212: 100.219 | R212: 162.193 | S212: 179.519 | T212: 216.805 | U212: -19.514374 | V212: -14.363708 | W212: -10.57252 | X212: -7.7819864 | Y212: -5.7279922
B213: 400791 | C213: 기타 | D213: Others | J213: -252.125 | K213: -276.902 | L213: -264.021 | M213: -280.172 | N213: -383.684 | O213: -321.053 | P213: -288.473 | Q213: -325.375 | R213: -577.038 | S213: -564.279 | T213: -817.383 | U213: -817.383 | V213: -817.383 | W213: -817.383 | X213: -817.383 | Y213: -817.383
B214: 401490 | C214: 영업관련자산부채변동 | D214: Changes in A/L from Operating Activities | J214: -403.943 | K214: -668.491 | L214: -292.198 | M214: -630.656 | N214: -489.8 | O214: -652.029 | P214: 1010.745 | Q214: -162.48 | R214: -827.056 | S214: -1816.344 | T214: 588 | U214: 1965.891 | V214: 3692.5972 | W214: 6487.187 | X214: 10972.236 | Y214: 18128.142
B215: 401500 | C215: 영업활동자산의감소 | D215: Decr.(Incr.) in Operating Assets | J215: -816.935 | K215: -1005.027 | L215: 236.699 | M215: 1605.499 | N215: -3.172 | O215: -179.893 | P215: 1328.781 | Q215: -1551.93 | R215: -2073.052 | S215: -3356.045 | T215: -1784.501 | U215: -1816.4007 | V215: -2057.2511 | W215: -2334.5034 | X215: -2654.3879 | Y215: -3024.3054
... B247: 403630 | C247: 재무활동현금흐름 | D247: Cash Flows from Financing Activities | J247: -80.221 | K247: 30.709 | L247: -176.854 | M247: -380.936 | N247: -37.29 | O247: 15.264 | P247: 95.488 | Q247: -492.604 | R247: -658.184 | S247: 365.989 | T247: 733.741 | U247: -180.78701 | V247: -180.78701 | W247: -180.78701 | X247: -180.78701 | Y247: -180.78701
B248: 403650 - 403980 | C248: 단기사채의증가(감소) | D248: Incr.(Decr.) in Short-Term Bonds | J248: 0 | K248: 0 | L248: 0 | M248: 0 | N248: 0 | O248: 0 | P248: 0 | Q248: 0 | R248: 0 | S248: 0 | T248: 0 | U248: 0 | V248: 0 | W248: 0 | X248: 0 | Y248: 0
B249: 403660 - 403990 | C249: 단기차입금의증가(감소) | D249: Incr.(Decr.) in Short-Term Borrowings | J249: 104.803 | K249: 1.089 | L249: -33.915 | M249: 203.106 | N249: -90.184 | O249: 142.788 | P249: 69.58 | Q249: -182.719 | R249: -52.913 | S249: 166.112 | T249: 492.873 | U249: 0 | V249: 0 | W249: 0 | X249: 0 | Y249: 0
B250: 403680 - 404010 | C250: 유동성장기부채의증가(감소) | D250: Incr.(Decr.) in Current Portion of Lt. Debt | J250: -760.16 | K250: -357.601 | L250: -238.713 | M250: -475.397 | N250: -223.261 | O250: -339.892 | P250: -522.226 | Q250: -444.018 | R250: -444.994 | S250: -441.041 | T250: -355.897 | U250: 0 | V250: 0 | W250: 0 | X250: 0 | Y250: 0
B251: 403750 - 404080 | C251: 사채의증가(감소) | D251: Incr.(Decr.) in (Long-Term)Bonds | J251: 547.961 | K251: 597.92 | L251: 199.124 | M251: 0 | N251: 300 | O251: 300 | P251: 710 | Q251: 300 | R251: 0 | S251: 410 | T251: 300 | U251: 0 | V251: 0 | W251: 0 | X251: 0 | Y251: 0
B252: 403760 - 404090 | C252: 장기차입금의증가(감소) | D252: Incr.(Decr.) in (Long-Term)Borrowings | J252: 261.477 | K252: -104.138 | L252: 5.053 | M252: 0 | N252: 138.249 | O252: 78.974 | P252: 53.648 | Q252: -30.198 | R252: 66.884 | S252: 430.881 | T252: 504.935 | U252: 0 | V252: 0 | W252: 0 | X252: 0 | Y252: 0
B253: 403840 + 403860 - 404170 - 404190 | C253: 자본금, 자본잉여금의 증가(감소) | D253: Incr.(Decr.) in Capital Stock & Capital Surplus | J253: 0.044 | K253: 2.559 | L253: 0 | M253: 0 | N253: 3.61 | O253: 0 | P253: 0 | Q253: 84.209 | R253: 0 | S253: 0 | T253: 0 | U253: 0 | V253: 0 | W253: 0 | X253: 0 | Y253: 0
B254: 403890 - 404220 | C254: 자기주식처분(취득) | D254: Gains(Losses) on Disposition of Treasury Stock | J254: 0 | K254: 0 | L254: 0 | M254: 0 | N254: 0 | O254: 0 | P254: 0 | Q254: 0 | R254: 0 | S254: 0 | T254: 0 | U254: 0 | V254: 0 | W254: 0 | X254: 0 | Y254: 0
B255: 403631 | C255: 기타 | D255: Others | J255: -130.692 | K255: -4.6185278e-14 | L255: 0 | M255: -0.04 | N255: -58.794 | O255: -58.848 | P255: -83.455 | Q255: -88.036 | R255: -112.201 | S255: -105.208 | T255: -113.288 | U255: -113.288 | V255: -113.288 | W255: -113.288 | X255: -113.288 | Y255: -113.288
B256: 400003 | C256: (*) 재무활동에서창출된현금흐름 | D256: (*)Cash Flows from Financing Activities | J256: 23.433 | K256: 139.829 | L256: -68.451 | M256: -272.331 | N256: 69.62 | O256: 123.022 | P256: 227.547 | Q256: -360.762 | R256: -543.224 | S256: 460.744 | T256: 828.623 | U256: -113.288 | V256: -113.288 | W256: -113.288 | X256: -113.288 | Y256: -113.288
B257: 404290 | C257: 이자수입 | D257: Interest Received | J257: 0 | K257: 0 | L257: 0 | M257: 0 | N257: 0 | O257: 0 | P257: 0 | Q257: 0 | R257: 0 | S257: 0 | T257: 0 | U257: 0 | V257: 0 | W257: 0 | X257: 0 | Y257: 0
B258: 404300 | C258: (이자지급) | D258: (Interest Paid) | J258: 0 | K258: 0 | L258: 0 | M258: 0 | N258: 0 | O258: 0 | P258: 0 | Q258: 0 | R258: 0 | S258: 0 | T258: 0 | U258: 0 | V258: 0 | W258: 0 | X258: 0 | Y258: 0
B259: 404310 | C259: 배당금수입 | D259: Divideds Received | J259: 0 | K259: 0 | L259: 0 | M259: 0 | N259: 0 | O259: 0 | P259: 0 | Q259: 0 | R259: 0 | S259: 0 | T259: 0 | U259: 0 | V259: 0 | W259: 0 | X259: 0 | Y259: 0
B260: 404320 | C260: (배당금지급) | D260: (Divideds Paid) | J260: -103.654 | K260: -109.12 | L260: -108.403 | M260: -108.605 | N260: -106.91 | O260: -107.758 | P260: -132.059 | Q260: -131.842 | R260: -114.96 | S260: -94.755 | T260: -94.882 | U260: -67.499009 | V260: -67.499009 | W260: -67.499009 | X260: -67.499009 | Y260: -67.499009
B261: 404330 | C261: 법인세환입 | D261: Refunds of Income Taxes | J261: 0 | K261: 0 | L261: 0 | M261: 0 | N261: 0 | O261: 0 | P261: 0 | Q261: 0 | R261: 0 | S261: 0 | T261: 0 | U261: 0 | V261: 0 | W261: 0 | X261: 0 | Y261: 0
B262: 404340 | C262: (법인세납부) | D262: (Payments of Income Taxes) | J262: 0 | K262: 0 | L262: 0 | M262: 0 | N262: 0 | O262: 0 | P262: 0 | Q262: 0 | R262: 0 | S262: 0 | T262: 0 | U262: 0 | V262: 0 | W262: 0 | X262: 0 | Y262: 0
B264: 404360 | C264: 기타현금흐름 | D264: Other Cash Flows | J264: 0 | K264: 0 | L264: 0 | M264: 0 | N264: 0 | O264: 0 | P264: 0 | Q264: 0 | R264: 0 | S264: 0 | T264: 0 | U264: 0 | V264: 0 | W264: 0 | X264: 0 | Y264: 0
B265: 404370 | C265: 연결범위변동으로인한현금의증가 | D265: Change of Consolidated Scope | J265: 0 | K265: 0 | L265: 0 | M265: 5.137 | N265: 0.147 | O265: 0 | P265: 0 | Q265: 0 | R265: 0 | S265: 0 | T265: 0 | U265: 0 | V265: 0 | W265: 0 | X265: 0 | Y265: 0
B266: 404380 | C266: 환율변동효과 | D266: Difference by Changes in Foreign Exchange Rates | J266: -11.551 | K266: 2.126 | L266: 18.114 | M266: -165.095 | N266: 13.608 | O266: 1.795 | P266: -5.202 | Q266: 21.533 | R266: -4.559 | S266: 17.929 | T266: 98.067 | U266: 0 | V266: 0 | W266: 0 | X266: 0 | Y266: 0
B268: 404390 | C268: 현금및현금성자산의 증가 | D268: Incr.(Decr.) in Cash and Cash Equivalents | J268: 658.821 | K268: -544.976 | L268: 152.579 | M268: -42.742 | N268: 133.946 | O268: 344.819 | P268: 600.835 | Q268: -259.986 | R268: 1047.041 | S268: 231.768 | T268: 924.707 | U268: 1623.4595 | V268: 3131.5034 | W268: 5730.3766 | X268: 10031.498 | Y268: 17007.048
... B270: 404410 | C270: 기말 현금및현금성자산 | D270: Ending Cash and Cash Equivalents | J270: 2542.381 | K270: 1997.405 | L270: 2149.984 | M270: 2107.242 | N270: 2241.188 | O270: 2586.007 | P270: 3186.842 | Q270: 2926.856 | R270: 3973.897 | S270: 4205.665 | T270: 5130.372 | U270: 6753.8315 | V270: 9885.3349 | W270: 15615.712 | X270: 25647.21 | Y270: 42654.258
A281: Shares, Prices, & Dividends
B283: 701100 | C283: 액면가 | D283: Face Value | J283: 5000 | K283: 5000 | L283: 5000 | M283: 5000 | N283: 5000 | O283: 5000 | P283: 5000 | Q283: 5000 | R283: 5000 | S283: 5000 | T283: 5000 | U283: 5000 | V283: 5000 | W283: 5000 | X283: 5000 | Y283: 5000
B285: 701201 | C285: 기말발행주식수 | D285: Shares (FY-end) | J285: 111454.62 | K285: 111454.62 | L285: 111454.62 | M285: 111454.62 | N285: 111454.62 | O285: 111454.62 | P285: 111454.62 | Q285: 112410.46 | R285: 112410.46 | S285: 112410.46 | T285: 112410.46 | U285: 112410.46 | V285: 112410.46 | W285: 112410.46 | X285: 112410.46 | Y285: 112410.46
B286: 701200 | C286: 보통주기말발행주식수 | D286: Common (FY-end) | J286: 111355.76 | K286: 111355.76 | L286: 111355.76 | M286: 111355.76 | N286: 111355.76 | O286: 111355.76 | P286: 111355.76 | Q286: 111355.76 | R286: 111355.76 | S286: 111355.76 | T286: 111355.76 | U286: 111355.76 | V286: 111355.76 | W286: 111355.76 | X286: 111355.76 | Y286: 111355.76
B287: 701700 | C287: 우선주기말발행주식수 | D287: Preferred (FY-end) | J287: 98.856 | K287: 98.856 | L287: 98.856 | M287: 98.856 | N287: 98.856 | O287: 98.856 | P287: 98.856 | Q287: 1054.693 | R287: 1054.693 | S287: 1054.693 | T287: 1054.693 | U287: 1054.693 | V287: 1054.693 | W287: 1054.693 | X287: 1054.693 | Y287: 1054.693
B288: 701301 | C288: 평균발행주식수 | D288: Shares (Wgt. Shrs) | J288: 111454.62 | K288: 111454.62 | L288: 111454.62 | M288: 111454.62 | N288: 111454.62 | O288: 111454.62 | P288: 111454.62 | Q288: 111629.34 | R288: 112410.46 | S288: 112410.46 | T288: 112410.46 | U288: 112410.46 | V288: 112410.46 | W288: 112410.46 | X288: 112410.46 | Y288: 112410.46
B289: 701300 | C289: 보통주평균발행주식수 | D289: Common (Wgt.) | J289: 111355.76 | K289: 111355.76 | L289: 111355.76 | M289: 111355.76 | N289: 111355.76 | O289: 111355.76 | P289: 111355.76 | Q289: 111355.76 | R289: 111355.76 | S289: 111355.76 | T289: 111355.76 | U289: 111355.76 | V289: 111355.76 | W289: 111355.76 | X289: 111355.76 | Y289: 111355.76
B290: 701800 | C290: 우선주평균발행주식수 | D290: Preferred (Wgt.) | J290: 98.856 | K290: 98.856 | L290: 98.856 | M290: 98.856 | N290: 98.856 | O290: 98.856 | P290: 98.856 | Q290: 273.576 | R290: 1054.693 | S290: 1054.693 | T290: 1054.693 | U290: 1054.693 | V290: 1054.693 | W290: 1054.693 | X290: 1054.693 | Y290: 1054.693
B291: 701501 | C291: 수정기말발행주식수 | D291: Shares (Adj. FY-end) | J291: 111546.01 | K291: 111546.01 | L291: 111546.01 | M291: 111546.01 | N291: 111546.01 | O291: 111546.01 | P291: 111546.01 | Q291: 112410.46 | R291: 112410.46 | S291: 112410.46 | T291: 112410.46 | U291: 112410.46 | V291: 112410.46 | W291: 112410.46 | X291: 112410.46 | Y291: 112410.46
B292: 701500 | C292: 보통주수정기말발행주식수 | D292: Common (Adj. FY-end) | J292: 111355.76 | K292: 111355.76 | L292: 111355.76 | M292: 111355.76 | N292: 111355.76 | O292: 111355.76 | P292: 111355.76 | Q292: 111355.76 | R292: 111355.76 | S292: 111355.76 | T292: 111355.76 | U292: 111355.76 | V292: 111355.76 | W292: 111355.76 | X292: 111355.76 | Y292: 111355.76
B293: 702000 | C293: 우선주수정기말발행주식수 | D293: Preferred (Adj. FY-end) | J293: 190.24649 | K293: 190.24649 | L293: 190.24649 | M293: 190.24649 | N293: 190.24649 | O293: 190.24649 | P293: 190.24649 | Q293: 1054.693 | R293: 1054.693 | S293: 1054.693 | T293: 1054.693 | U293: 1054.693 | V293: 1054.693 | W293: 1054.693 | X293: 1054.693 | Y293: 1054.693
B294: 701401 | C294: 수정평균발행주식수 | D294: Shares (Adj.Wgt.) | J294: 111546.01 | K294: 111546.01 | L294: 111546.01 | M294: 111546.01 | N294: 111546.01 | O294: 111546.01 | P294: 111546.01 | Q294: 111629.34 | R294: 112410.46 | S294: 112410.46 | T294: 112410.46 | U294: 112410.46 | V294: 112410.46 | W294: 112410.46 | X294: 112410.46 | Y294: 112410.46
B295: 701400 | C295: 보통주수정평균발행주식수 | D295: Common (Adj.Wgt.) | J295: 111355.76 | K295: 111355.76 | L295: 111355.76 | M295: 111355.76 | N295: 111355.76 | O295: 111355.76 | P295: 111355.76 | Q295: 111355.76 | R295: 111355.76 | S295: 111355.76 | T295: 111355.76 | U295: 111355.76 | V295: 111355.76 | W295: 111355.76 | X295: 111355.76 | Y295: 111355.76
... B352: 442000 | C352: 주식배당액(우선주) | D352: Stock Dividend(Pref.) | J352: 0 | K352: 0 | L352: 0 | M352: 0 | N352: 0 | O352: 0 | P352: 0 | Q352: 0 | R352: 0 | S352: 0 | T352: 0 | U352: 0 | V352: 0 | W352: 0 | X352: 0 | Y352: 0
A363: 기타계정
B365: 800000 | C365: NOPLAT | D365: NOPLAT | J365: 423.10498 | K365: 840.07081 | L365: 876.06091 | M365: 539.56167 | N365: 497.87727 | O365: 605.36153 | P365: 332.41167 | Q365: 454.27684 | R365: 390.7607 | S365: 577.35229 | T365: -1455.5071 | U365: -1081.6593 | V365: -1171.2212 | W365: -1276.3178 | X365: -1396.466 | Y365: -1531.8043
B366: 800010 | C366: EBITDA (*)영업이익기준 | D366: EBITDA (*) (Operationg Income) | J366: 983.249 | K366: 1285.147 | L366: 1349.42 | M366: 1179.466 | N366: 1012.107 | O366: 1043.921 | P366: 720.629 | Q366: 925.005 | R366: 756.61 | S366: 981.544 | T366: -1041.923 | U366: -1151.7154 | V366: -1342.2352 | W366: -1528.4594 | X366: -1717.658 | Y366: -1915.3297
B367: 201372 | C367: EBITDA (*)조정영업이익기준 | D367: EBITDA (*) (Adj. Operationg Income) | J367: 983.249 | K367: 1285.147 | L367: 1349.42 | M367: 1179.466 | N367: 1012.107 | O367: 1043.921 | P367: 720.629 | Q367: 925.005 | R367: 756.61 | S367: 981.544 | T367: -1041.923 | U367: -1151.7154 | V367: -1342.2352 | W367: -1528.4594 | X367: -1717.658 | Y367: -1915.3297
...

Sheet Quarter
C2: Quarter | D2: BaseQ
B5: Period_CY_ | J5: 2022.03 | K5: 2022.06 | L5: 2022.09 | M5: 2022.12 | N5: 2023.03 | O5: 2023.06 | P5: 2023.09 | Q5: 2023.12 | R5: 2024.03 | S5: 2024.06 | T5: 2024.09 | U5: 2024.12 | V5: 2025.03 | W5: 2025.06 | X5: 2025.09 | Y5: 2025.12 | Z5: 2026.03 | AA5: 2026.06 | AB5: 2026.09 | AC5: 2026.12 | AD5: 2027.03 | AE5: 2027.06 | AF5: 2027.09 | AG5: 2027.12
B6: Period_FY_ | J6: 2022_1A | K6: 2022_2A | L6: 2022_3A | M6: 2022_4A | N6: 2023_1A | O6: 2023_2A | P6: 2023_3A | Q6: 2023_4A | R6: 2024_1A | S6: 2024_2A | T6: 2024_3A | U6: 2024_4A | V6: 2025_1F | W6: 2025_2F | X6: 2025_3F | Y6: 2025_4F | Z6: 2026_1F | AA6: 2026_2F | AB6: 2026_3F | AC6: 2026_4F | AD6: 2027_1F | AE6: 2027_2F | AF6: 2027_3F | AG6: 2027_4F
A13: Income Statement
B15: 200000 | C15: 매출액 | D15: Sales | J15: 4145.303 | K15: 5579.448 | L15: 5430.844 | M15: 6083.487 | N15: 6031.081 | O15: 7163.359 | P15: 7858.53 | Q15: 8598.387 | R15: 8545.258 | S15: 8621.236 | T15: 8256.906 | U15: 7246.868 | V15: 8999.1363 | W15: 8999.1363 | X15: 8999.1363 | Y15: 8999.1363 | Z15: 9915.3706 | AA15: 9915.3706 | AB15: 9915.3706 | AC15: 9915.3706 | AD15: 10924.89 | AE15: 10924.89 | AF15: 10924.89 | AG15: 10924.89
B17: 200001 | C17: 순매출액 (직접 입력) | D17: Net sales (manual)
B19: 200360 | C19: 매출원가 | D19: Cost of Sales | J19: 3774.063 | K19: 5137.759 | L19: 5097.562 | M19: 5716.95 | N19: 5651.16 | O19: 6765.776 | P19: 7342.408 | Q19: 8189.205 | R19: 8011.925 | S19: 8279.049 | T19: 7908.598 | U19: 8687.629 | V19: 10788.268 | W19: 10788.268 | X19: 10788.268 | Y19: 3870.7595 | Z19: 4264.8554 | AA19: 4264.8554 | AB19: 4264.8554 | AC19: 27130.271 | AD19: 29892.502 | AE19: 29892.502 | AF19: 29892.502 | AG19: -45687.776
B21: 200810 | C21: 매출총이익 | D21: Gross Profit | J21: 371.24 | K21: 441.689 | L21: 333.282 | M21: 366.537 | N21: 379.921 | O21: 397.583 | P21: 516.122 | Q21: 409.182 | R21: 533.333 | S21: 342.187 | T21: 348.308 | U21: -1440.761 | V21: -1789.1322 | W21: -1789.1322 | X21: -1789.1322 | Y21: 5128.3768 | Z21: 5650.5152 | AA21: 5650.5152 | AB21: 5650.5152 | AC21: -17214.901 | AD21: -18967.612 | AE21: -18967.612 | AF21: -18967.612 | AG21: 56612.666
B23: 200820 | C23: 판매비와 관리비 | D23: SG&A | J23: 199.759 | K23: 266.281 | L23: 179.576 | M23: 292.23 | N23: 206.409 | O23: 174.032 | P23: 272.253 | Q23: 264.684 | R23: 282.42 | S23: 194.884 | T23: 234.017 | U23: 335.166 | V23: 288.12446 | W23: 288.12446 | X23: 288.12446 | Y23: 288.12446 | Z23: 310.84517 | AA23: 310.84517 | AB23: 310.84517 | AC23: 310.84517 | AD23: 337.94268 | AE23: 337.94268 | AF23: 337.94268 | AG23: 337.94268
B24: 200821 | C24: 인건비및복리후생비 | D24: Salaries and Wages | J24: 117.485 | K24: 162.113 | L24: 122.696 | M24: 136.083 | N24: 121.822 | O24: 167.215 | P24: 128.854 | Q24: 165.262 | R24: 204.274 | S24: 102.038 | T24: 136.546 | U24: 190.682 | V24: 174.51074 | W24: 174.51074 | X24: 174.51074 | Y24: 174.51074 | Z24: 192.27831 | AA24: 192.27831 | AB24: 192.27831 | AC24: 192.27831 | AD24: 211.85485 | AE24: 211.85485 | AF24: 211.85485 | AG24: 211.85485
B25: 200822 | C25: 일반관리비 | D25: General & Administrative Expenses | J25: 15.491 | K25: 24.796 | L25: 19.296 | M25: 31.678 | N25: 18.116 | O25: 24.288 | P25: 19.156 | Q25: 25.059 | R25: 18.857 | S25: 18.449 | T25: 21.023 | U25: 38.815 | V25: 26.758645 | W25: 26.758645 | X25: 26.758645 | Y25: 26.758645 | Z25: 29.483038 | AA25: 29.483038 | AB25: 29.483038 | AC25: 29.483038 | AD25: 32.484812 | AE25: 32.484812 | AF25: 32.484812 | AG25: 32.484812
B26: 200823 | C26: 판매비 | D26: Sales Expenses | J26: 14.247 | K26: 21.516 | L26: -13.871 | M26: 69.038 | N26: 10.834 | O26: -50.637 | P26: 84.155 | Q26: 21.705 | R26: 19.698 | S26: 20.4 | T26: 22.222 | U26: 37.929 | V26: 27.613928 | W26: 27.613928 | X26: 27.613928 | Y26: 27.613928 | Z26: 30.425401 | AA26: 30.425401 | AB26: 30.425401 | AC26: 30.425401 | AD26: 33.52312 | AE26: 33.52312 | AF26: 33.52312 | AG26: 33.52312
B27: 201130 | C27: 연구개발비 | D27: Research & Development | J27: 42.902 | K27: 48.475 | L27: 41.763 | M27: 45.472 | N27: 45.21 | O27: 22.375 | P27: 29.217 | Q27: 41.985 | R27: 27.414 | S27: 36.468 | T27: 38.865 | U27: 52.176 | V27: 42.674067 | W27: 42.674067 | X27: 42.674067 | Y27: 42.674067 | Z27: 47.018866 | AA27: 47.018866 | AB27: 47.018866 | AC27: 47.018866 | AD27: 51.806026 | AE27: 51.806026 | AF27: 51.806026 | AG27: 51.806026
B28: 201160 | C28: 광고선전비 | D28: Advertising Expenses | J28: 0 | K28: 0 | L28: 0 | M28: 0 | N28: 0 | O28: 0 | P28: 0 | Q28: 0 | R28: 0 | S28: 0 | T28: 0 | U28: 0 | V28: 0 | W28: 0 | X28: 0 | Y28: 0 | Z28: 0 | AA28: 0 | AB28: 0 | AC28: 0 | AD28: 0 | AE28: 0 | AF28: 0 | AG28: 0
B29: 201080 | C29: 유형자산 감가상각비 | D29: Depreciation (SG&A) | J29: 8.559 | K29: 8.49 | L29: 8.818 | M29: 8.992 | N29: 9.266 | O29: 9.543 | P29: 9.632 | Q29: 9.308 | R29: 10.654 | S29: 16.019 | T29: 13.608 | U29: 13.718 | V29: 14.515556 | W29: 14.515556 | X29: 14.515556 | Y29: 14.515556 | Z29: 9.7822836 | AA29: 9.7822836 | AB29: 9.7822836 | AC29: 9.7822836 | AD29: 6.5924495 | AE29: 6.5924495 | AF29: 6.5924495 | AG29: 6.5924495
B30: 201090+201100 | C30: 무형자산상각비 | D30: Amortization (SG&A) | J30: 1.075 | K30: 0.891 | L30: 0.874 | M30: 0.967 | N30: 1.161 | O30: 1.248 | P30: 1.239 | Q30: 1.365 | R30: 1.523 | S30: 1.51 | T30: 1.753 | U30: 1.846 | V30: 2.0515193 | W30: 2.0515193 | X30: 2.0515193 | Y30: 2.0515193 | Z30: 1.8572704 | AA30: 1.8572704 | AB30: 1.8572704 | AC30: 1.8572704 | AD30: 1.6814141 | AE30: 1.6814141 | AF30: 1.6814141 | AG30: 1.6814141
B32: 203590 | C32: 기타영업수익 | D32: Other Operating Income | J32: 0 | K32: 0 | L32: 0 | M32: 0 | N32: 0 | O32: 0 | P32: 0 | Q32: 0 | R32: 0 | S32: 0 | T32: 0 | U32: 0 | V32: 0 | W32: 0 | X32: 0 | Y32: 0 | Z32: 0 | AA32: 0 | AB32: 0 | AC32: 0 | AD32: 0 | AE32: 0 | AF32: 0 | AG32: 0
B33: 203600 | C33: 이자수익 | D33: Interest Income | J33: 0 | K33: 0 | L33: 0 | M33: 0 | N33: 0 | O33: 0 | P33: 0 | Q33: 0 | R33: 0 | S33: 0 | T33: 0 | U33: 0 | V33: 0 | W33: 0 | X33: 0 | Y33: 0 | Z33: 0 | AA33: 0 | AB33: 0 | AC33: 0 | AD33: 0 | AE33: 0 | AF33: 0 | AG33: 0
B34: 203610 | C34: 배당금수익 | D34: Dividend Income | J34: 0 | K34: 0 | L34: 0 | M34: 0 | N34: 0 | O34: 0 | P34: 0 | Q34: 0 | R34: 0 | S34: 0 | T34: 0 | U34: 0 | V34: 0 | W34: 0 | X34: 0 | Y34: 0 | Z34: 0 | AA34: 0 | AB34: 0 | AC34: 0 | AD34: 0 | AE34: 0 | AF34: 0 | AG34: 0
B35: 203620 | C35: 외환거래이익 | D35: Gains on Foreign Exchange | J35: 0 | K35: 0 | L35: 0 | M35: 0 | N35: 0 | O35: 0 | P35: 0 | Q35: 0 | R35: 0 | S35: 0 | T35: 0 | U35: 0 | V35: 0 | W35: 0 | X35: 0 | Y35: 0 | Z35: 0 | AA35: 0 | AB35: 0 | AC35: 0 | AD35: 0 | AE35: 0 | AF35: 0 | AG35: 0
B36: 203800 | C36: 투자자산평가이익 | D36: Gains on Investment Assets | J36: 0 | K36: 0 | L36: 0 | M36: 0 | N36: 0 | O36: 0 | P36: 0 | Q36: 0 | R36: 0 | S36: 0 | T36: 0 | U36: 0 | V36: 0 | W36: 0 | X36: 0 | Y36: 0 | Z36: 0 | AA36: 0 | AB36: 0 | AC36: 0 | AD36: 0 | AE36: 0 | AF36: 0 | AG36: 0
B37: 203591 | C37: 기타 기타수익 | D37: Others | J37: 0 | K37: 0 | L37: 0 | M37: 0 | N37: 0 | O37: 0 | P37: 0 | Q37: 0 | R37: 0 | S37: 0 | T37: 0 | U37: 0 | V37: 0 | W37: 0 | X37: 0 | Y37: 0 | Z37: 0 | AA37: 0 | AB37: 0 | AC37: 0 | AD37: 0 | AE37: 0 | AF37: 0 | AG37: 0
B39: 204030 | C39: 기타영업비용 | D39: Other Operating Expenses | J39: 0 | K39: 0 | L39: 0 | M39: 0 | N39: 0 | O39: 0 | P39: 0 | Q39: 0 | R39: 0 | S39: 0 | T39: 0 | U39: 0 | V39: 0 | W39: 0 | X39: 0 | Y39: 0 | Z39: 0 | AA39: 0 | AB39: 0 | AC39: 0 | AD39: 0 | AE39: 0 | AF39: 0 | AG39: 0
B40: 204040 | C40: 이자비용 | D40: Interest Expenses | J40: 0 | K40: 0 | L40: 0 | M40: 0 | N40: 0 | O40: 0 | P40: 0 | Q40: 0 | R40: 0 | S40: 0 | T40: 0 | U40: 0 | V40: 0 | W40: 0 | X40: 0 | Y40: 0 | Z40: 0 | AA40: 0 | AB40: 0 | AC40: 0 | AD40: 0 | AE40: 0 | AF40: 0 | AG40: 0
B41: 204050 | C41: 외환거래손실 | D41: Losses on Foreign Exchange | J41: 0 | K41: 0 | L41: 0 | M41: 0 | N41: 0 | O41: 0 | P41: 0 | Q41: 0 | R41: 0 | S41: 0 | T41: 0 | U41: 0 | V41: 0 | W41: 0 | X41: 0 | Y41: 0 | Z41: 0 | AA41: 0 | AB41: 0 | AC41: 0 | AD41: 0 | AE41: 0 | AF41: 0 | AG41: 0
B42: 204240 | C42: 투자자산평가손실 | D42: Losses on Investment Assets | J42: 0 | K42: 0 | L42: 0 | M42: 0 | N42: 0 | O42: 0 | P42: 0 | Q42: 0 | R42: 0 | S42: 0 | T42: 0 | U42: 0 | V42: 0 | W42: 0 | X42: 0 | Y42: 0 | Z42: 0 | AA42: 0 | AB42: 0 | AC42: 0 | AD42: 0 | AE42: 0 | AF42: 0 | AG42: 0
B43: 204031 | C43: 기타 기타비용 | D43: Others | J43: 0 | K43: 0 | L43: 0 | M43: 0 | N43: 0 | O43: 0 | P43: 0 | Q43: 0 | R43: 0 | S43: 0 | T43: 0 | U43: 0 | V43: 0 | W43: 0 | X43: 0 | Y43: 0 | Z43: 0 | AA43: 0 | AB43: 0 | AC43: 0 | AD43: 0 | AE43: 0 | AF43: 0 | AG43: 0
B45: 201370 | C45: 영업이익 | D45: Operating Income | J45: 171.481 | K45: 175.408 | L45: 153.706 | M45: 74.307 | N45: 173.512 | O45: 223.551 | P45: 243.869 | Q45: 144.498 | R45: 250.913 | S45: 147.303 | T45: 114.291 | U45: -1775.927 | V45: -2077.2566 | W45: -2077.2566 | X45: -2077.2566 | Y45: 4840.2523 | Z45: 5339.67 | AA45: 5339.67 | AB45: 5339.67 | AC45: -17525.746 | AD45: -19305.554 | AE45: -19305.554 | AF45: -19305.554 | AG45: 56274.724
... B72: 202890 | C72: 지분법관련손익 | D72: Gains(Losses) in Equity Method | J72: -1.529 | K72: 0.722 | L72: 0.863 | M72: -12.729 | N72: -1.094 | O72: -3.138 | P72: 0.666 | Q72: -1.714 | R72: -0.149 | S72: 0.919 | T72: -2.134 | U72: 6.939 | V72: 1.39375 | W72: 1.39375 | X72: 1.39375 | Y72: 1.39375 | Z72: 1.39375 | AA72: 1.39375 | AB72: 1.39375 | AC72: 1.39375 | AD72: 1.39375 | AE72: 1.39375 | AF72: 1.39375 | AG72: 1.39375
D73: Gains
D74: Losses
D75: Others
B76: 202990 | C76: 관계기업처분손익 | D76: Gains(Losses) in Associates | J76: 0 | K76: 0 | L76: 0 | M76: 0 | N76: 0 | O76: 0 | P76: 0 | Q76: 0 | R76: 0 | S76: 0 | T76: 0 | U76: 0 | V76: 0 | W76: 0 | X76: 0 | Y76: 0 | Z76: 0 | AA76: 0 | AB76: 0 | AC76: 0 | AD76: 0 | AE76: 0 | AF76: 0 | AG76: 0
B77: 203050 | C77: 종속기업관련손익 | D77: Gains(Losses) in Subsidiaries | J77: 0 | K77: 0 | L77: 0 | M77: 0 | N77: 0 | O77: 0 | P77: 0 | Q77: 0 | R77: 0 | S77: 0 | T77: 0 | U77: 0 | V77: 0 | W77: 0 | X77: 0 | Y77: 0 | Z77: 0 | AA77: 0 | AB77: 0 | AC77: 0 | AD77: 0 | AE77: 0 | AF77: 0 | AG77: 0
B78: 203110 | C78: 기타 | D78: Others | J78: 0 | K78: 0 | L78: 0 | M78: 0 | N78: 0 | O78: 0 | P78: 0 | Q78: 0 | R78: 0 | S78: 0 | T78: 0 | U78: 0 | V78: 0 | W78: 0 | X78: 0 | Y78: 0 | Z78: 0 | AA78: 0 | AB78: 0 | AC78: 0 | AD78: 0 | AE78: 0 | AF78: 0 | AG78: 0
B80: 203120 | C80: 세전이익 | D80: Pre-Tax Income | J80: 233.322 | K80: 321.728 | L80: 349.087 | M80: -150.322 | N80: 226.659 | O80: 240.13 | P80: 276.668 | Q80: 196.088 | R80: 302.796 | S80: 247.817 | T80: 85.012 | U80: -1621.342 | V80: -2088.8803 | W80: -2088.8803 | X80: -2088.8803 | Y80: 4828.6286 | Z80: 5326.7587 | AA80: 5326.7587 | AB80: 5326.7587 | AC80: -17538.657 | AD80: -19319.413 | AE80: -19319.413 | AF80: -19319.413 | AG80: 56260.864
B81: 203130 | C81: 법인세비용 | D81: Income Tax Expenses | J81: 50.214 | K81: 96.784 | L81: 114.289 | M81: 21.652 | N81: 76.107 | O81: 27.771 | P81: 95.343 | Q81: 86.043 | R81: 94.433 | S81: 101.7 | T81: 44.906 | U81: -460.535 | V81: -80.052876 | W81: -80.052876 | X81: -80.052876 | Y81: -80.052876 | Z81: -86.75371 | AA81: -86.75371 | AB81: -86.75371 | AC81: -86.75371 | AD81: -94.491404 | AE81: -94.491404 | AF81: -94.491404 | AG81: -94.491404
B82: 203165 | C82: 종속회사매수일전순손익 | D82: Others | J82: 0 | K82: 0 | L82: 0 | M82: 0 | N82: 0 | O82: 0 | P82: 0 | Q82: 0 | R82: 0 | S82: 0 | T82: 0 | U82: 0 | V82: 0 | W82: 0 | X82: 0 | Y82: 0 | Z82: 0 | AA82: 0 | AB82: 0 | AC82: 0 | AD82: 0 | AE82: 0 | AF82: 0 | AG82: 0
B83: 205560 | C83: 처분된종속회사순손익 | D83: Net Income(Net Loss) from Disposed Subsidies | J83: 0 | K83: 0 | L83: 0 | M83: 0 | N83: 0 | O83: 0 | P83: 0 | Q83: 0 | R83: 0 | S83: 0 | T83: 0 | U83: 0 | V83: 0 | W83: 0 | X83: 0 | Y83: 0 | Z83: 0 | AA83: 0 | AB83: 0 | AC83: 0 | AD83: 0 | AE83: 0 | AF83: 0 | AG83: 0
B84: 203140 | C84: 계속사업이익 | D84: Income from Continuing Operations | J84: 183.108 | K84: 224.944 | L84: 234.798 | M84: -171.974 | N84: 150.552 | O84: 212.359 | P84: 181.325 | Q84: 110.045 | R84: 208.363 | S84: 146.117 | T84: 40.106 | U84: -1160.807 | V84: -2008.8274 | W84: -2008.8274 | X84: -2008.8274 | Y84: 4908.6815 | Z84: 5413.5124 | AA84: 5413.5124 | AB84: 5413.5124 | AC84: -17451.904 | AD84: -19224.922 | AE84: -19224.922 | AF84: -19224.922 | AG84: 56355.356
B85: 203150 | C85: 중단사업이익 | D85: Income from Discontinued Operations | J85: 0 | K85: 0 | L85: 0 | M85: 0 | N85: 0 | O85: 0 | P85: 0 | Q85: 0 | R85: 0 | S85: 0 | T85: 0 | U85: 0 | V85: 0 | W85: 0 | X85: 0 | Y85: 0 | Z85: 0 | AA85: 0 | AB85: 0 | AC85: 0 | AD85: 0 | AE85: 0 | AF85: 0 | AG85: 0
B86: 203160 | C86: (중단사업 법인세효과) | D86: (Income Taxes Effects) | J86: 0 | K86: 0 | L86: 0 | M86: 0 | N86: 0 | O86: 0 | P86: 0 | Q86: 0 | R86: 0 | S86: 0 | T86: 0 | U86: 0 | V86: 0 | W86: 0 | X86: 0 | Y86: 0 | Z86: 0 | AA86: 0 | AB86: 0 | AC86: 0 | AD86: 0 | AE86: 0 | AF86: 0 | AG86: 0
B88: 203170 | C88: 당기순이익 | D88: Net Income | J88: 183.108 | K88: 224.944 | L88: 234.798 | M88: -171.974 | N88: 150.552 | O88: 212.359 | P88: 181.325 | Q88: 110.045 | R88: 208.363 | S88: 146.117 | T88: 40.106 | U88: -1160.807 | V88: -2008.8274 | W88: -2008.8274 | X88: -2008.8274 | Y88: 4908.6815 | Z88: 5413.5124 | AA88: 5413.5124 | AB88: 5413.5124 | AC88: -17451.904 | AD88: -19224.922 | AE88: -19224.922 | AF88: -19224.922 | AG88: 56355.356
B89: 203171 | C89: 조정 당기순이익 | D89: Adj. Net Income | J89: 183.108 | K89: 224.944 | L89: 234.798 | M89: -171.974 | N89: 150.552 | O89: 212.359 | P89: 181.325 | Q89: 110.045 | R89: 208.363 | S89: 146.117 | T89: 40.106 | U89: -1160.807 | V89: -2008.8274 | W89: -2008.8274 | X89: -2008.8274 | Y89: 4908.6815 | Z89: 5413.5124 | AA89: 5413.5124 | AB89: 5413.5124 | AC89: -17451.904 | AD89: -19224.922 | AE89: -19224.922 | AF89: -19224.922 | AG89: 56355.356
... B96: 203300 | C96: 총포괄이익 | D96: Total Comprehensive Income | J96: 215.418 | K96: 324.836 | L96: 513.641 | M96: -438.867 | N96: 263.406 | O96: 218.745 | P96: 227.242 | Q96: -83.366 | R96: 259.986 | S96: 207.323 | T96: -70.632 | U96: -1086.477 | V96: -1989.7221 | W96: -1989.7221 | X96: -1989.7221 | Y96: 4927.7868 | Z96: 5432.6177 | AA96: 5432.6177 | AB96: 5432.6177 | AC96: -17432.798 | AD96: -19205.817 | AE96: -19205.817 | AF96: -19205.817 | AG96: 56374.461
A105: Balance Sheet
B107: 110000 | C107: 자산총계 | D107: Assets | J107: 20093.35 | K107: 20525.833 | L107: 21228.666 | M107: 20911.708 | N107: 21693.73 | O107: 22688.832 | P107: 23042.465 | Q107: 23714.495 | R107: 24330.039 | S107: 24931.312 | T107: 24977.834 | U107: 27005.385 | V107: 22196.026 | W107: 22517.039 | X107: 22838.052 | Y107: 23159.065 | Z107: 23571.564 | AA107: 23984.064 | AB107: 24396.563 | AC107: 24809.063 | AD107: 25312.794 | AE107: 25816.525 | AF107: 26320.256 | AG107: 26823.987
B109: 110010 | C109: 비유동자산 | D109: Non-Current Assets | J109: 5124.735 | K109: 5350.605 | L109: 5391.9 | M109: 5394.964 | N109: 5432.658 | O109: 5447.286 | P109: 5305.091 | Q109: 5101.065 | R109: 5238.843 | S109: 5470.51 | T109: 5319.194 | U109: 5904.722 | V109: 5818.7995 | W109: 5732.8769 | X109: 5646.9544 | Y109: 5561.0318 | Z109: 5493.9347 | AA109: 5426.8375 | AB109: 5359.7404 | AC109: 5292.6432 | AD109: 5238.3013 | AE109: 5183.9594 | AF109: 5129.6175 | AG109: 5075.2756
B110: 110020 | C110: 유형자산 | D110: Tangible Assets | J110: 1016.926 | K110: 1046.163 | L110: 1098.012 | M110: 1048.81 | N110: 1119.695 | O110: 1146.601 | P110: 1162.931 | Q110: 1204.52 | R110: 1256.821 | S110: 1260.532 | T110: 1266.975 | U110: 1289.154 | V110: 1232.3299 | W110: 1175.5058 | X110: 1118.6818 | Y110: 1061.8577 | Z110: 1023.563 | AA110: 985.26823 | AB110: 946.9735 | AC110: 908.67878 | AD110: 882.8713 | AE110: 857.06382 | AF110: 831.25635 | AG110: 805.44887
B111: 190010 | C111: 토지 | D111: Land | J111: 0 | K111: 0 | L111: 0 | M111: 363 | N111: 0 | O111: 0 | P111: 0 | Q111: 363.045 | R111: 0 | S111: 0 | T111: 0 | U111: 368.27 | V111: 368.27 | W111: 368.27 | X111: 368.27 | Y111: 368.27 | Z111: 368.27 | AA111: 368.27 | AB111: 368.27 | AC111: 368.27 | AD111: 368.27 | AE111: 368.27 | AF111: 368.27 | AG111: 368.27
B112: 190020 | C112: 설비자산 | D112: Plant Assets | J112: 0 | K112: 0 | L112: 0 | M112: 487.634 | N112: 0 | O112: 0 | P112: 0 | Q112: 628.474 | R112: 0 | S112: 0 | T112: 0 | U112: 677.768 | V112: 622.51588 | W112: 567.26377 | X112: 512.01165 | Y112: 456.75954 | Z112: 419.52418 | AA112: 382.28883 | AB112: 345.05348 | AC112: 307.81812 | AD112: 282.72458 | AE112: 257.63103 | AF112: 232.53749 | AG112: 207.44394
B113: 190150 | C113: 건설중인자산 | D113: Construction in Progress | J113: 0 | K113: 0 | L113: 0 | M113: 178.217 | N113: 0 | O113: 0 | P113: 0 | Q113: 193.204 | R113: 0 | S113: 0 | T113: 0 | U113: 223.833 | V113: 223.833 | W113: 223.833 | X113: 223.833 | Y113: 223.833 | Z113: 223.833 | AA113: 223.833 | AB113: 223.833 | AC113: 223.833 | AD113: 223.833 | AE113: 223.833 | AF113: 223.833 | AG113: 223.833
B114: 190160 | C114: 기타유형자산 | D114: Other Property Plant Equipment | J114: 1016.926 | K114: 1046.163 | L114: 1098.012 | M114: 19.959 | N114: 1119.695 | O114: 1146.601 | P114: 1162.931 | Q114: 19.797 | R114: 1256.821 | S114: 1260.532 | T114: 1266.975 | U114: 19.283 | V114: 17.711037 | W114: 16.139073 | X114: 14.56711 | Y114: 12.995146 | Z114: 11.935773 | AA114: 10.876399 | AB114: 9.8170262 | AC114: 8.7576529 | AD114: 8.043723 | AE114: 7.3297931 | AF114: 6.6158631 | AG114: 5.9019332
B115: 110610 | C115: 무형자산 | D115: Intangible Assets | J115: 717.005 | K115: 715.267 | L115: 717.977 | M115: 720.626 | N115: 723.746 | O115: 720.611 | P115: 720.402 | Q115: 724.427 | R115: 724.882 | S115: 722.61 | T115: 745.506 | U115: 750.741 | V115: 747.61454 | W115: 744.48807 | X115: 741.36161 | Y115: 738.23515 | Z115: 735.40471 | AA115: 732.57428 | AB115: 729.74385 | AC115: 726.91341 | AD115: 724.35098 | AE115: 721.78855 | AF115: 719.22612 | AG115: 716.66368
B116: 190170 | C116: 영업권 | D116: Goodwill | J116: 0 | K116: 0 | L116: 0 | M116: 617.684 | N116: 0 | O116: 0 | P116: 0 | Q116: 617.684 | R116: 0 | S116: 0 | T116: 0 | U116: 618.663 | V116: 618.663 | W116: 618.663 | X116: 618.663 | Y116: 618.663 | Z116: 618.663 | AA116: 618.663 | AB116: 618.663 | AC116: 618.663 | AD116: 618.663 | AE116: 618.663 | AF116: 618.663 | AG116: 618.663
B117: 110611 | C117: 기타무형자산 | D117: Other Intangible Assets | J117: 717.005 | K117: 715.267 | L117: 717.977 | M117: 102.942 | N117: 723.746 | O117: 720.611 | P117: 720.402 | Q117: 106.743 | R117: 724.882 | S117: 722.61 | T117: 745.506 | U117: 132.078 | V117: 128.95154 | W117: 125.82507 | X117: 122.69861 | Y117: 119.57215 | Z117: 116.74171 | AA117: 113.91128 | AB117: 111.08085 | AC117: 108.25041 | AD117: 105.68798 | AE117: 103.12555 | AF117: 100.56312 | AG117: 98.000684
B118: 190311 | C118: 투자자산 | D118: Investment Assets | J118: 1397.901 | K118: 1519.659 | L118: 1473.366 | M118: 1557.3 | N118: 1481.111 | O118: 1297.415 | P118: 1161.119 | Q118: 1217.043 | R118: 1338.399 | S118: 1270.27 | T118: 1328.166 | U118: 1390.132 | V118: 1364.16 | W118: 1338.188 | X118: 1312.216 | Y118: 1286.244 | Z118: 1260.272 | AA118: 1234.3 | AB118: 1208.328 | AC118: 1182.356 | AD118: 1156.384 | AE118: 1130.412 | AF118: 1104.44 | AG118: 1078.468
B119: 111450 | C119: 관계기업등지분관련투자자산 | D119: Investments in Associates, Subs and JVs | J119: 86.001 | K119: 110.492 | L119: 99.291 | M119: 88.958 | N119: 90.633 | O119: 85.476 | P119: 88.893 | Q119: 86.608 | R119: 101.02 | S119: 121.095 | T119: 134.809 | U119: 168.064 | V119: 142.092 | W119: 116.12 | X119: 90.148 | Y119: 64.176 | Z119: 38.204 | AA119: 12.232 | AB119: -13.74 | AC119: -39.712 | AD119: -65.684 | AE119: -91.656 | AF119: -117.628 | AG119: -143.6
... B133: 113350 | C133: 매출채권 및 기타채권 | D133: Trade and Other Current Receivables | J133: 7099.886 | K133: 7729.183 | L133: 8020.969 | M133: 7848.789 | N133: 8745.614 | O133: 9591.685 | P133: 10585.093 | Q133: 10659.313 | R133: 11992.422 | S133: 12454.494 | T133: 11998.288 | U133: 12100.467 | V133: 12408.465 | W133: 12716.463 | X133: 13024.461 | Y133: 13332.459 | Z133: 13671.815 | AA133: 14011.172 | AB133: 14350.528 | AC133: 14689.884 | AD133: 15063.792 | AE133: 15437.699 | AF133: 15811.607 | AG133: 16185.514
B134: 190560 | C134: 매출채권 | J134: #N/A | K134: #N/A | L134: #N/A | M134: #N/A | N134: #N/A | O134: #N/A | P134: #N/A | Q134: #N/A | R134: #N/A | S134: #N/A | T134: #N/A | U134: #N/A | V134: #N/A | W134: #N/A | X134: #N/A | Y134: #N/A | Z134: #N/A | AA134: #N/A | AB134: #N/A | AC134: #N/A | AD134: #N/A | AE134: #N/A | AF134: #N/A | AG134: #N/A
B135: 190561 | C135: 기타단기채권 | J135: #N/A | K135: #N/A | L135: #N/A | M135: #N/A | N135: #N/A | O135: #N/A | P135: #N/A | Q135: #N/A | R135: #N/A | S135: #N/A | T135: #N/A | U135: #N/A | V135: #N/A | W135: #N/A | X135: #N/A | Y135: #N/A | Z135: #N/A | AA135: #N/A | AB135: #N/A | AC135: #N/A | AD135: #N/A | AE135: #N/A | AF135: #N/A | AG135: #N/A
B136: 190650 | C136: 현금및현금성자산 | D136: Cash and Cash Equivalents | J136: 3349.584 | K136: 3096.52 | L136: 3363.606 | M136: 3973.897 | N136: 3502.211 | O136: 3569.585 | P136: 3233.712 | Q136: 4205.665 | R136: 3213.209 | S136: 3041.257 | T136: 3704.479 | U136: 5130.372 | V136: 0 | W136: 0 | X136: 0 | Y136: 0 | Z136: 0 | AA136: 0 | AB136: 0 | AC136: 0 | AD136: 0 | AE136: 0 | AF136: 0 | AG136: 0
B137: 112831 | C137: 기타유동자산 | D137: Other Current Assets | J137: 1190.708 | K137: 1365.426 | L137: 1325.589 | M137: 1310.217 | N137: 1653.838 | O137: 1820.903 | P137: 1888.375 | Q137: 1961.743 | R137: 2124.232 | S137: 2330.081 | T137: 2347.476 | U137: 2378.539 | V137: 2504.8763 | W137: 2631.2137 | X137: 2757.551 | Y137: 2883.8883 | Z137: 3037.0676 | AA137: 3190.2468 | AB137: 3343.426 | AC137: 3496.6053 | AD137: 3682.3293 | AE137: 3868.0533 | AF137: 4053.7773 | AG137: 4239.5013
B138: 114350 | C138: 기타금융업자산 | D138: Other Financial Institutions Assets | J138: 0 | K138: 0 | L138: 0 | M138: 0 | N138: 0 | O138: 0 | P138: 0 | Q138: 0 | R138: 0 | S138: 0 | T138: 0 | U138: 0 | V138: 0 | W138: 0 | X138: 0 | Y138: 0 | Z138: 0 | AA138: 0 | AB138: 0 | AC138: 0 | AD138: 0 | AE138: 0 | AF138: 0 | AG138: 0
B141: 130000 | C141: 부채총계 | D141: Liabilities | J141: 10563.594 | K141: 10671.293 | L141: 10865.523 | M141: 10987.431 | N141: 11600.487 | O141: 12377.887 | P141: 12504.278 | Q141: 13258.98 | R141: 13708.881 | S141: 14104.306 | T141: 14221.46 | U141: 17335.972 | V141: 18281.545 | W141: 19227.118 | X141: 20172.691 | Y141: 21118.264 | Z141: 22555.726 | AA141: 23993.188 | AB141: 25430.65 | AC141: 26868.112 | AD141: 29073.535 | AE141: 31278.957 | AF141: 33484.38 | AG141: 35689.802
B143: 130010 | C143: 비유동부채 | D143: Non-Current Liabilities | J143: 2428.998 | K143: 2515.19 | L143: 2380.259 | M143: 2230.034 | N143: 2379.669 | O143: 2633.781 | P143: 2996.659 | Q143: 2902.333 | R143: 3092.06 | S143: 2976.996 | T143: 2641.506 | U143: 2672.197 | V143: 2672.197 | W143: 2672.197 | X143: 2672.197 | Y143: 2672.197 | Z143: 2672.197 | AA143: 2672.197 | AB143: 2672.197 | AC143: 2672.197 | AD143: 2672.197 | AE143: 2672.197 | AF143: 2672.197 | AG143: 2672.197
B144: 190710 | C144: 사채 | D144: Bonds | J144: 1266.636 | K144: 1266.915 | L144: 1067.449 | M144: 1017.694 | N144: 1047.278 | O144: 967.659 | P144: 1206.894 | Q144: 1207.22 | R144: 1176.704 | S144: 1177.067 | T144: 927.777 | U144: 928.047 | V144: 928.047 | W144: 928.047 | X144: 928.047 | Y144: 928.047 | Z144: 928.047 | AA144: 928.047 | AB144: 928.047 | AC144: 928.047 | AD144: 928.047 | AE144: 928.047 | AF144: 928.047 | AG144: 928.047
B145: 190760 | C145: 장기차입금 | D145: LT Borrowings | J145: 259.785 | K145: 244.974 | L145: 198.952 | M145: 193.531 | N145: 250.162 | O145: 590.181 | P145: 569.825 | Q145: 563.609 | R145: 651.338 | S145: 406.843 | T145: 402.071 | U145: 598.212 | V145: 598.212 | W145: 598.212 | X145: 598.212 | Y145: 598.212 | Z145: 598.212 | AA145: 598.212 | AB145: 598.212 | AC145: 598.212 | AD145: 598.212 | AE145: 598.212 | AF145: 598.212 | AG145: 598.212
B146: 190771 | C146: 장기금융부채 | D146: LT Financial Liabilities | J146: 133.08 | K146: 137.128 | L146: 132.094 | M146: 130.727 | N146: 131.243 | O146: 130.946 | P146: 127.288 | Q146: 128.164 | R146: 122.12 | S146: 144.125 | T146: 151.838 | U146: 184.537 | V146: 184.537 | W146: 184.537 | X146: 184.537 | Y146: 184.537 | Z146: 184.537 | AA146: 184.537 | AB146: 184.537 | AC146: 184.537 | AD146: 184.537 | AE146: 184.537 | AF146: 184.537 | AG146: 184.537
B147: 130880 | C147: 비유동종업원급여충당부채 | D147: Non-Current Provisions for Employee Benefits | J147: 47.46 | K147: 49.085 | L147: 49.1 | M147: 44.047 | N147: 41.547 | O147: 42.371 | P147: 42.98 | Q147: 50.591 | R147: 48.411 | S147: 49.094 | T147: 49.106 | U147: 70.661 | V147: 70.661 | W147: 70.661 | X147: 70.661 | Y147: 70.661 | Z147: 70.661 | AA147: 70.661 | AB147: 70.661 | AC147: 70.661 | AD147: 70.661 | AE147: 70.661 | AF147: 70.661 | AG147: 70.661
B148: 131090 | C148: 이연법인세부채 | D148: Deferred Tax Liabilities | J148: 13.266 | K148: 9.071 | L148: 7.819 | M148: 5.819 | N148: 5.85 | O148: 5.938 | P148: 21.28 | Q148: 20.049 | R148: 19.9 | S148: 23.932 | T148: 32.344 | U148: 31.608 | V148: 31.608 | W148: 31.608 | X148: 31.608 | Y148: 31.608 | Z148: 31.608 | AA148: 31.608 | AB148: 31.608 | AC148: 31.608 | AD148: 31.608 | AE148: 31.608 | AF148: 31.608 | AG148: 31.608
B149: 130011 | C149: 기타비유동부채 | D149: Other Non-Current Liabilities | J149: 708.771 | K149: 808.017 | L149: 924.845 | M149: 838.216 | N149: 903.589 | O149: 896.686 | P149: 1028.392 | Q149: 932.7 | R149: 1073.587 | S149: 1175.935 | T149: 1078.37 | U149: 859.132 | V149: 859.132 | W149: 859.132 | X149: 859.132 | Y149: 859.132 | Z149: 859.132 | AA149: 859.132 | AB149: 859.132 | AC149: 859.132 | AD149: 859.132 | AE149: 859.132 | AF149: 859.132 | AG149: 859.132
B151: 131580 | C151: 유동부채 | D151: Current Liabilities | J151: 8134.596 | K151: 8156.103 | L151: 8485.264 | M151: 8757.397 | N151: 9220.818 | O151: 9744.106 | P151: 9507.619 | Q151: 10356.647 | R151: 10616.821 | S151: 11127.31 | T151: 11579.954 | U151: 14663.775 | V151: 15609.348 | W151: 16554.921 | X151: 17500.494 | Y151: 18446.067 | Z151: 19883.529 | AA151: 21320.991 | AB151: 22758.453 | AC151: 24195.915 | AD151: 26401.338 | AE151: 28606.76 | AF151: 30812.183 | AG151: 33017.605
... B156: 132000 | C156: 매입채무및기타채무 | D156: Trade and Other Current Payables | J156: 6212.754 | K156: 6384.871 | L156: 6536.678 | M156: 6806.363 | N156: 7001.735 | O156: 7594.476 | P156: 7471.905 | Q156: 7714.943 | R156: 7724.704 | S156: 7929.54 | T156: 8467.83 | U156: 9940.085 | V156: 10885.658 | W156: 11831.231 | X156: 12776.804 | Y156: 13722.377 | Z156: 15159.839 | AA156: 16597.301 | AB156: 18034.763 | AC156: 19472.225 | AD156: 21677.648 | AE156: 23883.07 | AF156: 26088.493 | AG156: 28293.915
B157: 132010 | C157: 매입채무 | D157: Trade Payables | J157: #N/A | K157: #N/A | L157: #N/A | M157: #N/A | N157: #N/A | O157: #N/A | P157: #N/A | Q157: #N/A | R157: #N/A | S157: #N/A | T157: #N/A | U157: #N/A | V157: #N/A | W157: #N/A | X157: #N/A | Y157: #N/A | Z157: #N/A | AA157: #N/A | AB157: #N/A | AC157: #N/A | AD157: #N/A | AE157: #N/A | AF157: #N/A | AG157: #N/A
B158: 132011 | C158: 기타단기채권 | D158: Other Short-Term Receivables | J158: #N/A | K158: #N/A | L158: #N/A | M158: #N/A | N158: #N/A | O158: #N/A | P158: #N/A | Q158: #N/A | R158: #N/A | S158: #N/A | T158: #N/A | U158: #N/A | V158: #N/A | W158: #N/A | X158: #N/A | Y158: #N/A | Z158: #N/A | AA158: #N/A | AB158: #N/A | AC158: #N/A | AD158: #N/A | AE158: #N/A | AF158: #N/A | AG158: #N/A
B159: 131581 | C159: 기타유동부채 | D159: Other Current Liabilities | J159: 1406.353 | K159: 1382.622 | L159: 1392.27 | M159: 1306.716 | N159: 1639.559 | O159: 1410.831 | P159: 1448.87 | Q159: 1997.766 | R159: 1960.988 | S159: 2052.766 | T159: 1742.443 | U159: 2807.342 | V159: 2807.342 | W159: 2807.342 | X159: 2807.342 | Y159: 2807.342 | Z159: 2807.342 | AA159: 2807.342 | AB159: 2807.342 | AC159: 2807.342 | AD159: 2807.342 | AE159: 2807.342 | AF159: 2807.342 | AG159: 2807.342
B160: 132780 | C160: 기타금융업부채 | D160: Other Financial Institutions Liabilities | J160: 0 | K160: 0 | L160: 0 | M160: 0 | N160: 0 | O160: 0 | P160: 0 | Q160: 0 | R160: 0 | S160: 0 | T160: 0 | U160: 0 | V160: 0 | W160: 0 | X160: 0 | Y160: 0 | Z160: 0 | AA160: 0 | AB160: 0 | AC160: 0 | AD160: 0 | AE160: 0 | AF160: 0 | AG160: 0
B163: 120000 | C163: 자본총계 | D163: Stockholders' Equity | J163: 9529.756 | K163: 9854.54 | L163: 10363.143 | M163: 9924.277 | N163: 10093.243 | O163: 10310.945 | P163: 10538.187 | Q163: 10455.515 | R163: 10621.158 | S163: 10827.006 | T163: 10756.374 | U163: 9669.413 | V163: 9392.1933 | W163: 9114.9737 | X163: 8837.754 | Y163: 8560.5343 | Z163: 8259.9232 | AA163: 7959.3121 | AB163: 7658.7011 | AC163: 7358.09 | AD163: 7030.468 | AE163: 6702.846 | AF163: 6375.2241 | AG163: 6047.6021
B164: 120010 | C164: 지배주주지분 | D164: Owners of Parent Equity | J164: 7323.258 | K164: 7623.045 | L164: 8092.825 | M164: 7686.677 | N164: 7866.157 | O164: 8026.742 | P164: 8230.788 | Q164: 8136.651 | R164: 8274.298 | S164: 8487.587 | T164: 8436.285 | U164: 8025.41 | V164: 7966.127 | W164: 7906.8441 | X164: 7847.5611 | Y164: 7788.2782 | Z164: 7723.8462 | AA164: 7659.4142 | AB164: 7594.9823 | AC164: 7530.5503 | AD164: 7460.1727 | AE164: 7389.795 | AF164: 7319.4173 | AG164: 7249.0396
B165: 120020 | C165: 자본금 | D165: Capital Stock | J165: 562.052 | K165: 562.052 | L165: 562.052 | M165: 562.052 | N165: 562.052 | O165: 562.052 | P165: 562.052 | Q165: 562.052 | R165: 562.052 | S165: 562.052 | T165: 562.052 | U165: 562.052 | V165: 562.052 | W165: 562.052 | X165: 562.052 | Y165: 562.052 | Z165: 562.052 | AA165: 562.052 | AB165: 562.052 | AC165: 562.052 | AD165: 562.052 | AE165: 562.052 | AF165: 562.052 | AG165: 562.052
B166: 120030 | C166: 보통주자본금 | D166: Common Stock | J166: 556.779 | K166: 556.779 | L166: 556.779 | M166: 556.77882 | N166: 556.779 | O166: 556.779 | P166: 556.779 | Q166: 556.77882 | R166: 556.77882 | S166: 556.77853 | T166: 556.779 | U166: 556.77882 | V166: 556.77882 | W166: 556.77882 | X166: 556.77882 | Y166: 556.77882 | Z166: 556.77882 | AA166: 556.77882 | AB166: 556.77882 | AC166: 556.77882 | AD166: 556.77882 | AE166: 556.77882 | AF166: 556.77882 | AG166: 556.77882
B167: 120040 | C167: 우선주자본금 | D167: Preferred Stock | J167: 5.273 | K167: 5.273 | L167: 5.273 | M167: 5.273175 | N167: 5.273 | O167: 5.273 | P167: 5.273 | Q167: 5.273175 | R167: 5.273175 | S167: 5.273465 | T167: 5.273 | U167: 5.273175 | V167: 5.273175 | W167: 5.273175 | X167: 5.273175 | Y167: 5.273175 | Z167: 5.273175 | AA167: 5.273175 | AB167: 5.273175 | AC167: 5.273175 | AD167: 5.273175 | AE167: 5.273175 | AF167: 5.273175 | AG167: 5.273175
B168: 120710 | C168: 신종자본증권 | D168: Hybrid Bond | J168: 0 | K168: 0 | L168: 0 | M168: 0 | N168: 0 | O168: 0 | P168: 0 | Q168: 0 | R168: 0 | S168: 0 | T168: 0 | U168: 0 | V168: 0 | W168: 0 | X168: 0 | Y168: 0 | Z168: 0 | AA168: 0 | AB168: 0 | AC168: 0 | AD168: 0 | AE168: 0 | AF168: 0 | AG168: 0
B169: 120050 | C169: 자본잉여금 | D169: Capital Surplus | J169: 1098.158 | K169: 1098.158 | L169: 1095.324 | M169: 1095.324 | N169: 1095.324 | O169: 1095.324 | P169: 1095.324 | Q169: 1095.324 | R169: 1095.324 | S169: 1095.31 | T169: 1095.31 | U169: 1095.31 | V169: 1095.31 | W169: 1095.31 | X169: 1095.31 | Y169: 1095.31 | Z169: 1095.31 | AA169: 1095.31 | AB169: 1095.31 | AC169: 1095.31 | AD169: 1095.31 | AE169: 1095.31 | AF169: 1095.31 | AG169: 1095.31
B170: 120060 | C170: 주식발행초과금 | D170: Paid-In Capital in Excess of Par Value | J170: 366.47 | K170: 366.47 | L170: 366.47 | M170: 366.47 | N170: 366.47 | O170: 366.47 | P170: 366.47 | Q170: 366.47 | R170: 366.47 | S170: 366.47 | T170: 366.47 | U170: 366.47 | V170: 366.47 | W170: 366.47 | X170: 366.47 | Y170: 366.47 | Z170: 366.47 | AA170: 366.47 | AB170: 366.47 | AC170: 366.47 | AD170: 366.47 | AE170: 366.47 | AF170: 366.47 | AG170: 366.47
B171: 120051 | C171: 기타 | D171: Others | J171: 731.688 | K171: 731.688 | L171: 728.854 | M171: 728.854 | N171: 728.854 | O171: 728.854 | P171: 728.854 | Q171: 728.854 | R171: 728.854 | S171: 728.84 | T171: 728.84 | U171: 728.84 | V171: 728.84 | W171: 728.84 | X171: 728.84 | Y171: 728.84 | Z171: 728.84 | AA171: 728.84 | AB171: 728.84 | AC171: 728.84 | AD171: 728.84 | AE171: 728.84 | AF171: 728.84 | AG171: 728.84
B172: 120210 | C172: 기타자본 | D172: Other Reserves | J172: -5.711 | K172: -5.711 | L172: -5.849 | M172: -5.711 | N172: -5.711 | O172: -5.711 | P172: -5.711 | Q172: -5.711 | R172: -5.711 | S172: -5.711 | T172: -5.711 | U172: -5.711 | V172: -5.711 | W172: -5.711 | X172: -5.711 | Y172: -5.711 | Z172: -5.711 | AA172: -5.711 | AB172: -5.711 | AC172: -5.711 | AD172: -5.711 | AE172: -5.711 | AF172: -5.711 | AG172: -5.711
... B177: 120620 | C177: 비지배주주지분 | D177: Non-Controlling Interests Equity | J177: 2206.498 | K177: 2231.495 | L177: 2270.318 | M177: 2237.6 | N177: 2227.086 | O177: 2284.203 | P177: 2307.399 | Q177: 2318.864 | R177: 2346.86 | S177: 2339.419 | T177: 2320.089 | U177: 1644.003 | V177: 1426.0663 | W177: 1208.1296 | X177: 990.19286 | Y177: 772.25615 | Z177: 536.07702 | AA177: 299.8979 | AB177: 63.718769 | AC177: -172.46036 | AD177: -429.70466 | AE177: -686.94895 | AF177: -944.19325 | AG177: -1201.4375
A187: Cash Flow Statements
B189: 400000 | C189: 영업활동현금흐름 | D189: Cash Flows from Operating Activities | J189: 37.042 | K189: -352.025 | L189: 269.783 | M189: -98.274 | N189: -512.01 | O189: -457.803 | P189: -537.267 | Q189: 792.364 | R189: -1152.47 | S189: -191.347 | T189: 636.452 | U189: 588.565 | V189: -1122.5976 | W189: -1122.5976 | X189: -1122.5976 | Y189: 4562.9193 | Z189: 6743.9517 | AA189: 6743.9517 | AB189: 6743.9517 | AC189: -17478.89 | AD189: -17174.039 | AE189: -17174.039 | AF189: -17174.039 | AG189: 56910.609
B190: 400010 | C190: 당기순이익 | D190: Net Income | J190: 183.108 | K190: 224.944 | L190: 234.798 | M190: -171.974 | N190: 150.552 | O190: 212.359 | P190: 181.325 | Q190: 110.045 | R190: 208.363 | S190: 146.117 | T190: 40.106 | U190: -1160.807 | V190: -2008.8274 | W190: -2008.8274 | X190: -2008.8274 | Y190: 4908.6815 | Z190: 5413.5124 | AA190: 5413.5124 | AB190: 5413.5124 | AC190: -17451.904 | AD190: -19224.922 | AE190: -19224.922 | AF190: -19224.922 | AG190: 56355.356
B191: 400030 | C191: 현금유출이없는비용 | D191: Non-Cash Expenses | J191: 212.37 | K191: 291.338 | L191: 318.147 | M191: 243.473 | N191: 333.434 | O191: 234.676 | P191: 304.665 | Q191: 231.232 | R191: 339.219 | S191: 315.247 | T191: 190.266 | U191: 508.967 | V191: 238.25117 | W191: 238.25117 | X191: 238.25117 | Y191: 238.25117 | Z191: 212.72495 | AA191: 212.72495 | AB191: 212.72495 | AC191: 212.72495 | AD191: 192.232 | AE191: 192.232 | AF191: 192.232 | AG191: 192.232
B192: 400140 | C192: 유형자산감가상각비 | D192: Depreciation | J192: 37.764 | K192: 44.218 | L192: 43.616 | M192: 46.676 | N192: 46.917 | O192: 48.729 | P192: 55.837 | Q192: 35.119 | R192: 49.08 | S192: 53.493 | T192: 53.723 | U192: 55.094 | V192: 56.824079 | W192: 56.824079 | X192: 56.824079 | Y192: 56.824079 | Z192: 38.294726 | AA192: 38.294726 | AB192: 38.294726 | AC192: 38.294726 | AD192: 25.807476 | AE192: 25.807476 | AF192: 25.807476 | AG192: 25.807476
B193: 400150+400160 | C193: 무형자산상각비 | D193: Amortization | J193: 2.524 | K193: 2.307 | L193: 2.355 | M193: 2.248 | N193: 2.48 | O193: 2.398 | P193: 2.293 | Q193: 2.341 | R193: 2.573 | S193: 2.324 | T193: 2.57 | U193: 2.64 | V193: 3.1264634 | W193: 3.1264634 | X193: 3.1264634 | Y193: 3.1264634 | Z193: 2.8304331 | AA193: 2.8304331 | AB193: 2.8304331 | AC193: 2.8304331 | AD193: 2.5624325 | AE193: 2.5624325 | AF193: 2.5624325 | AG193: 2.5624325
B201: 400790 | C201: 현금유입이없는수익 | D201: Non-Cash Revenues | J201: -168.846 | K201: -204.336 | L201: -311.136 | M201: 88.654 | N201: -161.304 | O201: -186.576 | P201: -56.885 | Q201: -142.655 | R201: -173.394 | S201: -272.688 | T201: -13.081 | U201: -636.642 | V201: -212.01559 | W201: -212.01559 | X201: -212.01559 | Y201: -212.01559 | Z201: -210.72793 | AA201: -210.72793 | AB201: -210.72793 | AC201: -210.72793 | AD201: -209.78013 | AE201: -209.78013 | AF201: -209.78013 | AG201: -209.78013
B208: 401490 | C208: 영업관련자산부채변동 | D208: Changes in A/L from Operating Activities | J208: -134.964 | K208: -543.848 | L208: 88.135 | M208: -236.379 | N208: -807.894 | O208: -696.879 | P208: -910.445 | Q208: 598.874 | R208: -1503.575 | S208: -290.994 | T208: 485.806 | U208: 1896.763 | V208: 799.47074 | W208: 799.47074 | X208: 799.47074 | Y208: -432.52121 | Z208: 1262.5057 | AA208: 1262.5057 | AB208: 1262.5057 | AC208: -94.919797 | AD208: 1995.7042 | AE208: 1995.7042 | AF208: 1995.7042 | AG208: 500.07438
B209: 401500 | C209: 영업활동자산의감소 | D209: Decr.(Incr.) in Operating Assets | J209: -668.575 | K209: -1093.025 | L209: -226.52 | M209: -84.932 | N209: -1371.485 | O209: -1170.809 | P209: -967.298 | Q209: 153.547 | R209: -1833.071 | S209: -795.061 | T209: 385.453 | U209: 458.178 | V209: -146.10218 | W209: -146.10218 | X209: -146.10218 | Y209: -1378.0941 | Z209: -174.9564 | AA209: -174.9564 | AB209: -174.9564 | AC209: -1532.3819 | AD209: -209.71839 | AE209: -209.71839 | AF209: -209.71839 | AG209: -1705.3482
B210: 401510 | C210: 매출채권및기타채권의감소 | D210: Decr.(Incr.) in Trade and Other Receivables | J210: -432.277 | K210: -757.537 | L210: -101.759 | M210: 215.84 | N210: -1102.715 | O210: -1012.512 | P210: -940.059 | Q210: 168.998 | R210: -1823.916 | S210: -695.204 | T210: 216.198 | U210: 762.548 | V210: 0 | W210: 0 | X210: 0 | Y210: -1231.9919 | Z210: 0 | AA210: 0 | AB210: 0 | AC210: -1357.4255 | AD210: 0 | AE210: 0 | AF210: 0 | AG210: -1495.6298
B211: 401590 | C211: 재고자산의감소 | D211: Decr.(Incr.) in Inventories | J211: 18.037 | K211: -65.529 | L211: -18.035 | M211: -25.273 | N211: 8.072 | O211: 2.03 | P211: 20.913 | Q211: 23.16 | R211: 19.373 | S211: -1.358 | T211: -1.1 | U211: 26.323 | V211: -19.764842 | W211: -19.764842 | X211: -19.764842 | Y211: -19.764842 | Z211: -21.777172 | AA211: -21.777172 | AB211: -21.777172 | AC211: -21.777172 | AD211: -23.994384 | AE211: -23.994384 | AF211: -23.994384 | AG211: -23.994384
...

Sheet ForecastQ
C2: ForecastQ | D2: ForecastQ | AS2: Income Statement | DB2: Annual
AS3: Balance Sheet
AO4: History | AS4: Cash Flow Statements
B5: Period_CY_ | C5: (*) 우측(DF열)에서 연간금액 조회 가능 | J5: 2008.03 | K5: 2008.06 | L5: 2008.09 | M5: 2008.12 | N5: 2009.03 | O5: 2009.06 | P5: 2009.09 | Q5: 2009.12 | R5: 2010.03 | S5: 2010.06 | T5: 2010.09 | U5: 2010.12 | V5: 2011.03 | W5: 2011.06 | X5: 2011.09 | Y5: 2011.12 | Z5: 2012.03 | AA5: 2012.06 | AB5: 2012.09 | AC5: 2012.12 | AD5: 2013.03 | AE5: 2013.06 | AF5: 2013.09 | AG5: 2013.12 | AH5: 2014.03 | AI5: 2014.06 | AJ5: 2014.09 | AK5: 2014.12 | AL5: 2015.03 | AM5: 2015.06 | AN5: 2015.09 | AO5: 2015.12 | AP5: 2016.03 | AQ5: 2016.06 | AR5: 2016.09 | AS5: 2016.12 | AT5: 2017.03 | AU5: 2017.06 | AV5: 2017.09 | AW5: 2017.12 | AX5: 2018.03 | AY5: 2018.06 | AZ5: 2018.09 | BA5: 2018.12 | BB5: 2019.03 | BC5: 2019.06 | BD5: 2019.09 | BE5: 2019.12 | BF5: 2020.03 | BG5: 2020.06 | BH5: 2020.09 | BI5: 2020.12 | BJ5: 2021.03 | BK5: 2021.06 | BL5: 2021.09 | BM5: 2021.12 | BN5: 2022.03 | BO5: 2022.06 | BP5: 2022.09 | BQ5: 2022.12 | BR5: 2023.03 | BS5: 2023.06 | BT5: 2023.09 | BU5: 2023.12 | BV5: 2024.03 | BW5: 2024.06 | BX5: 2024.09 | BY5: 2024.12 | BZ5: 2025.03 | CA5: 2025.06 | CB5: 2025.09 | CC5: 2025.12 | CD5: 2026.03 | CE5: 2026.06 | CF5: 2026.09 | CG5: 2026.12 | CH5: 2027.03 | CI5: 2027.06 | CJ5: 2027.09 | CK5: 2027.12 | CL5: 2028.03 | CM5: 2028.06 | CN5: 2028.09 | CO5: 2028.12 | CP5: 2029.03 | CQ5: 2029.06 | CR5: 2029.09 | CS5: 2029.12 | CT5: 2030.03 | CU5: 2030.06 | CV5: 2030.09 | CW5: 2030.12 | DA5: Period_CY_ | DC5: 2008.12 | DD5: 2009.12 | DE5: 2010.12 | DF5: 2011.12 | DG5: 2012.12 | DH5: 2013.12 | DI5: 2014.12 | DJ5: 2015.12 | DK5: 2016.12 | DL5: 2017.12 | DM5: 2018.12 | DN5: 2019.12
B6: Period_FY_ | J6: 2008_1A | K6: 2008_2A | L6: 2008_3A | M6: 2008_4A | N6: 2009_1A | O6: 2009_2A | P6: 2009_3A | Q6: 2009_4A | R6: 2010_1A | S6: 2010_2A | T6: 2010_3A | U6: 2010_4A | V6: 2011_1A | W6: 2011_2A | X6: 2011_3A | Y6: 2011_4A | Z6: 2012_1A | AA6: 2012_2A | AB6: 2012_3A | AC6: 2012_4A | AD6: 2013_1A | AE6: 2013_2A | AF6: 2013_3A | AG6: 2013_4A | AH6: 2014_1A | AI6: 2014_2A | AJ6: 2014_3A | AK6: 2014_4A | AL6: 2015_1A | AM6: 2015_2A | AN6: 2015_3A | AO6: 2015_4A | AP6: 2016_1A | AQ6: 2016_2A | AR6: 2016_3A | AS6: 2016_4A | AT6: 2017_1A | AU6: 2017_2A | AV6: 2017_3A | AW6: 2017_4A | AX6: 2018_1A | AY6: 2018_2A | AZ6: 2018_3A | BA6: 2018_4A | BB6: 2019_1A | BC6: 2019_2A | BD6: 2019_3A | BE6: 2019_4A | BF6: 2020_1A | BG6: 2020_2A | BH6: 2020_3A | BI6: 2020_4A | BJ6: 2021_1A | BK6: 2021_2A | BL6: 2021_3A | BM6: 2021_4A | BN6: 2022_1A | BO6: 2022_2A | BP6: 2022_3A | BQ6: 2022_4A | BR6: 2023_1A | BS6: 2023_2A | BT6: 2023_3A | BU6: 2023_4A | BV6: 2024_1A | BW6: 2024_2A | BX6: 2024_3A | BY6: 2024_4A | BZ6: 2025_1F | CA6: 2025_2F | CB6: 2025_3F | CC6: 2025_4F | CD6: 2026_1F | CE6: 2026_2F | CF6: 2026_3F | CG6: 2026_4F | CH6: 2027_1F | CI6: 2027_2F | CJ6: 2027_3F | CK6: 2027_4F | CL6: 2028_1F | CM6: 2028_2F | CN6: 2028_3F | CO6: 2028_4F | CP6: 2029_1F | CQ6: 2029_2F | CR6: 2029_3F | CS6: 2029_4F | CT6: 2030_1F | CU6: 2030_2F | CV6: 2030_3F | CW6: 2030_4F | DA6: Period_FY_ | DC6: 2008A | DD6: 2009A | DE6: 2010A | DF6: 2011A | DG6: 2012A | DH6: 2013A | DI6: 2014A | DJ6: 2015A | DK6: 2016A | DL6: 2017A | DM6: 2018A | DN6: 2019A
C8: Balance_BS : Asset - (Liability + Equity) | D8: BS: A-(L+E) | BZ8: -5477.7124 | CA8: -5825.0527 | CB8: -6172.3931 | CC8: -6519.7335 | CD8: -7244.0848 | CE8: -7968.4362 | CF8: -8692.7875 | CG8: -9417.1389 | CH8: -10791.209 | CI8: -12165.278 | CJ8: -13539.348 | CK8: -14913.418 | CL8: -17362.768 | CM8: -19812.118 | CN8: -22261.468 | CO8: -24710.818 | CP8: -28904.055 | CQ8: -33097.293 | CR8: -37290.53 | CS8: -41483.768 | CT8: -48473.703 | CU8: -55463.638 | CV8: -62453.573 | CW8: -69443.508 | CX8: FALSE
C9: Balance_CF : Cash(BS) - Cash(CF) | D9: CF: Cash(BS) - Cash(CF) | BZ9: -4114.8576 | CA9: -3099.3432 | CB9: -2083.8289 | CC9: -6753.8315 | CD9: -13592.418 | CE9: -20431.004 | CF9: -27269.59 | CG9: -9885.3349 | CH9: 7203.2329 | CI9: 24291.801 | CJ9: 41380.369 | CK9: -15615.712 | CL9: -80992.095 | CM9: -146368.48 | CN9: -211744.86 | CO9: -25647.21 | CP9: 176093.48 | CQ9: 377834.16 | CR9: 579574.85 | CS9: -42654.258 | CT9: -732599.1 | CU9: -1422543.9 | CV9: -2112488.8 | CW9: -70848.096 | CX9: FALSE
A13: Income Statement | CZ13: Income Statement
B15: 200000 | C15: 매출액 | D15: Sales | J15: 0 | K15: 0 | L15: 0 | M15: 0 | N15: 0 | O15: 0 | P15: 0 | Q15: 0 | R15: 0 | S15: 0 | T15: 0 | U15: 0 | V15: 2285.5006 | W15: 2870.005 | X15: 2961.7368 | Y15: 3802.9246 | Z15: 2705.571 | AA15: 3181.345 | AB15: 3319.281 | AC15: 4118.624 | AD15: 2861.221 | AE15: 3470.697 | AF15: 3534.919 | AG15: 3985.205 | AH15: 3290.554 | AI15: 4702.888 | AJ15: 4259.166 | AK15: 5023.872 | AL15: 3943.209 | AM15: 4815.544 | AN15: 4711.383 | AO15: 5763.044 | AP15: 4287.904 | AQ15: 4686.557 | AR15: 4464.114 | AS15: 5386.44 | AT15: 4129.693 | AU15: 4217.811 | AV15: 4243.113 | AW15: 4296.473 | AX15: 3538.167 | AY15: 4240.094 | AZ15: 4486.329 | BA15: 4466.304 | BB15: 3877.659 | BC15: 4681.888 | BD15: 4087.761 | BE15: 4631.484 | BF15: 4058.864 | BG15: 4544.15 | BH15: 4042.483 | BI15: 4325.362 | BJ15: 4149.57 | BK15: 4383.532 | BL15: 4351.948 | BM15: 5180.484 | BN15: 4145.303 | BO15: 5579.448 | BP15: 5430.844 | BQ15: 6083.487 | BR15: 6031.081 | BS15: 7163.359 | BT15: 7858.53 | BU15: 8598.387 | BV15: 8545.258 | BW15: 8621.236 | BX15: 8256.906 | BY15: 7246.868 | BZ15: 8999.1363 | CA15: 8999.1363 | CB15: 8999.1363 | CC15: 8999.1363 | CD15: 9915.3706 | CE15: 9915.3706 | CF15: 9915.3706 | CG15: 9915.3706 | CH15: 10924.89 | CI15: 10924.89 | CJ15: 10924.89 | CK15: 10924.89 | CL15: 12037.192 | CM15: 12037.192 | CN15: 12037.192 | CO15: 12037.192 | CP15: 13262.742 | CQ15: 13262.742 | CR15: 13262.742 | CS15: 13262.742 | CT15: 14613.069 | CU15: 14613.069 | CV15: 14613.069 | CW15: 14613.069 | DA15: 200000 | DB15: 매출액 | DC15: 8036.4935 | DD15: 10390.595 | DE15: 11217.013 | DF15: 11920.167 | DG15: 13324.821 | DH15: 13852.042 | DI15: 17276.48 | DJ15: 19233.18 | DK15: 18825.015 | DL15: 16887.09 | DM15: 16730.894 | DN15: 17278.792
C16: (분기배분, manual) | D16: (% growth) | J16: 0 | K16: 0 | L16: 0 | M16: 0 | N16: 0 | O16: 0 | P16: 0 | Q16: 0 | R16: 0 | S16: 0 | T16: 0 | U16: 0 | V16: 0.19173394 | W16: 0.24076886 | X16: 0.24846437 | Y16: 0.31903283 | Z16: 0.20304746 | AA16: 0.2387533 | AB16: 0.24910511 | AC16: 0.30909413 | AD16: 0.2065559 | AE16: 0.2505549 | AF16: 0.25519118 | AG16: 0.28769802 | AH16: 0.19046438 | AI16: 0.27221332 | AJ16: 0.24652973 | AK16: 0.29079257 | AL16: 0.20502117 | AM16: 0.2503769 | AN16: 0.24496121 | AO16: 0.29964073 | AP16: 0.22777692 | AQ16: 0.24895369 | AR16: 0.23713734 | AS16: 0.28613204 | AT16: 0.24454734 | AU16: 0.24976541 | AV16: 0.25126372 | AW16: 0.25442353 | AX16: 0.21147507 | AY16: 0.25342902 | AZ16: 0.2681464 | BA16: 0.26694951 | BB16: 0.22441725 | BC16: 0.27096153 | BD16: 0.23657678 | BE16: 0.26804443 | BF16: 0.23916668 | BG16: 0.26776193 | BH16: 0.23820144 | BI16: 0.25486995 | BJ16: 0.2296954 | BK16: 0.24264613 | BL16: 0.24089783 | BM16: 0.28676063 | BN16: 0.19517336 | BO16: 0.26269723 | BP16: 0.25570051 | BQ16: 0.2864289 | BR16: 0.20339983 | BS16: 0.24158621 | BT16: 0.26503104 | BU16: 0.28998292 | BV16: 0.26156069 | BW16: 0.2638863 | BX16: 0.25273457 | BY16: 0.22181844 | BZ16: 0.25 | CA16: 0.25 | CB16: 0.25 | CC16: 0.25 | CD16: 0.25 | CE16: 0.25 | CF16: 0.25 | CG16: 0.25 | CH16: 0.25 | CI16: 0.25 | CJ16: 0.25 | CK16: 0.25 | CL16: 0.25 | CM16: 0.25 | CN16: 0.25 | CO16: 0.25 | CP16: 0.25 | CQ16: 0.25 | CR16: 0.25 | CS16: 0.25 | CT16: 0.25 | CU16: 0.25 | CV16: 0.25 | CW16: 0.25
B18: 200360 | C18: 매출원가 | D18: Cost of Sales | J18: 0 | K18: 0 | L18: 0 | M18: 0 | N18: 0 | O18: 0 | P18: 0 | Q18: 0 | R18: 0 | S18: 0 | T18: 0 | U18: 0 | V18: 2036.8264 | W18: 2566.8424 | X18: 2604.2633 | Y18: 3543.9239 | Z18: 2461.555 | AA18: 2906.66 | AB18: 2959.784 | AC18: 3747.95 | AD18: 2590.228 | AE18: 3162.457 | AF18: 3225.819 | AG18: 3753.861 | AH18: 2997.44 | AI18: 4234.801 | AJ18: 3897.897 | AK18: 4734.768 | AL18: 3603.914 | AM18: 4418.6 | AN18: 4308.803 | AO18: 5176.821 | AP18: 3925.333 | AQ18: 4180.289 | AR18: 4012.663 | AS18: 4776.99 | AT18: 3682.38 | AU18: 3746.099 | AV18: 3806.151 | AW18: 3873.496 | AX18: 3120.923 | AY18: 3801.835 | AZ18: 4044.589 | BA18: 4102.4 | BB18: 3487.987 | BC18: 4217.189 | BD18: 3671.56 | BE18: 4176.151 | BF18: 3623.956 | BG18: 4229.87 | BH18: 3694.079 | BI18: 4026.091 | BJ18: 3749.802 | BK18: 3965.536 | BL18: 3930.467 | BM18: 4622.493 | BN18: 3774.063 | BO18: 5137.759 | BP18: 5097.562 | BQ18: 5716.95 | BR18: 5651.16 | BS18: 6765.776 | BT18: 7342.408 | BU18: 8189.205 | BV18: 8011.925 | BW18: 8279.049 | BX18: 7908.598 | BY18: 8687.629 | BZ18: 10788.268 | CA18: 10788.268 | CB18: 10788.268 | CC18: 3870.7595 | CD18: 4264.8554 | CE18: 4264.8554 | CF18: 4264.8554 | CG18: 27130.271 | CH18: 29892.502 | CI18: 29892.502 | CJ18: 29892.502 | CK18: -45687.776 | CL18: -50339.413 | CM18: -50339.413 | CN18: -50339.413 | CO18: 199486.72 | CP18: 219797.18 | CQ18: 219797.18 | CR18: 219797.18 | CS18: -605988.3 | CT18: -667686.14 | CU18: -667686.14 | CV18: -667686.14 | CW18: 2061898.8 | DA18: 200360 | DB18: 매출원가 | DC18: 7148.7166 | DD18: 9441.7516 | DE18: 9908.9062 | DF18: 10751.856 | DG18: 12075.949 | DH18: 12732.365 | DI18: 15864.906 | DJ18: 17508.138 | DK18: 16895.275 | DL18: 15108.126 | DM18: 15069.747 | DN18: 15552.887
C19: (% of sales, manual) | D19: (% of sales) | J19: 0 | K19: 0 | L19: 0 | M19: 0 | N19: 0 | O19: 0 | P19: 0 | Q19: 0 | R19: 0 | S19: 0 | T19: 0 | U19: 0 | V19: 0.89119486 | W19: 0.8943686 | X19: 0.87930276 | Y19: 0.93189434 | Z19: 0.9098098 | AA19: 0.91365759 | AB19: 0.89169432 | AC19: 0.91000052 | AD19: 0.90528764 | AE19: 0.91118787 | AF19: 0.91255811 | AG19: 0.94194928 | AH19: 0.9109226 | AI19: 0.90046818 | AJ19: 0.91517846 | AK19: 0.94245395 | AL19: 0.9139546 | AM19: 0.91757027 | AN19: 0.91455163 | AO19: 0.89827893 | AP19: 0.9154433 | AQ19: 0.89197443 | AR19: 0.89887109 | AS19: 0.88685477 | AT19: 0.89168372 | AU19: 0.88816189 | AV19: 0.89701853 | AW19: 0.90155251 | AX19: 0.8820734 | AY19: 0.89663932 | AZ19: 0.90153642 | BA19: 0.91852234 | BB19: 0.89950844 | BC19: 0.90074538 | BD19: 0.89818363 | BE19: 0.90168745 | BF19: 0.89284982 | BG19: 0.93083855 | BH19: 0.91381436 | BI19: 0.93081018 | BJ19: 0.90366038 | BK19: 0.90464402 | BL19: 0.90315119 | BM19: 0.89228979 | BN19: 0.91044322 | BO19: 0.92083643 | BP19: 0.93863164 | BQ19: 0.93974886 | BR19: 0.93700615 | BS19: 0.94449769 | BT19: 0.93432334 | BU19: 0.95241177 | BV19: 0.93758726 | BW19: 0.96030882 | BX19: 0.95781616 | BY19: 1.1988115 | BZ19: 1.1988115 | CA19: 1.1988115 | CB19: 1.1988115 | CC19: 0.43012567 | CD19: 0.43012567 | CE19: 0.43012567 | CF19: 0.43012567 | CG19: 2.7361833 | CH19: 2.7361833 | CI19: 2.7361833 | CJ19: 2.7361833 | CK19: -4.1819896 | CL19: -4.1819896 | CM19: -4.1819896 | CN19: -4.1819896 | CO19: 16.572529 | CP19: 16.572529 | CQ19: 16.572529 | CR19: 16.572529 | CS19: -45.691027 | CT19: -45.691027 | CU19: -45.691027 | CV19: -45.691027 | CW19: 141.09964
B21: 200810 | C21: 매출총이익 | D21: Gross Profit | J21: 0 | K21: 0 | L21: 0 | M21: 0 | N21: 0 | O21: 0 | P21: 0 | Q21: 0 | R21: 0 | S21: 0 | T21: 0 | U21: 0 | V21: 248.67422 | W21: 303.16264 | X21: 357.47346 | Y21: 259.00068 | Z21: 244.016 | AA21: 274.685 | AB21: 359.497 | AC21: 370.674 | AD21: 270.993 | AE21: 308.24 | AF21: 309.1 | AG21: 231.344 | AH21: 293.114 | AI21: 468.087 | AJ21: 361.269 | AK21: 289.104 | AL21: 339.295 | AM21: 396.944 | AN21: 402.58 | AO21: 586.223 | AP21: 362.571 | AQ21: 506.268 | AR21: 451.451 | AS21: 609.45 | AT21: 447.313 | AU21: 471.712 | AV21: 436.962 | AW21: 422.977 | AX21: 417.244 | AY21: 438.259 | AZ21: 441.74 | BA21: 363.904 | BB21: 389.672 | BC21: 464.699 | BD21: 416.201 | BE21: 455.333 | BF21: 434.908 | BG21: 314.28 | BH21: 348.404 | BI21: 299.271 | BJ21: 399.768 | BK21: 417.996 | BL21: 421.481 | BM21: 557.991 | BN21: 371.24 | BO21: 441.689 | BP21: 333.282 | BQ21: 366.537 | BR21: 379.921 | BS21: 397.583 | BT21: 516.122 | BU21: 409.182 | BV21: 533.333 | BW21: 342.187 | BX21: 348.308 | BY21: -1440.761 | BZ21: -1789.1322 | CA21: -1789.1322 | CB21: -1789.1322 | CC21: 5128.3768 | CD21: 5650.5152 | CE21: 5650.5152 | CF21: 5650.5152 | CG21: -17214.901 | CH21: -18967.612 | CI21: -18967.612 | CJ21: -18967.612 | CK21: 56612.666 | CL21: 62376.605 | CM21: 62376.605 | CN21: 62376.605 | CO21: -187449.53 | CP21: -206534.43 | CQ21: -206534.43 | CR21: -206534.43 | CS21: 619251.04 | CT21: 682299.21 | CU21: 682299.21 | CV21: 682299.21 | CW21: -2047285.8 | DA21: 200810 | DB21: 매출총이익 | DC21: 887.77696 | DD21: 948.84324 | DE21: 1308.1073 | DF21: 1168.311 | DG21: 1248.872 | DH21: 1119.677 | DI21: 1411.574 | DJ21: 1725.042 | DK21: 1929.74 | DL21: 1778.964 | DM21: 1661.147 | DN21: 1725.905
C22: (% of sales) | D22: (% of sales) | J22: 0 | K22: 0 | L22: 0 | M22: 0 | N22: 0 | O22: 0 | P22: 0 | Q22: 0 | R22: 0 | S22: 0 | T22: 0 | U22: 0 | V22: 0.10880514 | W22: 0.1056314 | X22: 0.12069724 | Y22: 0.068105657 | Z22: 0.090190204 | AA22: 0.086342412 | AB22: 0.10830568 | AC22: 0.089999476 | AD22: 0.094712362 | AE22: 0.088812132 | AF22: 0.08744189 | AG22: 0.058050715 | AH22: 0.089077402 | AI22: 0.09953182 | AJ22: 0.084821535 | AK22: 0.057546052 | AL22: 0.086045401 | AM22: 0.082429732 | AN22: 0.08544837 | AO22: 0.10172107 | AP22: 0.084556697 | AQ22: 0.10802557 | AR22: 0.10112891 | AS22: 0.11314523 | AT22: 0.10831628 | AU22: 0.11183811 | AV22: 0.10298147 | AW22: 0.098447494 | AX22: 0.1179266 | AY22: 0.10336068 | AZ22: 0.098463577 | BA22: 0.08147766 | BB22: 0.10049156 | BC22: 0.099254617 | BD22: 0.10181637 | BE22: 0.098312549 | BF22: 0.10715018 | BG22: 0.069161449 | BH22: 0.086185644 | BI22: 0.069189816 | BJ22: 0.096339621 | BK22: 0.095355982 | BL22: 0.096848813 | BM22: 0.10771021 | BN22: 0.089556783 | BO22: 0.079163566 | BP22: 0.061368362 | BQ22: 0.060251136 | BR22: 0.062993848 | BS22: 0.055502314 | BT22: 0.06567666 | BU22: 0.047588228 | BV22: 0.062412744 | BW22: 0.039691177 | BX22: 0.04218384 | BY22: -0.19881154 | BZ22: -0.19881154 | CA22: -0.19881154 | CB22: -0.19881154 | CC22: 0.56987433 | CD22: 0.56987433 | CE22: 0.56987433 | CF22: 0.56987433 | CG22: -1.7361833 | CH22: -1.7361833 | CI22: -1.7361833 | CJ22: -1.7361833 | CK22: 5.1819896 | CL22: 5.1819896 | CM22: 5.1819896 | CN22: 5.1819896 | CO22: -15.572529 | CP22: -15.572529 | CQ22: -15.572529 | CR22: -15.572529 | CS22: 46.691027 | CT22: 46.691027 | CU22: 46.691027 | CV22: 46.691027 | CW22: -140.09964
B25: 200820 | C25: 판매비와 관리비 | D25: SG&A | J25: 0 | K25: 0 | L25: 0 | M25: 0 | N25: 0 | O25: 0 | P25: 0 | Q25: 0 | R25: 0 | S25: 0 | T25: 0 | U25: 0 | V25: 97.800588 | W25: 112.58617 | X25: 102.7165 | Y25: 119.61174 | Z25: 97.446 | AA25: 117.216 | AB25: 139.77 | AC25: 134.032 | AD25: 92.356 | AE25: 107.588 | AF25: 103.047 | AG25: 112.589 | AH25: 105.46 | AI25: 188.519 | AJ25: 130.57 | AK25: 157.83 | AL25: 138.641 | AM25: 142.636 | AN25: 138.187 | AO25: 216.25 | AP25: 155.395 | AQ25: 237.869 | AR25: 176.331 | AS25: 201.186 | AT25: 218.681 | AU25: 189.914 | AV25: 155.911 | AW25: 228.353 | AX25: 198.774 | AY25: 217.372 | AZ25: 203.821 | BA25: 201.191 | BB25: 184.469 | BC25: 219.609 | BD25: 177.039 | BE25: 285.121 | BF25: 269.561 | BG25: 160.422 | BH25: 208.558 | BI25: 209.35 | BJ25: 198.869 | BK25: 277.028 | BL25: 201.117 | BM25: 366.718 | BN25: 199.759 | BO25: 266.281 | BP25: 179.576 | BQ25: 292.23 | BR25: 206.409 | BS25: 174.032 | BT25: 272.253 | BU25: 264.684 | BV25: 282.42 | BW25: 194.884 | BX25: 234.017 | BY25: 335.166 | BZ25: 288.12446 | CA25: 288.12446 | CB25: 288.12446 | CC25: 288.12446 | CD25: 310.84517 | CE25: 310.84517 | CF25: 310.84517 | CG25: 310.84517 | CH25: 337.94268 | CI25: 337.94268 | CJ25: 337.94268 | CK25: 337.94268 | CL25: 369.19855 | CM25: 369.19855 | CN25: 369.19855 | CO25: 369.19855 | CP25: 404.58782 | CQ25: 404.58782 | CR25: 404.58782 | CS25: 404.58782 | CT25: 444.22842 | CU25: 444.22842 | CV25: 444.22842 | CW25: 444.22842 | DA25: 200820 | DB25: 판매비와 관리비 | DC25: 320.87371 | DD25: 367.80215 | DE25: 552.8057 | DF25: 432.715 | DG25: 488.464 | DH25: 415.58 | DI25: 582.379 | DJ25: 635.714 | DK25: 770.781 | DL25: 792.859 | DM25: 821.158 | DN25: 866.238
C26: (% of sales) | D26: (% of sales) | J26: 0 | K26: 0 | L26: 0 | M26: 0 | N26: 0 | O26: 0 | P26: 0 | Q26: 0 | R26: 0 | S26: 0 | T26: 0 | U26: 0 | V26: 0.042791757 | W26: 0.039228562 | X26: 0.034681173 | Y26: 0.031452566 | Z26: 0.036016796 | AA26: 0.036844794 | AB26: 0.042108517 | AC26: 0.032542908 | AD26: 0.032278527 | AE26: 0.030998961 | AF26: 0.029151163 | AG26: 0.028251746 | AH26: 0.032049314 | AI26: 0.040085794 | AJ26: 0.030656236 | AK26: 0.031416007 | AL26: 0.035159435 | AM26: 0.029619914 | AN26: 0.029330453 | AO26: 0.037523573 | AP26: 0.036240317 | AQ26: 0.050755597 | AR26: 0.039499663 | AS26: 0.037350458 | AT26: 0.052953331 | AU26: 0.045026674 | AV26: 0.036744485 | AW26: 0.053148943 | AX26: 0.056179937 | AY26: 0.051265845 | AZ26: 0.045431577 | BA26: 0.045046419 | BB26: 0.047572259 | BC26: 0.046906077 | BD26: 0.043309528 | BE26: 0.061561478 | BF26: 0.066412918 | BG26: 0.035302972 | BH26: 0.051591559 | BI26: 0.048400573 | BJ26: 0.047925207 | BK26: 0.06319744 | BL26: 0.046213098 | BM26: 0.070788366 | BN26: 0.04818924 | BO26: 0.047725331 | BP26: 0.033065947 | BQ26: 0.048036595 | BR26: 0.034224213 | BS26: 0.024294748 | BT26: 0.034644266 | BU26: 0.030782983 | BV26: 0.033049909 | BW26: 0.022605111 | BX26: 0.028341972 | BY26: 0.046249773 | BZ26: 0.032016901 | CA26: 0.032016901 | CB26: 0.032016901 | CC26: 0.032016901 | CD26: 0.031349829 | CE26: 0.031349829 | CF26: 0.031349829 | CG26: 0.031349829 | CH26: 0.030933279 | CI26: 0.030933279 | CJ26: 0.030933279 | CK26: 0.030933279 | CL26: 0.030671484 | CM26: 0.030671484 | CN26: 0.030671484 | CO26: 0.030671484 | CP26: 0.030505594 | CQ26: 0.030505594 | CR26: 0.030505594 | CS26: 0.030505594 | CT26: 0.030399392 | CU26: 0.030399392 | CV26: 0.030399392 | CW26: 0.030399392
B28: 200821 | C28: 인건비및복리후생비 | D28: Salaries and Wages | J28: 0 | K28: 0 | L28: 0 | M28: 0 | N28: 0 | O28: 0 | P28: 0 | Q28: 0 | R28: 0 | S28: 0 | T28: 0 | U28: 0 | V28: 55.225 | W28: 66.503759 | X28: 58.414505 | Y28: 68.227736 | Z28: 61.397 | AA28: 68.468 | AB28: 67.387 | AC28: 68.394 | AD28: 58.402 | AE28: 68.954 | AF28: 65.889 | AG28: 63.136 | AH28: 62.683 | AI28: 89.303 | AJ28: 77.423 | AK28: 81.235 | AL28: 79.753 | AM28: 83.803 | AN28: 81.276 | AO28: 85.347 | AP28: 90.214 | AQ28: 125.957 | AR28: 99.55 | AS28: 103.495 | AT28: 139.214 | AU28: 93.366 | AV28: 98.377 | AW28: 100.889 | AX28: 109.048 | AY28: 145.207 | AZ28: 102.925 | BA28: 118.304 | BB28: 109.849 | BC28: 146.017 | BD28: 104.925 | BE28: 105.823 | BF28: 122.546 | BG28: 143.774 | BH28: 106.184 | BI28: 125.756 | BJ28: 114.244 | BK28: 152.032 | BL28: 111.865 | BM28: 135.828 | BN28: 117.485 | BO28: 162.113 | BP28: 122.696 | BQ28: 136.083 | BR28: 121.822 | BS28: 167.215 | BT28: 128.854 | BU28: 165.262 | BV28: 204.274 | BW28: 102.038 | BX28: 136.546 | BY28: 190.682 | BZ28: 174.51074 | CA28: 174.51074 | CB28: 174.51074 | CC28: 174.51074 | CD28: 192.27831 | CE28: 192.27831 | CF28: 192.27831 | CG28: 192.27831 | CH28: 211.85485 | CI28: 211.85485 | CJ28: 211.85485 | CK28: 211.85485 | CL28: 233.42456 | CM28: 233.42456 | CN28: 233.42456 | CO28: 233.42456 | CP28: 257.19035 | CQ28: 257.19035 | CR28: 257.19035 | CS28: 257.19035 | CT28: 283.37582 | CU28: 283.37582 | CV28: 283.37582 | CW28: 283.37582 | DA28: 200821 | DB28: 인건비및복리후생비 | DC28: 157.94683 | DD28: 173.58203 | DE28: 214.30022 | DF28: 248.371 | DG28: 265.646 | DH28: 256.381 | DI28: 310.644 | DJ28: 330.179 | DK28: 419.216 | DL28: 431.846 | DM28: 475.484 | DN28: 466.614
C29: (분기배분, manual) | D29: (% growth) | J29: 0 | K29: 0 | L29: 0 | M29: 0 | N29: 0 | O29: 0 | P29: 0 | Q29: 0 | R29: 0 | S29: 0 | T29: 0 | U29: 0 | V29: 0.22234882 | W29: 0.26775976 | X29: 0.23519052 | Y29: 0.2747009 | Z29: 0.23112337 | AA29: 0.25774151 | AB29: 0.25367218 | AC29: 0.25746294 | AD29: 0.22779379 | AE29: 0.26895129 | AF29: 0.25699642 | AG29: 0.2462585 | AH29: 0.20178404 | AI29: 0.28747698 | AJ29: 0.24923385 | AK29: 0.26150513 | AL29: 0.24154474 | AM29: 0.25381081 | AN29: 0.24615739 | AO29: 0.25848706 | AP29: 0.21519694 | AQ29: 0.30045847 | AR29: 0.23746708 | AS29: 0.2468775 | AT29: 0.32236955 | AU29: 0.21620207 | AV29: 0.22780575 | AW29: 0.23362263 | AX29: 0.22934105 | AY29: 0.30538777 | AZ29: 0.21646365 | BA29: 0.24880753 | BB29: 0.23541728 | BC29: 0.31292889 | BD29: 0.22486466 | BE29: 0.22678917 | BF29: 0.2459479 | BG29: 0.28855216 | BH29: 0.21310962 | BI29: 0.25239032 | BJ29: 0.222278 | BK29: 0.29579994 | BL29: 0.21764931 | BM29: 0.26427275 | BN29: 0.21822069 | BO29: 0.30111427 | BP29: 0.22789978 | BQ29: 0.25276526 | BR29: 0.20890229 | BS29: 0.28674293 | BT29: 0.22096088 | BU29: 0.28339389 | BV29: 0.32243268 | BW29: 0.16106008 | BX29: 0.21552862 | BY29: 0.30097863 | BZ29: 0.25 | CA29: 0.25 | CB29: 0.25 | CC29: 0.25 | CD29: 0.25 | CE29: 0.25 | CF29: 0.25 | CG29: 0.25 | CH29: 0.25 | CI29: 0.25 | CJ29: 0.25 | CK29: 0.25 | CL29: 0.25 | CM29: 0.25 | CN29: 0.25 | CO29: 0.25 | CP29: 0.25 | CQ29: 0.25 | CR29: 0.25 | CS29: 0.25 | CT29: 0.25 | CU29: 0.25 | CV29: 0.25 | CW29: 0.25
B31: 200822 | C31: 일반관리비 | D31: General & Administrative Expenses | J31: 0 | K31: 0 | L31: 0 | M31: 0 | N31: 0 | O31: 0 | P31: 0 | Q31: 0 | R31: 0 | S31: 0 | T31: 0 | U31: 0 | V31: 10.27 | W31: 7.757 | X31: 9.333 | Y31: 7.787 | Z31: 9.721 | AA31: 9.05 | AB31: 9.152 | AC31: 4.391 | AD31: 9.338 | AE31: 9.298 | AF31: 8.843 | AG31: 13.983 | AH31: 14.331 | AI31: 16.416 | AJ31: 14.207 | AK31: 20.666 | AL31: 17.104 | AM31: 13.026 | AN31: 13.305 | AO31: 14.539 | AP31: 15.193 | AQ31: 14.555 | AR31: 15.652 | AS31: 18.959 | AT31: 15.761 | AU31: 20.911 | AV31: 17.094 | AW31: 22.856 | AX31: 23.93 | AY31: 14.494 | AZ31: 24.652 | BA31: 28.01 | BB31: 21.405 | BC31: 18.453 | BD31: 24.11 | BE31: 21.806 | BF31: 18.131 | BG31: 20.583 | BH31: 18.144 | BI31: 20.612 | BJ31: 13.846 | BK31: 20.961 | BL31: 17.838 | BM31: 18.936 | BN31: 15.491 | BO31: 24.796 | BP31: 19.296 | BQ31: 31.678 | BR31: 18.116 | BS31: 24.288 | BT31: 19.156 | BU31: 25.059 | BV31: 18.857 | BW31: 18.449 | BX31: 21.023 | BY31: 38.815 | BZ31: 26.758645 | CA31: 26.758645 | CB31: 26.758645 | CC31: 26.758645 | CD31: 29.483038 | CE31: 29.483038 | CF31: 29.483038 | CG31: 29.483038 | CH31: 32.484812 | CI31: 32.484812 | CJ31: 32.484812 | CK31: 32.484812 | CL31: 35.792207 | CM31: 35.792207 | CN31: 35.792207 | CO31: 35.792207 | CP31: 39.43634 | CQ31: 39.43634 | CR31: 39.43634 | CS31: 39.43634 | CT31: 43.451496 | CU31: 43.451496 | CV31: 43.451496 | CW31: 43.451496 | DA31: 200822 | DB31: 일반관리비 | DC31: 26.715606 | DD31: 31.753244 | DE31: 41.608142 | DF31: 35.147 | DG31: 32.314 | DH31: 41.462 | DI31: 65.62 | DJ31: 57.974 | DK31: 64.359 | DL31: 76.622 | DM31: 91.086 | DN31: 85.774
C32: (분기배분, manual) | D32: (% growth) | J32: 0 | K32: 0 | L32: 0 | M32: 0 | N32: 0 | O32: 0 | P32: 0 | Q32: 0 | R32: 0 | S32: 0 | T32: 0 | U32: 0 | V32: 0.29220133 | W32: 0.22070162 | X32: 0.26554187 | Y32: 0.22155518 | Z32: 0.30082936 | AA32: 0.28006437 | AB32: 0.28322089 | AC32: 0.13588537 | AD32: 0.22521827 | AE32: 0.22425353 | AF32: 0.21327963 | AG32: 0.33724856 | AH32: 0.21839378 | AI32: 0.25016763 | AJ32: 0.21650411 | AK32: 0.31493447 | AL32: 0.29502881 | AM32: 0.22468693 | AN32: 0.22949943 | AO32: 0.25078483 | AP32: 0.23606644 | AQ32: 0.2261533 | AR32: 0.24319831 | AS32: 0.29458195 | AT32: 0.2056981 | AU32: 0.27291117 | AV32: 0.22309519 | AW32: 0.29829553 | AX32: 0.26271875 | AY32: 0.15912434 | AZ32: 0.27064532 | BA32: 0.30751158 | BB32: 0.24955115 | BC32: 0.21513512 | BD32: 0.28108751 | BE32: 0.25422622 | BF32: 0.23403898 | BG32: 0.26568994 | BH32: 0.23420679 | BI32: 0.26606428 | BJ32: 0.19343122 | BK32: 0.2928291 | BL32: 0.24920021 | BM32: 0.26453947 | BN32: 0.16974392 | BO32: 0.27170423 | BP32: 0.21143753 | BQ32: 0.34711432 | BR32: 0.2091458 | BS32: 0.28040037 | BT32: 0.2211524 | BU32: 0.28930142 | BV32: 0.19411389 | BW32: 0.18991394 | BX32: 0.21641069 | BY32: 0.39956148 | BZ32: 0.25 | CA32: 0.25 | CB32: 0.25 | CC32: 0.25 | CD32: 0.25 | CE32: 0.25 | CF32: 0.25 | CG32: 0.25 | CH32: 0.25 | CI32: 0.25 | CJ32: 0.25 | CK32: 0.25 | CL32: 0.25 | CM32: 0.25 | CN32: 0.25 | CO32: 0.25 | CP32: 0.25 | CQ32: 0.25 | CR32: 0.25 | CS32: 0.25 | CT32: 0.25 | CU32: 0.25 | CV32: 0.25 | CW32: 0.25
B34: 200823 | C34: 판매비 | D34: Sales Expenses | J34: 0 | K34: 0 | L34: 0 | M34: 0 | N34: 0 | O34: 0 | P34: 0 | Q34: 0 | R34: 0 | S34: 0 | T34: 0 | U34: 0 | V34: 14.207588 | W34: 2.497412 | X34: 9.439 | Y34: 10.644 | Z34: 8.039 | AA34: 17.1 | AB34: 40.105 | AC34: 30.622 | AD34: 8.509 | AE34: 8.24 | AF34: 8.389 | AG34: 10.285 | AH34: 13.025 | AI34: 46.538 | AJ34: 10.007 | AK34: 14.619 | AL34: 11.673 | AM34: 11.16 | AN34: 14.56 | AO34: 52.567 | AP34: 15.222 | AQ34: 51.491 | AR34: 15.434 | AS34: 39.823 | AT34: 17.304 | AU34: 41.771 | AV34: 12.683 | AW34: 48.141 | AX34: 17.91 | AY34: 20.882 | AZ34: 35.898 | BA34: 58.255 | BB34: 8.008 | BC34: 16.128 | BD34: 11.38 | BE34: 92.933 | BF34: 70.873 | BG34: -52.867 | BH34: 31.726 | BI34: 11.913 | BJ34: 7.39 | BK34: 35.676 | BL34: 17.737 | BM34: 166.379 | BN34: 14.247 | BO34: 21.516 | BP34: -13.871 | BQ34: 69.038 | BR34: 10.834 | BS34: -50.637 | BT34: 84.155 | BU34: 21.705 | BV34: 19.698 | BW34: 20.4 | BX34: 22.222 | BY34: 37.929 | BZ34: 27.613928 | CA34: 27.613928 | CB34: 27.613928 | CC34: 27.613928 | CD34: 30.425401 | CE34: 30.425401 | CF34: 30.425401 | CG34: 30.425401 | CH34: 33.52312 | CI34: 33.52312 | CJ34: 33.52312 | CK34: 33.52312 | CL34: 36.936229 | CM34: 36.936229 | CN34: 36.936229 | CO34: 36.936229 | CP34: 40.696839 | CQ34: 40.696839 | CR34: 40.696839 | CS34: 40.696839 | CT34: 44.84033 | CU34: 44.84033 | CV34: 44.84033 | CW34: 44.84033 | DA34: 200823 | DB34: 판매비 | DC34: 57.794431 | DD34: 75.636948 | DE34: 78.384366 | DF34: 36.788 | DG34: 95.866 | DH34: 35.423 | DI34: 84.189 | DJ34: 89.96 | DK34: 121.97 | DL34: 119.899 | DM34: 132.945 | DN34: 128.449
C35: (분기배분, manual) | D35: (% growth) | J35: 0 | K35: 0 | L35: 0 | M35: 0 | N35: 0 | O35: 0 | P35: 0 | Q35: 0 | R35: 0 | S35: 0 | T35: 0 | U35: 0 | V35: 0.3862017 | W35: 0.067886593 | X35: 0.25657823 | Y35: 0.28933348 | Z35: 0.083856633 | AA35: 0.17837398 | AB35: 0.41834436 | AC35: 0.31942503 | AD35: 0.24021116 | AE35: 0.23261723 | AF35: 0.23682353 | AG35: 0.29034808 | AH35: 0.15471142 | AI35: 0.55278005 | AJ35: 0.11886351 | AK35: 0.17364501 | AL35: 0.12975767 | AM35: 0.12405514 | AN35: 0.16184971 | AO35: 0.58433748 | AP35: 0.12480118 | AQ35: 0.42216119 | AR35: 0.12653931 | AS35: 0.32649832 | AT35: 0.14432147 | AU35: 0.34838489 | AV35: 0.1057807 | AW35: 0.40151294 | AX35: 0.13471736 | AY35: 0.15707247 | AZ35: 0.27002144 | BA35: 0.43818872 | BB35: 0.06234381 | BC35: 0.12555956 | BD35: 0.088595474 | BE35: 0.72350116 | BF35: 1.1496958 | BG35: -0.85760402 | BH35: 0.5146565 | BI35: 0.19325168 | BJ35: 0.032528986 | BK35: 0.15703709 | BL35: 0.078073967 | BM35: 0.73235996 | BN35: 0.15668096 | BO35: 0.23662158 | BP35: -0.15254591 | BQ35: 0.75924337 | BR35: 0.16400987 | BS35: -0.76656524 | BT35: 1.2739755 | BU35: 0.32857986 | BV35: 0.19649074 | BW35: 0.2034933 | BX35: 0.22166805 | BY35: 0.37834791 | BZ35: 0.25 | CA35: 0.25 | CB35: 0.25 | CC35: 0.25 | CD35: 0.25 | CE35: 0.25 | CF35: 0.25 | CG35: 0.25 | CH35: 0.25 | CI35: 0.25 | CJ35: 0.25 | CK35: 0.25 | CL35: 0.25 | CM35: 0.25 | CN35: 0.25 | CO35: 0.25 | CP35: 0.25 | CQ35: 0.25 | CR35: 0.25 | CS35: 0.25 | CT35: 0.25 | CU35: 0.25 | CV35: 0.25 | CW35: 0.25
B37: 201130 | C37: 연구개발비 | D37: Research & Development | J37: 0 | K37: 0 | L37: 0 | M37: 0 | N37: 0 | O37: 0 | P37: 0 | Q37: 0 | R37: 0 | S37: 0 | T37: 0 | U37: 0 | V37: 14.4 | W37: 29.097 | X37: 21.078 | Y37: 28.893 | Z37: 14.606 | AA37: 18.132 | AB37: 16.251 | AC37: 24.885 | AD37: 11.316 | AE37: 15.896 | AF37: 16.166 | AG37: 18.681 | AH37: 10.734 | AI37: 17.662 | AJ37: 10.971 | AK37: 21.016 | AL37: 12.784 | AM37: 16.254 | AN37: 10.806 | AO37: 23.628 | AP37: 17.159 | AQ37: 28.355 | AR37: 26.398 | AS37: 15.708 | AT37: 28.314 | AU37: 15.344 | AV37: 9.765 | AW37: 32.511 | AX37: 27.395 | AY37: 23.018 | AZ37: 23.33 | BA37: 36.206 | BB37: 29.86 | BC37: 30.287 | BD37: 37.309 | BE37: 53.976 | BF37: 49.868 | BG37: 41.049 | BH37: 44.762 | BI37: 41.848 | BJ37: 53.242 | BK37: 58.244 | BL37: 43.723 | BM37: 34.816 | BN37: 42.902 | BO37: 48.475 | BP37: 41.763 | BQ37: 45.472 | BR37: 45.21 | BS37: 22.375 | BT37: 29.217 | BU37: 41.985 | BV37: 27.414 | BW37: 36.468 | BX37: 38.865 | BY37: 52.176 | BZ37: 42.674067 | CA37: 42.674067 | CB37: 42.674067 | CC37: 42.674067 | CD37: 47.018866 | CE37: 47.018866 | CF37: 47.018866 | CG37: 47.018866 | CH37: 51.806026 | CI37: 51.806026 | CJ37: 51.806026 | CK37: 51.806026 | CL37: 57.080583 | CM37: 57.080583 | CN37: 57.080583 | CO37: 57.080583 | CP37: 62.892162 | CQ37: 62.892162 | CR37: 62.892162 | CS37: 62.892162 | CT37: 69.295438 | CU37: 69.295438 | CV37: 69.295438 | CW37: 69.295438 | DA37: 201130 | DB37: 연구개발비 | DC37: 50.786809 | DD37: 68.254526 | DE37: 190.47143 | DF37: 93.468 | DG37: 73.874 | DH37: 62.059 | DI37: 60.383 | DJ37: 63.472 | DK37: 87.62 | DL37: 85.934 | DM37: 109.949 | DN37: 151.432
C38: (분기배분, manual) | D38: (% growth) | J38: 0 | K38: 0 | L38: 0 | M38: 0 | N38: 0 | O38: 0 | P38: 0 | Q38: 0 | R38: 0 | S38: 0 | T38: 0 | U38: 0 | V38: 0.15406342 | W38: 0.3113044 | X38: 0.22551034 | Y38: 0.30912184 | Z38: 0.19771503 | AA38: 0.24544495 | AB38: 0.21998267 | AC38: 0.33685735 | AD38: 0.18234261 | AE38: 0.25614335 | AF38: 0.26049405 | AG38: 0.30102 | AH38: 0.17776527 | AI38: 0.29249954 | AJ38: 0.18169021 | AK38: 0.34804498 | AL38: 0.20141165 | AM38: 0.25608142 | AN38: 0.1702483 | AO38: 0.37225863 | AP38: 0.19583428 | AQ38: 0.32361333 | AR38: 0.30127825 | AS38: 0.17927414 | AT38: 0.32948542 | AU38: 0.17855564 | AV38: 0.11363372 | AW38: 0.37832523 | AX38: 0.24916097 | AY38: 0.20935161 | AZ38: 0.21218929 | BA38: 0.32929813 | BB38: 0.19718421 | BC38: 0.20000396 | BD38: 0.24637461 | BE38: 0.35643721 | BF38: 0.28090375 | BG38: 0.2312268 | BH38: 0.25214193 | BI38: 0.23572752 | BJ38: 0.28018419 | BK38: 0.30650704 | BL38: 0.23009078 | BM38: 0.183218 | BN38: 0.24019663 | BO38: 0.27139834 | BP38: 0.23381968 | BQ38: 0.25458536 | BR38: 0.32575097 | BS38: 0.16121827 | BT38: 0.21051684 | BU38: 0.30251392 | BV38: 0.17695242 | BW38: 0.23539436 | BX38: 0.25086656 | BY38: 0.33678666 | BZ38: 0.25 | CA38: 0.25 | CB38: 0.25 | CC38: 0.25 | CD38: 0.25 | CE38: 0.25 | CF38: 0.25 | CG38: 0.25 | CH38: 0.25 | CI38: 0.25 | CJ38: 0.25 | CK38: 0.25 | CL38: 0.25 | CM38: 0.25 | CN38: 0.25 | CO38: 0.25 | CP38: 0.25 | CQ38: 0.25 | CR38: 0.25 | CS38: 0.25 | CT38: 0.25 | CU38: 0.25 | CV38: 0.25 | CW38: 0.25
B40: 201160 | C40: 광고선전비 | D40: Advertising Expenses | J40: 0 | K40: 0 | L40: 0 | M40: 0 | N40: 0 | O40: 0 | P40: 0 | Q40: 0 | R40: 0 | S40: 0 | T40: 0 | U40: 0 | V40: 1.856 | W40: 4.844 | X40: 2.622 | Y40: 2.078 | Z40: 1.72 | AA40: 2.024 | AB40: 4.599 | AC40: 3.163 | AD40: 2.155 | AE40: 2.654 | AF40: 1.444 | AG40: 3.771 | AH40: 1.983 | AI40: 3.887 | AJ40: 2.903 | AK40: 5.028 | AL40: 2.135 | AM40: 2.922 | AN40: 2.696 | AO40: 6.702 | AP40: 2.189 | AQ40: 2.838 | AR40: 3.335 | AS40: 6.451 | AT40: 2.033 | AU40: 1.634 | AV40: 0.872 | AW40: 6.053 | AX40: 1.84 | AY40: -0.703 | AZ40: 1.133 | BA40: -2.27 | BB40: 1.616 | BC40: 3.027 | BD40: -4.643 | BE40: 0 | BF40: 0 | BG40: 0 | BH40: 0 | BI40: 0 | BJ40: 0 | BK40: 0 | BL40: 0 | BM40: 0 | BN40: 0 | BO40: 0 | BP40: 0 | BQ40: 0 | BR40: 0 | BS40: 0 | BT40: 0 | BU40: 0 | BV40: 0 | BW40: 0 | BX40: 0 | BY40: 0 | BZ40: 0 | CA40: 0 | CB40: 0 | CC40: 0 | CD40: 0 | CE40: 0 | CF40: 0 | CG40: 0 | CH40: 0 | CI40: 0 | CJ40: 0 | CK40: 0 | CL40: 0 | CM40: 0 | CN40: 0 | CO40: 0 | CP40: 0 | CQ40: 0 | CR40: 0 | CS40: 0 | CT40: 0 | CU40: 0 | CV40: 0 | CW40: 0 | DA40: 201160 | DB40: 광고선전비 | DC40: 22.429208 | DD40: 13.709182 | DE40: 14.352038 | DF40: 11.4 | DG40: 11.506 | DH40: 10.024 | DI40: 13.801 | DJ40: 14.455 | DK40: 14.813 | DL40: 10.592 | DM40: 0 | DN40: 0
C41: (분기배분, manual) | D41: (% growth) | J41: 0 | K41: 0 | L41: 0 | M41: 0 | N41: 0 | O41: 0 | P41: 0 | Q41: 0 | R41: 0 | S41: 0 | T41: 0 | U41: 0 | V41: 0.16280702 | W41: 0.42491228 | X41: 0.23 | Y41: 0.1822807 | Z41: 0.14948722 | AA41: 0.17590822 | AB41: 0.3997045 | AC41: 0.27490005 | AD41: 0.21498404 | AE41: 0.26476457 | AF41: 0.14405427 | AG41: 0.37619713 | AH41: 0.14368524 | AI41: 0.28164626 | AJ41: 0.21034708 | AK41: 0.36432143 | AL41: 0.14769976 | AM41: 0.20214459 | AN41: 0.18650986 | AO41: 0.4636458 | AP41: 0.1477756 | AQ41: 0.19158847 | AR41: 0.22514008 | AS41: 0.43549585 | AT41: 0.19193731 | AU41: 0.15426737 | AV41: 0.082326284 | AW41: 0.57146903 | AX41: 0 | AY41: 0 | AZ41: 0 | BA41: 0 | BB41: 0 | BC41: 0 | BD41: 0 | BE41: 0 | BF41: 0 | BG41: 0 | BH41: 0 | BI41: 0 | BJ41: 0 | BK41: 0 | BL41: 0 | BM41: 0 | BN41: 0 | BO41: 0 | BP41: 0 | BQ41: 0 | BR41: 0 | BS41: 0 | BT41: 0 | BU41: 0 | BV41: 0 | BW41: 0 | BX41: 0 | BY41: 0 | BZ41: 0.25 | CA41: 0.25 | CB41: 0.25 | CC41: 0.25 | CD41: 0.25 | CE41: 0.25 | CF41: 0.25 | CG41: 0.25 | CH41: 0.25 | CI41: 0.25 | CJ41: 0.25 | CK41: 0.25 | CL41: 0.25 | CM41: 0.25 | CN41: 0.25 | CO41: 0.25 | CP41: 0.25 | CQ41: 0.25 | CR41: 0.25 | CS41: 0.25 | CT41: 0.25 | CU41: 0.25 | CV41: 0.25 | CW41: 0.25
B43: 201080 | C43: 유형자산 감가상각비 | D43: Depreciation (SG&A) | J43: 0 | K43: 0 | L43: 0 | M43: 0 | N43: 0 | O43: 0 | P43: 0 | Q43: 0 | R43: 0 | S43: 0 | T43: 0 | U43: 0 | V43: 1.714 | W43: 1.787 | X43: 1.728 | Y43: 1.864 | Z43: 1.963 | AA43: 1.998 | AB43: 2.037 | AC43: 2.304 | AD43: 1.568 | AE43: 2.839 | AF43: 2.046 | AG43: 2.365 | AH43: 2.295 | AI43: 3.896 | AJ43: 0.461 | AK43: 2.439 | AL43: 2.462 | AM43: 2.503 | AN43: 2.547 | AO43: 2.582 | AP43: 2.725 | AQ43: 2.709 | AR43: 2.845 | AS43: 2.99 | AT43: 2.95 | AU43: 2.967 | AV43: 2.949 | AW43: 2.986 | AX43: 2.91 | AY43: 2.639 | AZ43: 3.093 | BA43: 3.052 | BB43: 2.901 | BC43: 2.792 | BD43: 2.791 | BE43: 9.323 | BF43: 6.727 | BG43: 6.535 | BH43: 6.455 | BI43: 7.863 | BJ43: 8.746 | BK43: 8.669 | BL43: 8.27 | BM43: 8.693 | BN43: 8.559 | BO43: 8.49 | BP43: 8.818 | BQ43: 8.992 | BR43: 9.266 | BS43: 9.543 | BT43: 9.632 | BU43: 9.308 | BV43: 10.654 | BW43: 16.019 | BX43: 13.608 | BY43: 13.718 | BZ43: 14.515556 | CA43: 14.515556 | CB43: 14.515556 | CC43: 14.515556 | CD43: 9.7822836 | CE43: 9.7822836 | CF43: 9.7822836 | CG43: 9.7822836 | CH43: 6.5924495 | CI43: 6.5924495 | CJ43: 6.5924495 | CK43: 6.5924495 | CL43: 4.4427654 | CM43: 4.4427654 | CN43: 4.4427654 | CO43: 4.4427654 | CP43: 2.9940561 | CQ43: 2.9940561 | CR43: 2.9940561 | CS43: 2.9940561 | CT43: 2.017746 | CU43: 2.017746 | CV43: 2.017746 | CW43: 2.017746 | DA43: 201080 | DB43: 유형자산 감가상각비 | DC43: 4.847228 | DD43: 4.468217 | DE43: 6.656417 | DF43: 7.093 | DG43: 8.302 | DH43: 8.818 | DI43: 9.091 | DJ43: 10.094 | DK43: 11.269 | DL43: 11.852 | DM43: 11.694 | DN43: 17.807
C44: (분기배분, manual) | D44: (% growth) | J44: 0 | K44: 0 | L44: 0 | M44: 0 | N44: 0 | O44: 0 | P44: 0 | Q44: 0 | R44: 0 | S44: 0 | T44: 0 | U44: 0 | V44: 0.24164669 | W44: 0.25193853 | X44: 0.24362047 | Y44: 0.2627943 | Z44: 0.23644905 | AA44: 0.2406649 | AB44: 0.24536256 | AC44: 0.27752349 | AD44: 0.1778181 | AE44: 0.32195509 | AF44: 0.2320254 | AG44: 0.26820141 | AH44: 0.25244748 | AI44: 0.42855571 | AJ44: 0.050709493 | AK44: 0.26828732 | AL44: 0.24390727 | AM44: 0.24796909 | AN44: 0.25232812 | AO44: 0.25579552 | AP44: 0.24181383 | AQ44: 0.240394 | AR44: 0.25246251 | AS44: 0.26532967 | AT44: 0.24890314 | AU44: 0.2503375 | AV44: 0.24881876 | AW44: 0.2519406 | AX44: 0.24884556 | AY44: 0.22567128 | AZ44: 0.26449461 | BA44: 0.26098854 | BB44: 0.16291346 | BC44: 0.15679227 | BD44: 0.15673612 | BE44: 0.52355815 | BF44: 0.24390863 | BG44: 0.23694706 | BH44: 0.23404641 | BI44: 0.2850979 | BJ44: 0.25440689 | BK44: 0.25216708 | BL44: 0.24056082 | BM44: 0.2528652 | BN44: 0.245532 | BO44: 0.2435526 | BP44: 0.25296193 | BQ44: 0.25795347 | BR44: 0.24546346 | BS44: 0.2528014 | BT44: 0.25515908 | BU44: 0.24657607 | BV44: 0.19729995 | BW44: 0.29665364 | BX44: 0.25200467 | BY44: 0.25404174 | BZ44: 0.25 | CA44: 0.25 | CB44: 0.25 | CC44: 0.25 | CD44: 0.25 | CE44: 0.25 | CF44: 0.25 | CG44: 0.25 | CH44: 0.25 | CI44: 0.25 | CJ44: 0.25 | CK44: 0.25 | CL44: 0.25 | CM44: 0.25 | CN44: 0.25 | CO44: 0.25 | CP44: 0.25 | CQ44: 0.25 | CR44: 0.25 | CS44: 0.25 | CT44: 0.25 | CU44: 0.25 | CV44: 0.25 | CW44: 0.25
B46: 201090+201100 | C46: 무형자산상각비 | D46: Amortization (SG&A) | J46: 0 | K46: 0 | L46: 0 | M46: 0 | N46: 0 | O46: 0 | P46: 0 | Q46: 0 | R46: 0 | S46: 0 | T46: 0 | U46: 0 | V46: 0.128 | W46: 0.1 | X46: 0.102 | Y46: 0.118 | Z46: 0 | AA46: 0.444 | AB46: 0.239 | AC46: 0.273 | AD46: 1.068 | AE46: -0.293 | AF46: 0.27 | AG46: 0.368 | AH46: 0.409 | AI46: 10.817 | AJ46: 14.598 | AK46: 12.827 | AL46: 12.73 | AM46: 12.968 | AN46: 12.997 | AO46: 30.885 | AP46: 12.693 | AQ46: 11.964 | AR46: 13.117 | AS46: 13.76 | AT46: 13.105 | AU46: 13.921 | AV46: 14.171 | AW46: 14.917 | AX46: 15.741 | AY46: 11.835 | AZ46: 12.79 | BA46: -40.366 | BB46: 10.83 | BC46: 2.905 | BD46: 1.167 | BE46: 1.26 | BF46: 1.416 | BG46: 1.348 | BH46: 1.287 | BI46: 1.358 | BJ46: 1.401 | BK46: 1.446 | BL46: 1.684 | BM46: 2.066 | BN46: 1.075 | BO46: 0.891 | BP46: 0.874 | BQ46: 0.967 | BR46: 1.161 | BS46: 1.248 | BT46: 1.239 | BU46: 1.365 | BV46: 1.523 | BW46: 1.51 | BX46: 1.753 | BY46: 1.846 | BZ46: 2.0515193 | CA46: 2.0515193 | CB46: 2.0515193 | CC46: 2.0515193 | CD46: 1.8572704 | CE46: 1.8572704 | CF46: 1.8572704 | CG46: 1.8572704 | CH46: 1.6814141 | CI46: 1.6814141 | CJ46: 1.6814141 | CK46: 1.6814141 | CL46: 1.5222088 | CM46: 1.5222088 | CN46: 1.5222088 | CO46: 1.5222088 | CP46: 1.3780779 | CQ46: 1.3780779 | CR46: 1.3780779 | CS46: 1.3780779 | CT46: 1.2475941 | CU46: 1.2475941 | CV46: 1.2475941 | CW46: 1.2475941 | DA46: 201090+201100 | DB46: 무형자산상각비 | DC46: 0.353596 | DD46: 0.398002 | DE46: 7.033087 | DF46: 0.448 | DG46: 0.956 | DH46: 1.413 | DI46: 38.651 | DJ46: 69.58 | DK46: 51.534 | DL46: 56.114 | DM46: 0 | DN46: 16.162
C47: (분기배분, manual) | D47: (% growth) | J47: 0 | K47: 0 | L47: 0 | M47: 0 | N47: 0 | O47: 0 | P47: 0 | Q47: 0 | R47: 0 | S47: 0 | T47: 0 | U47: 0 | V47: 0.28571429 | W47: 0.22321429 | X47: 0.22767857 | Y47: 0.26339286 | Z47: 0 | AA47: 0.46443515 | AB47: 0.25 | AC47: 0.28556485 | AD47: 0.75583864 | AE47: -0.20736023 | AF47: 0.1910828 | AG47: 0.26043878 | AH47: 0.010581874 | AI47: 0.27986339 | AJ47: 0.37768751 | AK47: 0.33186722 | AL47: 0.18295487 | AM47: 0.1863754 | AN47: 0.18679218 | AO47: 0.44387755 | AP47: 0.24630341 | AQ47: 0.23215741 | AR47: 0.25453099 | AS47: 0.26700819 | AT47: 0.23354243 | AU47: 0.24808426 | AV47: 0.25253947 | AW47: 0.26583384 | AX47: 0 | AY47: 0 | AZ47: 0 | BA47: 0 | BB47: 0.67009034 | BC47: 0.17974261 | BD47: 0.07220641 | BE47: 0.077960648 | BF47: 0.26178591 | BG47: 0.24921427 | BH47: 0.23793677 | BI47: 0.25106304 | BJ47: 0.21236926 | BK47: 0.21919054 | BL47: 0.25526755 | BM47: 0.31317265 | BN47: 0.28237457 | BO47: 0.23404255 | BP47: 0.22957709 | BQ47: 0.25400578 | BR47: 0.23159785 | BS47: 0.24895272 | BT47: 0.24715739 | BU47: 0.27229204 | BV47: 0.22964415 | BW47: 0.22768396 | BX47: 0.26432449 | BY47: 0.27834741 | BZ47: 0.25 | CA47: 0.25 | CB47: 0.25 | CC47: 0.25 | CD47: 0.25 | CE47: 0.25 | CF47: 0.25 | CG47: 0.25 | CH47: 0.25 | CI47: 0.25 | CJ47: 0.25 | CK47: 0.25 | CL47: 0.25 | CM47: 0.25 | CN47: 0.25 | CO47: 0.25 | CP47: 0.25 | CQ47: 0.25 | CR47: 0.25 | CS47: 0.25 | CT47: 0.25 | CU47: 0.25 | CV47: 0.25 | CW47: 0.25
B50: 203590 | C50: 기타영업수익 | D50: Other Operating Income | J50: 0 | K50: 0 | L50: 0 | M50: 0 | N50: 0 | O50: 0 | P50: 0 | Q50: 0 | R50: 0 | S50: 0 | T50: 0 | U50: 0 | V50: 36.671314 | W50: 45.292914 | X50: 54.5007 | Y50: 66.014343 | Z50: 30.698 | AA50: 49.59 | AB50: 20.405 | AC50: 0 | AD50: 0 | AE50: 0 | AF50: 0 | AG50: 0 | AH50: 0 | AI50: 0 | AJ50: 0 | AK50: 0 | AL50: 0 | AM50: 0 | AN50: 0 | AO50: 0 | AP50: 0 | AQ50: 0 | AR50: 0 | AS50: 0 | AT50: 0 | AU50: 0 | AV50: 0 | AW50: 0 | AX50: 0 | AY50: 0 | AZ50: 0 | BA50: 0 | BB50: 0 | BC50: 0 | BD50: 0 | BE50: 0 | BF50: 0 | BG50: 0 | BH50: 0 | BI50: 0 | BJ50: 0 | BK50: 0 | BL50: 0 | BM50: 0 | BN50: 0 | BO50: 0 | BP50: 0 | BQ50: 0 | BR50: 0 | BS50: 0 | BT50: 0 | BU50: 0 | BV50: 0 | BW50: 0 | BX50: 0 | BY50: 0 | BZ50: 0 | CA50: 0 | CB50: 0 | CC50: 0 | CD50: 0 | CE50: 0 | CF50: 0 | CG50: 0 | CH50: 0 | CI50: 0 | CJ50: 0 | CK50: 0 | CL50: 0 | CM50: 0 | CN50: 0 | CO50: 0 | CP50: 0 | CQ50: 0 | CR50: 0 | CS50: 0 | CT50: 0 | CU50: 0 | CV50: 0 | CW50: 0 | DA50: 203590 | DB50: 기타영업수익 | DC50: 0 | DD50: 0 | DE50: 0 | DF50: 202.47927 | DG50: 0 | DH50: 0 | DI50: 0 | DJ50: 0 | DK50: 0 | DL50: 0 | DM50: 0 | DN50: 0
B52: 203600 | C52: 이자수익 | D52: Interest Income | J52: 0 | K52: 0 | L52: 0 | M52: 0 | N52: 0 | O52: 0 | P52: 0 | Q52: 0 | R52: 0 | S52: 0 | T52: 0 | U52: 0 | V52: 0 | W52: 0 | X52: 0 | Y52: 0 | Z52: 0 | AA52: 0 | AB52: 0 | AC52: 0 | AD52: 0 | AE52: 0 | AF52: 0 | AG52: 0 | AH52: 0 | AI52: 0 | AJ52: 0 | AK52: 0 | AL52: 0 | AM52: 0 | AN52: 0 | AO52: 0 | AP52: 0 | AQ52: 0 | AR52: 0 | AS52: 0 | AT52: 0 | AU52: 0 | AV52: 0 | AW52: 0 | AX52: 0 | AY52: 0 | AZ52: 0 | BA52: 0 | BB52: 0 | BC52: 0 | BD52: 0 | BE52: 0 | BF52: 0 | BG52: 0 | BH52: 0 | BI52: 0 | BJ52: 0 | BK52: 0 | BL52: 0 | BM52: 0 | BN52: 0 | BO52: 0 | BP52: 0 | BQ52: 0 | BR52: 0 | BS52: 0 | BT52: 0 | BU52: 0 | BV52: 0 | BW52: 0 | BX52: 0 | BY52: 0 | BZ52: 0 | CA52: 0 | CB52: 0 | CC52: 0 | CD52: 0 | CE52: 0 | CF52: 0 | CG52: 0 | CH52: 0 | CI52: 0 | CJ52: 0 | CK52: 0 | CL52: 0 | CM52: 0 | CN52: 0 | CO52: 0 | CP52: 0 | CQ52: 0 | CR52: 0 | CS52: 0 | CT52: 0 | CU52: 0 | CV52: 0 | CW52: 0 | DA52: 203600 | DB52: 이자수익 | DC52: 0 | DD52: 0 | DE52: 0 | DF52: 0 | DG52: 0 | DH52: 0 | DI52: 0 | DJ52: 0 | DK52: 0 | DL52: 0 | DM52: 0 | DN52: 0
C53: (분기배분, manual) | D53: (Q Distribution) | J53: 0 | K53: 0 | L53: 0 | M53: 0 | N53: 0 | O53: 0 | P53: 0 | Q53: 0 | R53: 0 | S53: 0 | T53: 0 | U53: 0 | V53: 0 | W53: 0 | X53: 0 | Y53: 0 | Z53: 0 | AA53: 0 | AB53: 0 | AC53: 0 | AD53: 0 | AE53: 0 | AF53: 0 | AG53: 0 | AH53: 0 | AI53: 0 | AJ53: 0 | AK53: 0 | AL53: 0 | AM53: 0 | AN53: 0 | AO53: 0 | AP53: 0 | AQ53: 0 | AR53: 0 | AS53: 0 | AT53: 0 | AU53: 0 | AV53: 0 | AW53: 0 | AX53: 0 | AY53: 0 | AZ53: 0 | BA53: 0 | BB53: 0 | BC53: 0 | BD53: 0 | BE53: 0 | BF53: 0 | BG53: 0 | BH53: 0 | BI53: 0 | BJ53: 0 | BK53: 0 | BL53: 0 | BM53: 0 | BN53: 0 | BO53: 0 | BP53: 0 | BQ53: 0 | BR53: 0 | BS53: 0 | BT53: 0 | BU53: 0 | BV53: 0 | BW53: 0 | BX53: 0 | BY53: 0 | BZ53: 0.25 | CA53: 0.25 | CB53: 0.25 | CC53: 0.25 | CD53: 0.25 | CE53: 0.25 | CF53: 0.25 | CG53: 0.25 | CH53: 0.25 | CI53: 0.25 | CJ53: 0.25 | CK53: 0.25 | CL53: 0.25 | CM53: 0.25 | CN53: 0.25 | CO53: 0.25 | CP53: 0.25 | CQ53: 0.25 | CR53: 0.25 | CS53: 0.25 | CT53: 0.25 | CU53: 0.25 | CV53: 0.25 | CW53: 0.25
B54: 203620 | C54: 외환거래이익 | D54: Dividend Income | J54: 0 | K54: 0 | L54: 0 | M54: 0 | N54: 0 | O54: 0 | P54: 0 | Q54: 0 | R54: 0 | S54: 0 | T54: 0 | U54: 0 | V54: 28.702 | W54: 9.799 | X54: 30.718 | Y54: 21.378 | Z54: 15.163 | AA54: 12.833 | AB54: 12.324 | AC54: 0 | AD54: 0 | AE54: 0 | AF54: 0 | AG54: 0 | AH54: 0 | AI54: 0 | AJ54: 0 | AK54: 0 | AL54: 0 | AM54: 0 | AN54: 0 | AO54: 0 | AP54: 0 | AQ54: 0 | AR54: 0 | AS54: 0 | AT54: 0 | AU54: 0 | AV54: 0 | AW54: 0 | AX54: 0 | AY54: 0 | AZ54: 0 | BA54: 0 | BB54: 0 | BC54: 0 | BD54: 0 | BE54: 0 | BF54: 0 | BG54: 0 | BH54: 0 | BI54: 0 | BJ54: 0 | BK54: 0 | BL54: 0 | BM54: 0 | BN54: 0 | BO54: 0 | BP54: 0 | BQ54: 0 | BR54: 0 | BS54: 0 | BT54: 0 | BU54: 0 | BV54: 0 | BW54: 0 | BX54: 0 | BY54: 0 | BZ54: 0 | CA54: 0 | CB54: 0 | CC54: 0 | CD54: 0 | CE54: 0 | CF54: 0 | CG54: 0 | CH54: 0 | CI54: 0 | CJ54: 0 | CK54: 0 | CL54: 0 | CM54: 0 | CN54: 0 | CO54: 0 | CP54: 0 | CQ54: 0 | CR54: 0 | CS54: 0 | CT54: 0 | CU54: 0 | CV54: 0 | CW54: 0 | DA54: 203620 | DB54: 외환거래이익 | DC54: 0 | DD54: 0 | DE54: 0 | DF54: 90.597 | DG54: 0 | DH54: 0 | DI54: 0 | DJ54: 0 | DK54: 0 | DL54: 0 | DM54: 0 | DN54: 0
C55: (분기배분, manual) | D55: (Q Distribution) | J55: 0 | K55: 0 | L55: 0 | M55: 0 | N55: 0 | O55: 0 | P55: 0 | Q55: 0 | R55: 0 | S55: 0 | T55: 0 | U55: 0 | V55: 0.31680961 | W55: 0.10816031 | X55: 0.339062 | Y55: 0.23596808 | Z55: 0 | AA55: 0 | AB55: 0 | AC55: 0 | AD55: 0 | AE55: 0 | AF55: 0 | AG55: 0 | AH55: 0 | AI55: 0 | AJ55: 0 | AK55: 0 | AL55: 0 | AM55: 0 | AN55: 0 | AO55: 0 | AP55: 0 | AQ55: 0 | AR55: 0 | AS55: 0 | AT55: 0 | AU55: 0 | AV55: 0 | AW55: 0 | AX55: 0 | AY55: 0 | AZ55: 0 | BA55: 0 | BB55: 0 | BC55: 0 | BD55: 0 | BE55: 0 | BF55: 0 | BG55: 0 | BH55: 0 | BI55: 0 | BJ55: 0 | BK55: 0 | BL55: 0 | BM55: 0 | BN55: 0 | BO55: 0 | BP55: 0 | BQ55: 0 | BR55: 0 | BS55: 0 | BT55: 0 | BU55: 0 | BV55: 0 | BW55: 0 | BX55: 0 | BY55: 0 | BZ55: 0.25 | CA55: 0.25 | CB55: 0.25 | CC55: 0.25 | CD55: 0.25 | CE55: 0.25 | CF55: 0.25 | CG55: 0.25 | CH55: 0.25 | CI55: 0.25 | CJ55: 0.25 | CK55: 0.25 | CL55: 0.25 | CM55: 0.25 | CN55: 0.25 | CO55: 0.25 | CP55: 0.25 | CQ55: 0.25 | CR55: 0.25 | CS55: 0.25 | CT55: 0.25 | CU55: 0.25 | CV55: 0.25 | CW55: 0.25
B56: 203610 | C56: 배당금수익 | D56: Gains on Disposal of Assets | J56: 0 | K56: 0 | L56: 0 | M56: 0 | N56: 0 | O56: 0 | P56: 0 | Q56: 0 | R56: 0 | S56: 0 | T56: 0 | U56: 0 | V56: 0 | W56: 0 | X56: 0 | Y56: 0 | Z56: 0 | AA56: 0 | AB56: 0 | AC56: 0 | AD56: 0 | AE56: 0 | AF56: 0 | AG56: 0 | AH56: 0 | AI56: 0 | AJ56: 0 | AK56: 0 | AL56: 0 | AM56: 0 | AN56: 0 | AO56: 0 | AP56: 0 | AQ56: 0 | AR56: 0 | AS56: 0 | AT56: 0 | AU56: 0 | AV56: 0 | AW56: 0 | AX56: 0 | AY56: 0 | AZ56: 0 | BA56: 0 | BB56: 0 | BC56: 0 | BD56: 0 | BE56: 0 | BF56: 0 | BG56: 0 | BH56: 0 | BI56: 0 | BJ56: 0 | BK56: 0 | BL56: 0 | BM56: 0 | BN56: 0 | BO56: 0 | BP56: 0 | BQ56: 0 | BR56: 0 | BS56: 0 | BT56: 0 | BU56: 0 | BV56: 0 | BW56: 0 | BX56: 0 | BY56: 0 | BZ56: 0 | CA56: 0 | CB56: 0 | CC56: 0 | CD56: 0 | CE56: 0 | CF56: 0 | CG56: 0 | CH56: 0 | CI56: 0 | CJ56: 0 | CK56: 0 | CL56: 0 | CM56: 0 | CN56: 0 | CO56: 0 | CP56: 0 | CQ56: 0 | CR56: 0 | CS56: 0 | CT56: 0 | CU56: 0 | CV56: 0 | CW56: 0 | DA56: 203610 | DB56: 배당금수익 | DC56: 0 | DD56: 0 | DE56: 0 | DF56: 0 | DG56: 0 | DH56: 0 | DI56: 0 | DJ56: 0 | DK56: 0 | DL56: 0 | DM56: 0 | DN56: 0
C57: (분기배분, manual) | D57: (Q Distribution) | J57: 0 | K57: 0 | L57: 0 | M57: 0 | N57: 0 | O57: 0 | P57: 0 | Q57: 0 | R57: 0 | S57: 0 | T57: 0 | U57: 0 | V57: 0 | W57: 0 | X57: 0 | Y57: 0 | Z57: 0 | AA57: 0 | AB57: 0 | AC57: 0 | AD57: 0 | AE57: 0 | AF57: 0 | AG57: 0 | AH57: 0 | AI57: 0 | AJ57: 0 | AK57: 0 | AL57: 0 | AM57: 0 | AN57: 0 | AO57: 0 | AP57: 0 | AQ57: 0 | AR57: 0 | AS57: 0 | AT57: 0 | AU57: 0 | AV57: 0 | AW57: 0 | AX57: 0 | AY57: 0 | AZ57: 0 | BA57: 0 | BB57: 0 | BC57: 0 | BD57: 0 | BE57: 0 | BF57: 0 | BG57: 0 | BH57: 0 | BI57: 0 | BJ57: 0 | BK57: 0 | BL57: 0 | BM57: 0 | BN57: 0 | BO57: 0 | BP57: 0 | BQ57: 0 | BR57: 0 | BS57: 0 | BT57: 0 | BU57: 0 | BV57: 0 | BW57: 0 | BX57: 0 | BY57: 0 | BZ57: 0.25 | CA57: 0.25 | CB57: 0.25 | CC57: 0.25 | CD57: 0.25 | CE57: 0.25 | CF57: 0.25 | CG57: 0.25 | CH57: 0.25 | CI57: 0.25 | CJ57: 0.25 | CK57: 0.25 | CL57: 0.25 | CM57: 0.25 | CN57: 0.25 | CO57: 0.25 | CP57: 0.25 | CQ57: 0.25 | CR57: 0.25 | CS57: 0.25 | CT57: 0.25 | CU57: 0.25 | CV57: 0.25 | CW57: 0.25
B58: 203800 | C58: 투자자산평가이익 | D58: Gains on Investment Assets | J58: 0 | K58: 0 | L58: 0 | M58: 0 | N58: 0 | O58: 0 | P58: 0 | Q58: 0 | R58: 0 | S58: 0 | T58: 0 | U58: 0 | V58: 0 | W58: 0 | X58: 0 | Y58: 0 | Z58: 0 | AA58: 0 | AB58: 0 | AC58: 0 | AD58: 0 | AE58: 0 | AF58: 0 | AG58: 0 | AH58: 0 | AI58: 0 | AJ58: 0 | AK58: 0 | AL58: 0 | AM58: 0 | AN58: 0 | AO58: 0 | AP58: 0 | AQ58: 0 | AR58: 0 | AS58: 0 | AT58: 0 | AU58: 0 | AV58: 0 | AW58: 0 | AX58: 0 | AY58: 0 | AZ58: 0 | BA58: 0 | BB58: 0 | BC58: 0 | BD58: 0 | BE58: 0 | BF58: 0 | BG58: 0 | BH58: 0 | BI58: 0 | BJ58: 0 | BK58: 0 | BL58: 0 | BM58: 0 | BN58: 0 | BO58: 0 | BP58: 0 | BQ58: 0 | BR58: 0 | BS58: 0 | BT58: 0 | BU58: 0 | BV58: 0 | BW58: 0 | BX58: 0 | BY58: 0 | BZ58: 0 | CA58: 0 | CB58: 0 | CC58: 0 | CD58: 0 | CE58: 0 | CF58: 0 | CG58: 0 | CH58: 0 | CI58: 0 | CJ58: 0 | CK58: 0 | CL58: 0 | CM58: 0 | CN58: 0 | CO58: 0 | CP58: 0 | CQ58: 0 | CR58: 0 | CS58: 0 | CT58: 0 | CU58: 0 | CV58: 0 | CW58: 0 | DA58: 203800 | DB58: 투자자산평가이익 | DC58: 0 | DD58: 0 | DE58: 0 | DF58: 0 | DG58: 0 | DH58: 0 | DI58: 0 | DJ58: 0 | DK58: 0 | DL58: 0 | DM58: 0 | DN58: 0
C59: (분기배분, manual) | D59: (Q Distribution) | J59: 0 | K59: 0 | L59: 0 | M59: 0 | N59: 0 | O59: 0 | P59: 0 | Q59: 0 | R59: 0 | S59: 0 | T59: 0 | U59: 0 | V59: 0 | W59: 0 | X59: 0 | Y59: 0 | Z59: 0 | AA59: 0 | AB59: 0 | AC59: 0 | AD59: 0 | AE59: 0 | AF59: 0 | AG59: 0 | AH59: 0 | AI59: 0 | AJ59: 0 | AK59: 0 | AL59: 0 | AM59: 0 | AN59: 0 | AO59: 0 | AP59: 0 | AQ59: 0 | AR59: 0 | AS59: 0 | AT59: 0 | AU59: 0 | AV59: 0 | AW59: 0 | AX59: 0 | AY59: 0 | AZ59: 0 | BA59: 0 | BB59: 0 | BC59: 0 | BD59: 0 | BE59: 0 | BF59: 0 | BG59: 0 | BH59: 0 | BI59: 0 | BJ59: 0 | BK59: 0 | BL59: 0 | BM59: 0 | BN59: 0 | BO59: 0 | BP59: 0 | BQ59: 0 | BR59: 0 | BS59: 0 | BT59: 0 | BU59: 0 | BV59: 0 | BW59: 0 | BX59: 0 | BY59: 0 | BZ59: 0.25 | CA59: 0.25 | CB59: 0.25 | CC59: 0.25 | CD59: 0.25 | CE59: 0.25 | CF59: 0.25 | CG59: 0.25 | CH59: 0.25 | CI59: 0.25 | CJ59: 0.25 | CK59: 0.25 | CL59: 0.25 | CM59: 0.25 | CN59: 0.25 | CO59: 0.25 | CP59: 0.25 | CQ59: 0.25 | CR59: 0.25 | CS59: 0.25 | CT59: 0.25 | CU59: 0.25 | CV59: 0.25 | CW59: 0.25
B60: 203591 | C60: 기타 기타수익 | D60: Others | J60: 0 | K60: 0 | L60: 0 | M60: 0 | N60: 0 | O60: 0 | P60: 0 | Q60: 0 | R60: 0 | S60: 0 | T60: 0 | U60: 0 | V60: 7.969314 | W60: 35.493914 | X60: 23.7827 | Y60: 44.636343 | Z60: 15.535 | AA60: 36.757 | AB60: 8.081 | AC60: 0 | AD60: 0 | AE60: 0 | AF60: 0 | AG60: 0 | AH60: 0 | AI60: 0 | AJ60: 0 | AK60: 0 | AL60: 0 | AM60: 0 | AN60: 0 | AO60: 0 | AP60: 0 | AQ60: 0 | AR60: 0 | AS60: 0 | AT60: 0 | AU60: 0 | AV60: 0 | AW60: 0 | AX60: 0 | AY60: 0 | AZ60: 0 | BA60: 0 | BB60: 0 | BC60: 0 | BD60: 0 | BE60: 0 | BF60: 0 | BG60: 0 | BH60: 0 | BI60: 0 | BJ60: 0 | BK60: 0 | BL60: 0 | BM60: 0 | BN60: 0 | BO60: 0 | BP60: 0 | BQ60: 0 | BR60: 0 | BS60: 0 | BT60: 0 | BU60: 0 | BV60: 0 | BW60: 0 | BX60: 0 | BY60: 0 | BZ60: 0 | CA60: 0 | CB60: 0 | CC60: 0 | CD60: 0 | CE60: 0 | CF60: 0 | CG60: 0 | CH60: 0 | CI60: 0 | CJ60: 0 | CK60: 0 | CL60: 0 | CM60: 0 | CN60: 0 | CO60: 0 | CP60: 0 | CQ60: 0 | CR60: 0 | CS60: 0 | CT60: 0 | CU60: 0 | CV60: 0 | CW60: 0 | DA60: 203591 | DB60: 기타 기타수익 | DC60: 0 | DD60: 0 | DE60: 0 | DF60: 111.88227 | DG60: 0 | DH60: 0 | DI60: 0 | DJ60: 0 | DK60: 0 | DL60: 0 | DM60: 0 | DN60: 0
C61: (분기배분, manual) | D61: (Q Distribution) | J61: 0 | K61: 0 | L61: 0 | M61: 0 | N61: 0 | O61: 0 | P61: 0 | Q61: 0 | R61: 0 | S61: 0 | T61: 0 | U61: 0 | V61: 0.071229462 | W61: 0.31724342 | X61: 0.21256898 | Y61: 0.39895814 | Z61: 0 | AA61: 0 | AB61: 0 | AC61: 0 | AD61: 0 | AE61: 0 | AF61: 0 | AG61: 0 | AH61: 0 | AI61: 0 | AJ61: 0 | AK61: 0 | AL61: 0 | AM61: 0 | AN61: 0 | AO61: 0 | AP61: 0 | AQ61: 0 | AR61: 0 | AS61: 0 | AT61: 0 | AU61: 0 | AV61: 0 | AW61: 0 | AX61: 0 | AY61: 0 | AZ61: 0 | BA61: 0 | BB61: 0 | BC61: 0 | BD61: 0 | BE61: 0 | BF61: 0 | BG61: 0 | BH61: 0 | BI61: 0 | BJ61: 0 | BK61: 0 | BL61: 0 | BM61: 0 | BN61: 0 | BO61: 0 | BP61: 0 | BQ61: 0 | BR61: 0 | BS61: 0 | BT61: 0 | BU61: 0 | BV61: 0 | BW61: 0 | BX61: 0 | BY61: 0 | BZ61: 0.25 | CA61: 0.25 | CB61: 0.25 | CC61: 0.25 | CD61: 0.25 | CE61: 0.25 | CF61: 0.25 | CG61: 0.25 | CH61: 0.25 | CI61: 0.25 | CJ61: 0.25 | CK61: 0.25 | CL61: 0.25 | CM61: 0.25 | CN61: 0.25 | CO61: 0.25 | CP61: 0.25 | CQ61: 0.25 | CR61: 0.25 | CS61: 0.25 | CT61: 0.25 | CU61: 0.25 | CV61: 0.25 | CW61: 0.25
B63: 204030 | C63: 기타영업비용 | D63: Other Operating Expenses | J63: 0 | K63: 0 | L63: 0 | M63: 0 | N63: 0 | O63: 0 | P63: 0 | Q63: 0 | R63: 0 | S63: 0 | T63: 0 | U63: 0 | V63: 44.910788 | W63: 47.887893 | X63: 38.480823 | Y63: 52.788991 | Z63: 24.08 | AA63: 40.229 | AB63: 21.301 | AC63: 0 | AD63: 0 | AE63: 0 | AF63: 0 | AG63: 0 | AH63: 0 | AI63: 0 | AJ63: 0 | AK63: 0 | AL63: 0 | AM63: 0 | AN63: 0 | AO63: 0 | AP63: 0 | AQ63: 0 | AR63: 0 | AS63: 0 | AT63: 0 | AU63: 0 | AV63: 0 | AW63: 0 | AX63: 0 | AY63: 0 | AZ63: 0 | BA63: 0 | BB63: 0 | BC63: 0 | BD63: 0 | BE63: 0 | BF63: 0 | BG63: 0 | BH63: 0 | BI63: 0 | BJ63: 0 | BK63: 0 | BL63: 0 | BM63: 0 | BN63: 0 | BO63: 0 | BP63: 0 | BQ63: 0 | BR63: 0 | BS63: 0 | BT63: 0 | BU63: 0 | BV63: 0 | BW63: 0 | BX63: 0 | BY63: 0 | BZ63: 0 | CA63: 0 | CB63: 0 | CC63: 0 | CD63: 0 | CE63: 0 | CF63: 0 | CG63: 0 | CH63: 0 | CI63: 0 | CJ63: 0 | CK63: 0 | CL63: 0 | CM63: 0 | CN63: 0 | CO63: 0 | CP63: 0 | CQ63: 0 | CR63: 0 | CS63: 0 | CT63: 0 | CU63: 0 | CV63: 0 | CW63: 0 | DA63: 204030 | DB63: 기타영업비용 | DC63: 0 | DD63: 0 | DE63: 0 | DF63: 184.06849 | DG63: 0 | DH63: 0 | DI63: 0 | DJ63: 0 | DK63: 0 | DL63: 0 | DM63: 0 | DN63: 0
B65: 204040 | C65: 이자비용 | D65: Interest Expenses | J65: 0 | K65: 0 | L65: 0 | M65: 0 | N65: 0 | O65: 0 | P65: 0 | Q65: 0 | R65: 0 | S65: 0 | T65: 0 | U65: 0 | V65: 0 | W65: 0 | X65: 0 | Y65: 0 | Z65: 0 | AA65: 0 | AB65: 0 | AC65: 0 | AD65: 0 | AE65: 0 | AF65: 0 | AG65: 0 | AH65: 0 | AI65: 0 | AJ65: 0 | AK65: 0 | AL65: 0 | AM65: 0 | AN65: 0 | AO65: 0 | AP65: 0 | AQ65: 0 | AR65: 0 | AS65: 0 | AT65: 0 | AU65: 0 | AV65: 0 | AW65: 0 | AX65: 0 | AY65: 0 | AZ65: 0 | BA65: 0 | BB65: 0 | BC65: 0 | BD65: 0 | BE65: 0 | BF65: 0 | BG65: 0 | BH65: 0 | BI65: 0 | BJ65: 0 | BK65: 0 | BL65: 0 | BM65: 0 | BN65: 0 | BO65: 0 | BP65: 0 | BQ65: 0 | BR65: 0 | BS65: 0 | BT65: 0 | BU65: 0 | BV65: 0 | BW65: 0 | BX65: 0 | BY65: 0 | BZ65: 0 | CA65: 0 | CB65: 0 | CC65: 0 | CD65: 0 | CE65: 0 | CF65: 0 | CG65: 0 | CH65: 0 | CI65: 0 | CJ65: 0 | CK65: 0 | CL65: 0 | CM65: 0 | CN65: 0 | CO65: 0 | CP65: 0 | CQ65: 0 | CR65: 0 | CS65: 0 | CT65: 0 | CU65: 0 | CV65: 0 | CW65: 0 | DA65: 204040 | DB65: 이자비용 | DC65: 0 | DD65: 0 | DE65: 0 | DF65: 0 | DG65: 0 | DH65: 0 | DI65: 0 | DJ65: 0 | DK65: 0 | DL65: 0 | DM65: 0 | DN65: 0
C66: (분기배분, manual) | D66: (Q Distribution) | J66: 0 | K66: 0 | L66: 0 | M66: 0 | N66: 0 | O66: 0 | P66: 0 | Q66: 0 | R66: 0 | S66: 0 | T66: 0 | U66: 0 | V66: 0 | W66: 0 | X66: 0 | Y66: 0 | Z66: 0 | AA66: 0 | AB66: 0 | AC66: 0 | AD66: 0 | AE66: 0 | AF66: 0 | AG66: 0 | AH66: 0 | AI66: 0 | AJ66: 0 | AK66: 0 | AL66: 0 | AM66: 0 | AN66: 0 | AO66: 0 | AP66: 0 | AQ66: 0 | AR66: 0 | AS66: 0 | AT66: 0 | AU66: 0 | AV66: 0 | AW66: 0 | AX66: 0 | AY66: 0 | AZ66: 0 | BA66: 0 | BB66: 0 | BC66: 0 | BD66: 0 | BE66: 0 | BF66: 0 | BG66: 0 | BH66: 0 | BI66: 0 | BJ66: 0 | BK66: 0 | BL66: 0 | BM66: 0 | BN66: 0 | BO66: 0 | BP66: 0 | BQ66: 0 | BR66: 0 | BS66: 0 | BT66: 0 | BU66: 0 | BV66: 0 | BW66: 0 | BX66: 0 | BY66: 0 | BZ66: 0.25 | CA66: 0.25 | CB66: 0.25 | CC66: 0.25 | CD66: 0.25 | CE66: 0.25 | CF66: 0.25 | CG66: 0.25 | CH66: 0.25 | CI66: 0.25 | CJ66: 0.25 | CK66: 0.25 | CL66: 0.25 | CM66: 0.25 | CN66: 0.25 | CO66: 0.25 | CP66: 0.25 | CQ66: 0.25 | CR66: 0.25 | CS66: 0.25 | CT66: 0.25 | CU66: 0.25 | CV66: 0.25 | CW66: 0.25
B67: 204050 | C67: 외환거래손실 | D67: Losses on Foreign Exchange | J67: 0 | K67: 0 | L67: 0 | M67: 0 | N67: 0 | O67: 0 | P67: 0 | Q67: 0 | R67: 0 | S67: 0 | T67: 0 | U67: 0 | V67: 25.864 | W67: 14.436 | X67: 19.429 | Y67: 29.669 | Z67: 15.384 | AA67: 11.714 | AB67: 10.807 | AC67: 0 | AD67: 0 | AE67: 0 | AF67: 0 | AG67: 0 | AH67: 0 | AI67: 0 | AJ67: 0 | AK67: 0 | AL67: 0 | AM67: 0 | AN67: 0 | AO67: 0 | AP67: 0 | AQ67: 0 | AR67: 0 | AS67: 0 | AT67: 0 | AU67: 0 | AV67: 0 | AW67: 0 | AX67: 0 | AY67: 0 | AZ67: 0 | BA67: 0 | BB67: 0 | BC67: 0 | BD67: 0 | BE67: 0 | BF67: 0 | BG67: 0 | BH67: 0 | BI67: 0 | BJ67: 0 | BK67: 0 | BL67: 0 | BM67: 0 | BN67: 0 | BO67: 0 | BP67: 0 | BQ67: 0 | BR67: 0 | BS67: 0 | BT67: 0 | BU67: 0 | BV67: 0 | BW67: 0 | BX67: 0 | BY67: 0 | BZ67: 0 | CA67: 0 | CB67: 0 | CC67: 0 | CD67: 0 | CE67: 0 | CF67: 0 | CG67: 0 | CH67: 0 | CI67: 0 | CJ67: 0 | CK67: 0 | CL67: 0 | CM67: 0 | CN67: 0 | CO67: 0 | CP67: 0 | CQ67: 0 | CR67: 0 | CS67: 0 | CT67: 0 | CU67: 0 | CV67: 0 | CW67: 0 | DA67: 204050 | DB67: 외환거래손실 | DC67: 0 | DD67: 0 | DE67: 0 | DF67: 89.398 | DG67: 0 | DH67: 0 | DI67: 0 | DJ67: 0 | DK67: 0 | DL67: 0 | DM67: 0 | DN67: 0
C68: (분기배분, manual) | D68: (Q Distribution) | J68: 0 | K68: 0 | L68: 0 | M68: 0 | N68: 0 | O68: 0 | P68: 0 | Q68: 0 | R68: 0 | S68: 0 | T68: 0 | U68: 0 | V68: 0.28931296 | W68: 0.16148012 | X68: 0.21733148 | Y68: 0.33187543 | Z68: 0 | AA68: 0 | AB68: 0 | AC68: 0 | AD68: 0 | AE68: 0 | AF68: 0 | AG68: 0 | AH68: 0 | AI68: 0 | AJ68: 0 | AK68: 0 | AL68: 0 | AM68: 0 | AN68: 0 | AO68: 0 | AP68: 0 | AQ68: 0 | AR68: 0 | AS68: 0 | AT68: 0 | AU68: 0 | AV68: 0 | AW68: 0 | AX68: 0 | AY68: 0 | AZ68: 0 | BA68: 0 | BB68: 0 | BC68: 0 | BD68: 0 | BE68: 0 | BF68: 0 | BG68: 0 | BH68: 0 | BI68: 0 | BJ68: 0 | BK68: 0 | BL68: 0 | BM68: 0 | BN68: 0 | BO68: 0 | BP68: 0 | BQ68: 0 | BR68: 0 | BS68: 0 | BT68: 0 | BU68: 0 | BV68: 0 | BW68: 0 | BX68: 0 | BY68: 0 | BZ68: 0.25 | CA68: 0.25 | CB68: 0.25 | CC68: 0.25 | CD68: 0.25 | CE68: 0.25 | CF68: 0.25 | CG68: 0.25 | CH68: 0.25 | CI68: 0.25 | CJ68: 0.25 | CK68: 0.25 | CL68: 0.25 | CM68: 0.25 | CN68: 0.25 | CO68: 0.25 | CP68: 0.25 | CQ68: 0.25 | CR68: 0.25 | CS68: 0.25 | CT68: 0.25 | CU68: 0.25 | CV68: 0.25 | CW68: 0.25
B69: 204240 | C69: 투자자산평가손실 | D69: Losses on Investment Assets | J69: 0 | K69: 0 | L69: 0 | M69: 0 | N69: 0 | O69: 0 | P69: 0 | Q69: 0 | R69: 0 | S69: 0 | T69: 0 | U69: 0 | V69: 0 | W69: 0 | X69: 0 | Y69: 0 | Z69: 0 | AA69: 0 | AB69: 0 | AC69: 0 | AD69: 0 | AE69: 0 | AF69: 0 | AG69: 0 | AH69: 0 | AI69: 0 | AJ69: 0 | AK69: 0 | AL69: 0 | AM69: 0 | AN69: 0 | AO69: 0 | AP69: 0 | AQ69: 0 | AR69: 0 | AS69: 0 | AT69: 0 | AU69: 0 | AV69: 0 | AW69: 0 | AX69: 0 | AY69: 0 | AZ69: 0 | BA69: 0 | BB69: 0 | BC69: 0 | BD69: 0 | BE69: 0 | BF69: 0 | BG69: 0 | BH69: 0 | BI69: 0 | BJ69: 0 | BK69: 0 | BL69: 0 | BM69: 0 | BN69: 0 | BO69: 0 | BP69: 0 | BQ69: 0 | BR69: 0 | BS69: 0 | BT69: 0 | BU69: 0 | BV69: 0 | BW69: 0 | BX69: 0 | BY69: 0 | BZ69: 0 | CA69: 0 | CB69: 0 | CC69: 0 | CD69: 0 | CE69: 0 | CF69: 0 | CG69: 0 | CH69: 0 | CI69: 0 | CJ69: 0 | CK69: 0 | CL69: 0 | CM69: 0 | CN69: 0 | CO69: 0 | CP69: 0 | CQ69: 0 | CR69: 0 | CS69: 0 | CT69: 0 | CU69: 0 | CV69: 0 | CW69: 0 | DA69: 204240 | DB69: 투자자산평가손실 | DC69: 0 | DD69: 0 | DE69: 0 | DF69: 0 | DG69: 0 | DH69: 0 | DI69: 0 | DJ69: 0 | DK69: 0 | DL69: 0 | DM69: 0 | DN69: 0
C70: (분기배분, manual) | D70: (Q Distribution) | J70: 0 | K70: 0 | L70: 0 | M70: 0 | N70: 0 | O70: 0 | P70: 0 | Q70: 0 | R70: 0 | S70: 0 | T70: 0 | U70: 0 | V70: 0 | W70: 0 | X70: 0 | Y70: 0 | Z70: 0 | AA70: 0 | AB70: 0 | AC70: 0 | AD70: 0 | AE70: 0 | AF70: 0 | AG70: 0 | AH70: 0 | AI70: 0 | AJ70: 0 | AK70: 0 | AL70: 0 | AM70: 0 | AN70: 0 | AO70: 0 | AP70: 0 | AQ70: 0 | AR70: 0 | AS70: 0 | AT70: 0 | AU70: 0 | AV70: 0 | AW70: 0 | AX70: 0 | AY70: 0 | AZ70: 0 | BA70: 0 | BB70: 0 | BC70: 0 | BD70: 0 | BE70: 0 | BF70: 0 | BG70: 0 | BH70: 0 | BI70: 0 | BJ70: 0 | BK70: 0 | BL70: 0 | BM70: 0 | BN70: 0 | BO70: 0 | BP70: 0 | BQ70: 0 | BR70: 0 | BS70: 0 | BT70: 0 | BU70: 0 | BV70: 0 | BW70: 0 | BX70: 0 | BY70: 0 | BZ70: 0.25 | CA70: 0.25 | CB70: 0.25 | CC70: 0.25 | CD70: 0.25 | CE70: 0.25 | CF70: 0.25 | CG70: 0.25 | CH70: 0.25 | CI70: 0.25 | CJ70: 0.25 | CK70: 0.25 | CL70: 0.25 | CM70: 0.25 | CN70: 0.25 | CO70: 0.25 | CP70: 0.25 | CQ70: 0.25 | CR70: 0.25 | CS70: 0.25 | CT70: 0.25 | CU70: 0.25 | CV70: 0.25 | CW70: 0.25
B71: 204031 | C71: 기타 기타비용 | D71: Others | J71: 0 | K71: 0 | L71: 0 | M71: 0 | N71: 0 | O71: 0 | P71: 0 | Q71: 0 | R71: 0 | S71: 0 | T71: 0 | U71: 0 | V71: 19.046788 | W71: 33.451893 | X71: 19.051823 | Y71: 23.119991 | Z71: 8.696 | AA71: 28.515 | AB71: 10.494 | AC71: 0 | AD71: 0 | AE71: 0 | AF71: 0 | AG71: 0 | AH71: 0 | AI71: 0 | AJ71: 0 | AK71: 0 | AL71: 0 | AM71: 0 | AN71: 0 | AO71: 0 | AP71: 0 | AQ71: 0 | AR71: 0 | AS71: 0 | AT71: 0 | AU71: 0 | AV71: 0 | AW71: 0 | AX71: 0 | AY71: 0 | AZ71: 0 | BA71: 0 | BB71: 0 | BC71: 0 | BD71: 0 | BE71: 0 | BF71: 0 | BG71: 0 | BH71: 0 | BI71: 0 | BJ71: 0 | BK71: 0 | BL71: 0 | BM71: 0 | BN71: 0 | BO71: 0 | BP71: 0 | BQ71: 0 | BR71: 0 | BS71: 0 | BT71: 0 | BU71: 0 | BV71: 0 | BW71: 0 | BX71: 0 | BY71: 0 | BZ71: 0 | CA71: 0 | CB71: 0 | CC71: 0 | CD71: 0 | CE71: 0 | CF71: 0 | CG71: 0 | CH71: 0 | CI71: 0 | CJ71: 0 | CK71: 0 | CL71: 0 | CM71: 0 | CN71: 0 | CO71: 0 | CP71: 0 | CQ71: 0 | CR71: 0 | CS71: 0 | CT71: 0 | CU71: 0 | CV71: 0 | CW71: 0 | DA71: 204031 | DB71: 기타 기타비용 | DC71: 0 | DD71: 0 | DE71: 0 | DF71: 94.670495 | DG71: 0 | DH71: 0 | DI71: 0 | DJ71: 0 | DK71: 0 | DL71: 0 | DM71: 0 | DN71: 0
C72: (분기배분, manual) | D72: (Q Distribution) | J72: 0 | K72: 0 | L72: 0 | M72: 0 | N72: 0 | O72: 0 | P72: 0 | Q72: 0 | R72: 0 | S72: 0 | T72: 0 | U72: 0 | V72: 0.20119033 | W72: 0.35335078 | X72: 0.20124351 | Y72: 0.24421538 | Z72: 0 | AA72: 0 | AB72: 0 | AC72: 0 | AD72: 0 | AE72: 0 | AF72: 0 | AG72: 0 | AH72: 0 | AI72: 0 | AJ72: 0 | AK72: 0 | AL72: 0 | AM72: 0 | AN72: 0 | AO72: 0 | AP72: 0 | AQ72: 0 | AR72: 0 | AS72: 0 | AT72: 0 | AU72: 0 | AV72: 0 | AW72: 0 | AX72: 0 | AY72: 0 | AZ72: 0 | BA72: 0 | BB72: 0 | BC72: 0 | BD72: 0 | BE72: 0 | BF72: 0 | BG72: 0 | BH72: 0 | BI72: 0 | BJ72: 0 | BK72: 0 | BL72: 0 | BM72: 0 | BN72: 0 | BO72: 0 | BP72: 0 | BQ72: 0 | BR72: 0 | BS72: 0 | BT72: 0 | BU72: 0 | BV72: 0 | BW72: 0 | BX72: 0 | BY72: 0 | BZ72: 0.25 | CA72: 0.25 | CB72: 0.25 | CC72: 0.25 | CD72: 0.25 | CE72: 0.25 | CF72: 0.25 | CG72: 0.25 | CH72: 0.25 | CI72: 0.25 | CJ72: 0.25 | CK72: 0.25 | CL72: 0.25 | CM72: 0.25 | CN72: 0.25 | CO72: 0.25 | CP72: 0.25 | CQ72: 0.25 | CR72: 0.25 | CS72: 0.25 | CT72: 0.25 | CU72: 0.25 | CV72: 0.25 | CW72: 0.25
B75: 201370 | C75: 영업이익 | D75: Operating Income | J75: 0 | K75: 0 | L75: 0 | M75: 0 | N75: 0 | O75: 0 | P75: 0 | Q75: 0 | R75: 0 | S75: 0 | T75: 0 | U75: 0 | V75: 142.63415 | W75: 187.98149 | X75: 270.77684 | Y75: 152.61429 | Z75: 153.188 | AA75: 166.83 | AB75: 218.831 | AC75: 236.642 | AD75: 178.637 | AE75: 200.652 | AF75: 206.053 | AG75: 118.755 | AH75: 187.654 | AI75: 279.568 | AJ75: 230.699 | AK75: 131.274 | AL75: 200.654 | AM75: 254.308 | AN75: 264.393 | AO75: 369.973 | AP75: 207.176 | AQ75: 268.399 | AR75: 275.12 | AS75: 408.264 | AT75: 228.632 | AU75: 281.798 | AV75: 281.051 | AW75: 194.624 | AX75: 218.47 | AY75: 220.887 | AZ75: 237.919 | BA75: 162.713 | BB75: 205.203 | BC75: 245.09 | BD75: 239.162 | BE75: 170.212 | BF75: 165.347 | BG75: 153.858 | BH75: 139.846 | BI75: 89.921 | BJ75: 200.899 | BK75: 140.968 | BL75: 220.364 | BM75: 191.273 | BN75: 171.481 | BO75: 175.408 | BP75: 153.706 | BQ75: 74.307 | BR75: 173.512 | BS75: 223.551 | BT75: 243.869 | BU75: 144.498 | BV75: 250.913 | BW75: 147.303 | BX75: 114.291 | BY75: -1775.927 | BZ75: -2077.2566 | CA75: -2077.2566 | CB75: -2077.2566 | CC75: 4840.2523 | CD75: 5339.67 | CE75: 5339.67 | CF75: 5339.67 | CG75: -17525.746 | CH75: -19305.554 | CI75: -19305.554 | CJ75: -19305.554 | CK75: 56274.724 | CL75: 62007.406 | CM75: 62007.406 | CN75: 62007.406 | CO75: -187818.72 | CP75: -206939.02 | CQ75: -206939.02 | CR75: -206939.02 | CS75: 618846.45 | CT75: 681854.98 | CU75: 681854.98 | CV75: 681854.98 | CW75: -2047730 | DA75: 201370 | DB75: 영업이익 | DC75: 566.90325 | DD75: 581.04109 | DE75: 755.30163 | DF75: 754.00678 | DG75: 760.408 | DH75: 704.097 | DI75: 829.195 | DJ75: 1089.328 | DK75: 1158.959 | DL75: 986.105 | DM75: 839.989 | DN75: 859.667
C76: (분기비중) | D76: (Q Portion) | J76: 0 | K76: 0 | L76: 0 | M76: 0 | N76: 0 | O76: 0 | P76: 0 | Q76: 0 | R76: 0 | S76: 0 | T76: 0 | U76: 0 | V76: 0.18916827 | W76: 0.24931008 | X76: 0.35911725 | Y76: 0.2024044 | Z76: 0.20145501 | AA76: 0.21939538 | AB76: 0.28778103 | AC76: 0.31120399 | AD76: 0.25371078 | AE76: 0.28497778 | AF76: 0.2926486 | AG76: 0.16866284 | AH76: 0.22630865 | AI76: 0.33715592 | AJ76: 0.27822044 | AK76: 0.15831499 | AL76: 0.1841998 | AM76: 0.23345402 | AN76: 0.24271202 | AO76: 0.33963416 | AP76: 0.17876042 | AQ76: 0.23158628 | AR76: 0.23738545 | AS76: 0.35226785 | AT76: 0.23185361 | AU76: 0.28576876 | AV76: 0.28501123 | AW76: 0.19736641 | AX76: 0.26008674 | AY76: 0.26296416 | AZ76: 0.28324061 | BA76: 0.19370849 | BB76: 0.23870057 | BC76: 0.28509876 | BD76: 0.27820307 | BE76: 0.1979976 | BF76: 0.30119387 | BG76: 0.28026566 | BH76: 0.25474159 | BI76: 0.16379888 | BJ76: 0.26661969 | BK76: 0.18708328 | BL76: 0.29245233 | BM76: 0.2538447 | BN76: 0.29827866 | BO76: 0.30510939 | BP76: 0.26736035 | BQ76: 0.12925159 | BR76: 0.22091339 | BS76: 0.28462244 | BT76: 0.31049107 | BU76: 0.18397311 | BV76: -0.19859825 | BW76: -0.11659068 | BX76: -0.090461604 | BY76: 1.4056505 | BZ76: 1.4927994 | CA76: 1.4927994 | CB76: 1.4927994 | CC76: -3.4783983 | CD76: -3.543866 | CE76: -3.543866 | CF76: -3.543866 | CG76: 11.631598 | CH76: 11.757778 | CI76: 11.757778 | CJ76: 11.757778 | CK76: -34.273333 | CL76: -34.515565 | CM76: -34.515565 | CN76: -34.515565 | CO76: 104.5467 | CP76: 105.01248 | CQ76: 105.01248 | CR76: 105.01248 | CS76: -314.03743 | CT76: -314.93858 | CU76: -314.93858 | CV76: -314.93858 | CW76: 945.81574
C77: (% of sales) | D77: (% of sales) | J77: 0 | K77: 0 | L77: 0 | M77: 0 | N77: 0 | O77: 0 | P77: 0 | Q77: 0 | R77: 0 | S77: 0 | T77: 0 | U77: 0 | V77: 0.062408276 | W77: 0.065498663 | X77: 0.091425017 | Y77: 0.04013077 | Z77: 0.056619471 | AA77: 0.052440084 | AB77: 0.065927229 | AC77: 0.057456568 | AD77: 0.062433835 | AE77: 0.057813171 | AF77: 0.058290727 | AG77: 0.029798969 | AH77: 0.057028087 | AI77: 0.059446026 | AJ77: 0.054165299 | AK77: 0.026130045 | AL77: 0.050885966 | AM77: 0.052809818 | AN77: 0.056117917 | AO77: 0.064197497 | AP77: 0.04831638 | AQ77: 0.057269975 | AR77: 0.061629251 | AS77: 0.075794774 | AT77: 0.055362953 | AU77: 0.066811434 | AV77: 0.066236982 | AW77: 0.045298551 | AX77: 0.061746661 | AY77: 0.052094836 | AZ77: 0.053032 | BA77: 0.036431242 | BB77: 0.0529193 | BC77: 0.05234854 | BD77: 0.058506845 | BE77: 0.036751072 | BF77: 0.04073726 | BG77: 0.033858477 | BH77: 0.034594085 | BI77: 0.020789243 | BJ77: 0.048414414 | BK77: 0.032158542 | BL77: 0.050635715 | BM77: 0.03692184 | BN77: 0.041367543 | BO77: 0.031438235 | BP77: 0.028302415 | BQ77: 0.012214541 | BR77: 0.028769635 | BS77: 0.031207566 | BT77: 0.031032394 | BU77: 0.016805245 | BV77: 0.029362835 | BW77: 0.017086065 | BX77: 0.013841868 | BY77: -0.24506131 | BZ77: -0.23082844 | CA77: -0.23082844 | CB77: -0.23082844 | CC77: 0.53785743 | CD77: 0.5385245 | CE77: 0.5385245 | CF77: 0.5385245 | CG77: -1.7675331 | CH77: -1.7671166 | CI77: -1.7671166 | CJ77: -1.7671166 | CK77: 5.1510563 | CL77: 5.1513181 | CM77: 5.1513181 | CN77: 5.1513181 | CO77: -15.6032 | CP77: -15.603035 | CQ77: -15.603035 | CR77: -15.603035 | CS77: 46.660521 | CT77: 46.660627 | CU77: 46.660627 | CV77: 46.660627 | CW77: -140.13004
C78: (% growth, QoQ) | D78: (% growth, QoQ) | J78: 0 | K78: 0 | L78: 0 | M78: 0 | N78: 0 | O78: 0 | P78: 0 | Q78: 0 | R78: 0 | S78: 0 | T78: 0 | U78: 0 | V78: 0 | W78: 0.31792762 | X78: 0.44044412 | Y78: -0.43638351 | Z78: 0.0037592059 | AA78: 0.089053973 | AB78: 0.31170053 | AC78: 0.081391576 | AD78: -0.2451171 | AE78: 0.12323875 | AF78: 0.02691725 | AG78: -0.4236677 | AH78: 0.58017768 | AI78: 0.48980571 | AJ78: -0.17480184 | AK78: -0.43097283 | AL78: 0.52851288 | AM78: 0.26739562 | AN78: 0.039656637 | AO78: 0.39932979 | AP78: -0.440024 | AQ78: 0.29551203 | AR78: 0.025041077 | AS78: 0.48394882 | AT78: -0.43998981 | AU78: 0.23253963 | AV78: -0.002650835 | AW78: -0.30751358 | AX78: 0.12252343 | AY78: 0.011063304 | AZ78: 0.077107299 | BA78: -0.31609918 | BB78: 0.26113464 | BC78: 0.19437825 | BD78: -0.024187033 | BE78: -0.28829831 | BF78: -0.028582004 | BG78: -0.069484176 | BH78: -0.091070988 | BI78: -0.35699984 | BJ78: 1.2341722 | BK78: -0.29831408 | BL78: 0.56322002 | BM78: -0.1320134 | BN78: -0.10347514 | BO78: 0.022900496 | BP78: -0.12372298 | BQ78: -0.51656409 | BR78: 1.3350694 | BS78: 0.28838928 | BT78: 0.090887538 | BU78: -0.40747697 | BV78: 0.73644618 | BW78: -0.41293197 | BX78: -0.22410949 | BY78: -16.538643 | BZ78: -0.16967455 | CA78: 0 | CB78: 0 | CC78: 3.3301176 | CD78: 0.1031801 | CE78: 0 | CF78: 0 | CG78: -4.2821777 | CH78: -0.10155393 | CI78: 0 | CJ78: 0 | CK78: 3.9149499 | CL78: 0.10186958 | CM78: 0 | CN78: 0 | CO78: -4.0289724 | CP78: -0.10180187 | CQ78: 0 | CR78: 0 | CS78: 3.9904773 | CT78: 0.10181609 | CU78: 0 | CV78: 0 | CW78: -4.0031752
C79: (% growth, YoY) | D79: (% growth, YoY) | J79: 0 | K79: 0 | L79: 0 | M79: 0 | N79: 0 | O79: 0 | P79: 0 | Q79: 0 | R79: 0 | S79: 0 | T79: 0 | U79: 0 | V79: 0 | W79: 0 | X79: 0 | Y79: 0 | Z79: 0.073992411 | AA79: -0.11251902 | AB79: -0.19184003 | AC79: 0.55058873 | AD79: 0.1661292 | AE79: 0.20273332 | AF79: -0.058392093 | AG79: -0.49816601 | AH79: 0.050476665 | AI79: 0.39329785 | AJ79: 0.11961 | AK79: 0.10541872 | AL79: 0.069276434 | AM79: -0.090353689 | AN79: 0.14605178 | AO79: 1.8183266 | AP79: 0.032503713 | AQ79: 0.055409189 | AR79: 0.040572179 | AS79: 0.10349674 | AT79: 0.10356412 | AU79: 0.049921945 | AV79: 0.021557866 | AW79: -0.52328885 | AX79: -0.044446972 | AY79: -0.21615129 | AZ79: -0.15346681 | BA79: -0.16396231 | BB79: -0.060726873 | BC79: 0.10957186 | BD79: 0.0052244672 | BE79: 0.046087283 | BF79: -0.19422718 | BG79: -0.37223877 | BH79: -0.41526664 | BI79: -0.47171175 | BJ79: 0.21501448 | BK79: -0.083778549 | BL79: 0.57576191 | BM79: 1.1271227 | BN79: -0.14643179 | BO79: 0.24431077 | BP79: -0.30249042 | BQ79: -0.61151339 | BR79: 0.011843878 | BS79: 0.27446297 | BT79: 0.58659389 | BU79: 0.94460818 | BV79: 0.44608442 | BW79: -0.34107653 | BX79: -0.53134265 | BY79: -13.290322 | BZ79: -9.2787923 | CA79: -15.10193 | CB79: -19.175155 | CC79: 3.7254793 | CD79: 3.5705394 | CE79: 3.5705394 | CF79: 3.5705394 | CG79: -4.6208331 | CH79: -4.6154957 | CI79: -4.6154957 | CJ79: -4.6154957 | CK79: 4.2109745 | CL79: 4.2118947 | CM79: 4.2118947 | CN79: 4.2118947 | CO79: -4.3375326 | CP79: -4.3373275 | CQ79: -4.3373275 | CR79: -4.3373275 | CS79: 4.2949135 | CT79: 4.294956 | CU79: 4.294956 | CV79: 4.294956 | CW79: -4.3089468
B81: 201371 | C81: 조정영업이익 | D81: Operating Income | J81: 0 | K81: 0 | L81: 0 | M81: 0 | N81: 0 | O81: 0 | P81: 0 | Q81: 0 | R81: 0 | S81: 0 | T81: 0 | U81: 0 | V81: 150.87363 | W81: 190.57647 | X81: 254.75696 | Y81: 139.38894 | Z81: 146.57 | AA81: 157.469 | AB81: 219.727 | AC81: 236.642 | AD81: 178.637 | AE81: 200.652 | AF81: 206.053 | AG81: 118.755 | AH81: 187.654 | AI81: 279.568 | AJ81: 230.699 | AK81: 131.274 | AL81: 200.654 | AM81: 254.308 | AN81: 264.393 | AO81: 369.973 | AP81: 207.176 | AQ81: 268.399 | AR81: 275.12 | AS81: 408.264 | AT81: 228.632 | AU81: 281.798 | AV81: 281.051 | AW81: 194.624 | AX81: 218.47 | AY81: 220.887 | AZ81: 237.919 | BA81: 162.713 | BB81: 205.203 | BC81: 245.09 | BD81: 239.162 | BE81: 170.212 | BF81: 165.347 | BG81: 153.858 | BH81: 139.846 | BI81: 89.921 | BJ81: 200.899 | BK81: 140.968 | BL81: 220.364 | BM81: 191.273 | BN81: 171.481 | BO81: 175.408 | BP81: 153.706 | BQ81: 74.307 | BR81: 173.512 | BS81: 223.551 | BT81: 243.869 | BU81: 144.498 | BV81: 250.913 | BW81: 147.303 | BX81: 114.291 | BY81: -1775.927 | BZ81: -2077.2566 | CA81: -2077.2566 | CB81: -2077.2566 | CC81: 4840.2523 | CD81: 5339.67 | CE81: 5339.67 | CF81: 5339.67 | CG81: -17525.746 | CH81: -19305.554 | CI81: -19305.554 | CJ81: -19305.554 | CK81: 56274.724 | CL81: 62007.406 | CM81: 62007.406 | CN81: 62007.406 | CO81: -187818.72 | CP81: -206939.02 | CQ81: -206939.02 | CR81: -206939.02 | CS81: 618846.45 | CT81: 681854.98 | CU81: 681854.98 | CV81: 681854.98 | CW81: -2047730 | DA81: 201371 | DB81: 조정영업이익 | DC81: 566.90325 | DD81: 581.04109 | DE81: 755.30163 | DF81: 735.596 | DG81: 760.408 | DH81: 704.097 | DI81: 829.195 | DJ81: 1089.328 | DK81: 1158.959 | DL81: 986.105 | DM81: 839.989 | DN81: 859.667
C82: (분기비중) | D82: (Q Portion) | J82: 0 | K82: 0 | L82: 0 | M82: 0 | N82: 0 | O82: 0 | P82: 0 | Q82: 0 | R82: 0 | S82: 0 | T82: 0 | U82: 0 | V82: 0.20510393 | W82: 0.25907764 | X82: 0.34632728 | Y82: 0.18949116 | Z82: 0.19275179 | AA82: 0.20708488 | AB82: 0.28895935 | AC82: 0.31120399 | AD82: 0.25371078 | AE82: 0.28497778 | AF82: 0.2926486 | AG82: 0.16866284 | AH82: 0.22630865 | AI82: 0.33715592 | AJ82: 0.27822044 | AK82: 0.15831499 | AL82: 0.1841998 | AM82: 0.23345402 | AN82: 0.24271202 | AO82: 0.33963416 | AP82: 0.17876042 | AQ82: 0.23158628 | AR82: 0.23738545 | AS82: 0.35226785 | AT82: 0.23185361 | AU82: 0.28576876 | AV82: 0.28501123 | AW82: 0.19736641 | AX82: 0.26008674 | AY82: 0.26296416 | AZ82: 0.28324061 | BA82: 0.19370849 | BB82: 0.23870057 | BC82: 0.28509876 | BD82: 0.27820307 | BE82: 0.1979976 | BF82: 0.30119387 | BG82: 0.28026566 | BH82: 0.25474159 | BI82: 0.16379888 | BJ82: 0.26661969 | BK82: 0.18708328 | BL82: 0.29245233 | BM82: 0.2538447 | BN82: 0.29827866 | BO82: 0.30510939 | BP82: 0.26736035 | BQ82: 0.12925159 | BR82: 0.22091339 | BS82: 0.28462244 | BT82: 0.31049107 | BU82: 0.18397311 | BV82: -0.19859825 | BW82: -0.11659068 | BX82: -0.090461604 | BY82: 1.4056505 | BZ82: 1.4927994 | CA82: 1.4927994 | CB82: 1.4927994 | CC82: -3.4783983 | CD82: -3.543866 | CE82: -3.543866 | CF82: -3.543866 | CG82: 11.631598 | CH82: 11.757778 | CI82: 11.757778 | CJ82: 11.757778 | CK82: -34.273333 | CL82: -34.515565 | CM82: -34.515565 | CN82: -34.515565 | CO82: 104.5467 | CP82: 105.01248 | CQ82: 105.01248 | CR82: 105.01248 | CS82: -314.03743 | CT82: -314.93858 | CU82: -314.93858 | CV82: -314.93858 | CW82: 945.81574
C83: (% of sales) | D83: (% of sales) | J83: 0 | K83: 0 | L83: 0 | M83: 0 | N83: 0 | O83: 0 | P83: 0 | Q83: 0 | R83: 0 | S83: 0 | T83: 0 | U83: 0 | V83: 0.066013383 | W83: 0.066402835 | X83: 0.086016071 | Y83: 0.036653091 | Z83: 0.054173407 | AA83: 0.049497618 | AB83: 0.066197167 | AC83: 0.057456568 | AD83: 0.062433835 | AE83: 0.057813171 | AF83: 0.058290727 | AG83: 0.029798969 | AH83: 0.057028087 | AI83: 0.059446026 | AJ83: 0.054165299 | AK83: 0.026130045 | AL83: 0.050885966 | AM83: 0.052809818 | AN83: 0.056117917 | AO83: 0.064197497 | AP83: 0.04831638 | AQ83: 0.057269975 | AR83: 0.061629251 | AS83: 0.075794774 | AT83: 0.055362953 | AU83: 0.066811434 | AV83: 0.066236982 | AW83: 0.045298551 | AX83: 0.061746661 | AY83: 0.052094836 | AZ83: 0.053032 | BA83: 0.036431242 | BB83: 0.0529193 | BC83: 0.05234854 | BD83: 0.058506845 | BE83: 0.036751072 | BF83: 0.04073726 | BG83: 0.033858477 | BH83: 0.034594085 | BI83: 0.020789243 | BJ83: 0.048414414 | BK83: 0.032158542 | BL83: 0.050635715 | BM83: 0.03692184 | BN83: 0.041367543 | BO83: 0.031438235 | BP83: 0.028302415 | BQ83: 0.012214541 | BR83: 0.028769635 | BS83: 0.031207566 | BT83: 0.031032394 | BU83: 0.016805245 | BV83: 0.029362835 | BW83: 0.017086065 | BX83: 0.013841868 | BY83: -0.24506131 | BZ83: -0.23082844 | CA83: -0.23082844 | CB83: -0.23082844 | CC83: 0.53785743 | CD83: 0.5385245 | CE83: 0.5385245 | CF83: 0.5385245 | CG83: -1.7675331 | CH83: -1.7671166 | CI83: -1.7671166 | CJ83: -1.7671166 | CK83: 5.1510563 | CL83: 5.1513181 | CM83: 5.1513181 | CN83: 5.1513181 | CO83: -15.6032 | CP83: -15.603035 | CQ83: -15.603035 | CR83: -15.603035 | CS83: 46.660521 | CT83: 46.660627 | CU83: 46.660627 | CV83: 46.660627 | CW83: -140.13004
C84: (% growth, QoQ) | D84: (% growth, QoQ) | J84: 0 | K84: 0 | L84: 0 | M84: 0 | N84: 0 | O84: 0 | P84: 0 | Q84: 0 | R84: 0 | S84: 0 | T84: 0 | U84: 0 | V84: 0 | W84: 0.26315297 | X84: 0.33677026 | Y84: -0.45285523 | Z84: 0.051518155 | AA84: 0.074360374 | AB84: 0.39536671 | AC84: 0.076981891 | AD84: -0.2451171 | AE84: 0.12323875 | AF84: 0.02691725 | AG84: -0.4236677 | AH84: 0.58017768 | AI84: 0.48980571 | AJ84: -0.17480184 | AK84: -0.43097283 | AL84: 0.52851288 | AM84: 0.26739562 | AN84: 0.039656637 | AO84: 0.39932979 | AP84: -0.440024 | AQ84: 0.29551203 | AR84: 0.025041077 | AS84: 0.48394882 | AT84: -0.43998981 | AU84: 0.23253963 | AV84: -0.002650835 | AW84: -0.30751358 | AX84: 0.12252343 | AY84: 0.011063304 | AZ84: 0.077107299 | BA84: -0.31609918 | BB84: 0.26113464 | BC84: 0.19437825 | BD84: -0.024187033 | BE84: -0.28829831 | BF84: -0.028582004 | BG84: -0.069484176 | BH84: -0.091070988 | BI84: -0.35699984 | BJ84: 1.2341722 | BK84: -0.29831408 | BL84: 0.56322002 | BM84: -0.1320134 | BN84: -0.10347514 | BO84: 0.022900496 | BP84: -0.12372298 | BQ84: -0.51656409 | BR84: 1.3350694 | BS84: 0.28838928 | BT84: 0.090887538 | BU84: -0.40747697 | BV84: 0.73644618 | BW84: -0.41293197 | BX84: -0.22410949 | BY84: -16.538643 | BZ84: -0.16967455 | CA84: 0 | CB84: 0 | CC84: 3.3301176 | CD84: 0.1031801 | CE84: 0 | CF84: 0 | CG84: -4.2821777 | CH84: -0.10155393 | CI84: 0 | CJ84: 0 | CK84: 3.9149499 | CL84: 0.10186958 | CM84: 0 | CN84: 0 | CO84: -4.0289724 | CP84: -0.10180187 | CQ84: 0 | CR84: 0 | CS84: 3.9904773 | CT84: 0.10181609 | CU84: 0 | CV84: 0 | CW84: -4.0031752
C85: (% growth, YoY) | D85: (% growth, YoY) | J85: 0 | K85: 0 | L85: 0 | M85: 0 | N85: 0 | O85: 0 | P85: 0 | Q85: 0 | R85: 0 | S85: 0 | T85: 0 | U85: 0 | V85: 0 | W85: 0 | X85: 0 | Y85: 0 | Z85: -0.028524726 | AA85: -0.17372277 | AB85: -0.13750345 | AC85: 0.69771003 | AD85: 0.21878283 | AE85: 0.27423175 | AF85: -0.062231769 | AG85: -0.49816601 | AH85: 0.050476665 | AI85: 0.39329785 | AJ85: 0.11961 | AK85: 0.10541872 | AL85: 0.069276434 | AM85: -0.090353689 | AN85: 0.14605178 | AO85: 1.8183266 | AP85: 0.032503713 | AQ85: 0.055409189 | AR85: 0.040572179 | AS85: 0.10349674 | AT85: 0.10356412 | AU85: 0.049921945 | AV85: 0.021557866 | AW85: -0.52328885 | AX85: -0.044446972 | AY85: -0.21615129 | AZ85: -0.15346681 | BA85: -0.16396231 | BB85: -0.060726873 | BC85: 0.10957186 | BD85: 0.0052244672 | BE85: 0.046087283 | BF85: -0.19422718 | BG85: -0.37223877 | BH85: -0.41526664 | BI85: -0.47171175 | BJ85: 0.21501448 | BK85: -0.083778549 | BL85: 0.57576191 | BM85: 1.1271227 | BN85: -0.14643179 | BO85: 0.24431077 | BP85: -0.30249042 | BQ85: -0.61151339 | BR85: 0.011843878 | BS85: 0.27446297 | BT85: 0.58659389 | BU85: 0.94460818 | BV85: 0.44608442 | BW85: -0.34107653 | BX85: -0.53134265 | BY85: -13.290322 | BZ85: -9.2787923 | CA85: -15.10193 | CB85: -19.175155 | CC85: 3.7254793 | CD85: 3.5705394 | CE85: 3.5705394 | CF85: 3.5705394 | CG85: -4.6208331 | CH85: -4.6154957 | CI85: -4.6154957 | CJ85: -4.6154957 | CK85: 4.2109745 | CL85: 4.2118947 | CM85: 4.2118947 | CN85: 4.2118947 | CO85: -4.3375326 | CP85: -4.3373275 | CQ85: -4.3373275 | CR85: -4.3373275 | CS85: 4.2949135 | CT85: 4.294956 | CU85: 4.294956 | CV85: 4.294956 | CW85: -4.3089468
B87: 201372 | C87: EBITDA (*)조정영업이익 기준 | D87: Operating Income | J87: 0 | K87: 0 | L87: 0 | M87: 0 | N87: 0 | O87: 0 | P87: 0 | Q87: 0 | R87: 0 | S87: 0 | T87: 0 | U87: 0 | V87: 169.57563 | W87: 209.61247 | X87: 273.69396 | Y87: 159.14794 | Z87: 168.104 | AA87: 178.869 | AB87: 241.035 | AC87: 258.179 | AD87: 201.425 | AE87: 224.7 | AF87: 226.752 | AG87: 144.483 | AH87: 214.532 | AI87: 320.146 | AJ87: 272.682 | AK87: 175.889 | AL87: 245.629 | AM87: 300.564 | AN87: 307.099 | AO87: 431.855 | AP87: 251.817 | AQ87: 314.786 | AR87: 322.677 | AS87: 460.14 | AT87: 276.822 | AU87: 330.381 | AV87: 328.825 | AW87: 243.438 | AX87: 266.347 | AY87: 264.411 | AZ87: 279.142 | BA87: 202.207 | BB87: 251.469 | BC87: 287.717 | BD87: 280.345 | BE87: 224.39 | BF87: 209.825 | BG87: 203.449 | BH87: 183.978 | BI87: 123.377 | BJ87: 243.65 | BK87: 185.673 | BL87: 251.73 | BM87: 243.952 | BN87: 211.769 | BO87: 221.933 | BP87: 199.677 | BQ87: 123.231 | BR87: 222.909 | BS87: 274.678 | BT87: 301.999 | BU87: 181.958 | BV87: 302.566 | BW87: 203.12 | BX87: 170.584 | BY87: -1718.193 | BZ87: -2017.3061 | CA87: -2017.3061 | CB87: -2017.3061 | CC87: 4900.2028 | CD87: 5380.7952 | CE87: 5380.7952 | CF87: 5380.7952 | CG87: -17484.621 | CH87: -19277.184 | CI87: -19277.184 | CJ87: -19277.184 | CK87: 56303.093 | CL87: 62027.118 | CM87: 62027.118 | CN87: 62027.118 | CO87: -187799.01 | CP87: -206925.2 | CQ87: -206925.2 | CR87: -206925.2 | CS87: 618860.27 | CT87: 681864.78 | CU87: 681864.78 | CV87: 681864.78 | CW87: -2047720.2 | DA87: 201372 | DB87: EBITDA (*)조정영업이익 기준 | DC87: 611.31641 | DD87: 666.32031 | DE87: 840.22744 | DF87: 812.03 | DG87: 846.187 | DH87: 797.36 | DI87: 983.249 | DJ87: 1285.147 | DK87: 1349.42 | DL87: 1179.466 | DM87: 1012.107 | DN87: 1043.921
C88: (분기비중) | D88: (Q Portion) | J88: 0 | K88: 0 | L88: 0 | M88: 0 | N88: 0 | O88: 0 | P88: 0 | Q88: 0 | R88: 0 | S88: 0 | T88: 0 | U88: 0 | V88: 0.20882927 | W88: 0.2581339 | X88: 0.33704907 | Y88: 0.19598776 | Z88: 0.19866058 | AA88: 0.21138235 | AB88: 0.28484838 | AC88: 0.30510868 | AD88: 0.25261488 | AE88: 0.28180496 | AF88: 0.28437845 | AG88: 0.18120172 | AH88: 0.21818685 | AI88: 0.32560013 | AJ88: 0.27732751 | AK88: 0.17888551 | AL88: 0.19112911 | AM88: 0.23387519 | AN88: 0.23896021 | AO88: 0.33603549 | AP88: 0.18661128 | AQ88: 0.23327504 | AR88: 0.23912273 | AS88: 0.34099094 | AT88: 0.23470113 | AU88: 0.28011066 | AV88: 0.27879142 | AW88: 0.20639679 | AX88: 0.26316091 | AY88: 0.26124807 | AZ88: 0.27580285 | BA88: 0.19978816 | BB88: 0.24088892 | BC88: 0.27561185 | BD88: 0.26855001 | BE88: 0.21494922 | BF88: 0.29116924 | BG88: 0.28232142 | BH88: 0.25530197 | BI88: 0.17120738 | BJ88: 0.26340398 | BK88: 0.20072648 | BL88: 0.27213907 | BM88: 0.26373047 | BN88: 0.27989189 | BO88: 0.29332549 | BP88: 0.26391007 | BQ88: 0.16287255 | BR88: 0.22710036 | BS88: 0.27984278 | BT88: 0.3076775 | BU88: 0.18537936 | BV88: -0.2903919 | BW88: -0.19494723 | BX88: -0.16372035 | BY88: 1.6490595 | BZ88: 1.7515665 | CA88: 1.7515665 | CB88: 1.7515665 | CC88: -4.2546994 | CD88: -4.0088318 | CE88: -4.0088318 | CF88: -4.0088318 | CG88: 13.026495 | CH88: 12.612167 | CI88: 12.612167 | CJ88: 12.612167 | CK88: -36.8365 | CL88: -36.111449 | CM88: -36.111449 | CN88: -36.111449 | CO88: 109.33435 | CP88: 108.03634 | CQ88: 108.03634 | CR88: 108.03634 | CS88: -323.10901 | CT88: -320.75069 | CU88: -320.75069 | CV88: -320.75069 | CW88: 963.25206
